Workbook

Sheet Dashboard
A1: Dashboard
A2: ="As of "&TEXT(Calc!$EB$34,"mmmm d, yyyy")&" · Next: fill "&TEXT(EDATE(DATE(YEAR(Calc!$EB$34),MONTH(Calc!$EB$34),1),IF(DAY(Calc!$EB$34+1)=1,1,0)),"mmmm yyyy")&" on Month-End once its statements are out"
A4: NET WORTH | D4: LIQUID CASH | G4: INVESTMENTS + RETIREMENT | J4: OWED ON CARDS & LOANS
A5: =Calc!$EB$6 | D5: =Calc!$EB$7 | G5: =Calc!$EB$10 | J5: =Calc!$EB$11
A7: =IF(Calc!$EB$38="","Starting point · opening "&TEXT(Calc!$EB$34,"m/d/yy"),IF(Calc!$EB$38>=0,"▲ ","▼ ")&TEXT(ABS(Calc!$EB$38),"$#,##0")&IF(Calc!$EB$37=0," since opening"," vs last month")) | D7: =IF(Calc!$EB$15<=0,"",TEXT(Calc!$EB$7/Calc!$EB$15,"0.0")&" months of living costs") | G7: ="Contributed "&TEXT(Calc!$EB$19,"$#,##0")&" this year" | J7: =IF(Calc!$EB$11=0,"Nothing owed",IF(Calc!$EB$5=0,"As of opening",IF(Calc!$EB$67<0,"▼ "&TEXT(ABS(Calc!$EB$67),"$#,##0")&IF(Calc!$EB$37=0," less than at opening"," less than last month"),IF(Calc!$EB$67>0,"▲ "&TEXT(Calc!$EB$67,"$#,##0")&IF(Calc!$EB$37=0," more than at opening"," more than last month"),IF(Calc!$EB$37=0,"Same as at opening","Same as last month")))))
A9: Money flow | F9: Health checks
B10: ="Latest month ("&Calc!$EB$35&")" | C10: ="Average (last "&Settings!$B$10&" full)" | D10: ="This year ("&YEAR(TODAY())&")" | F10: =Calc!$EA$95
A11: Income | B11: =IF(Calc!$EB$5=0,"",INDEX(Calc!$S:$S,Calc!$EB$5)) | C11: =Calc!$EB$12 | D11: =Calc!$EB$16 | F11: =Calc!$EA$96
A12: Household-paid living | B12: =IF(Calc!$EB$5=0,"",INDEX(Calc!$DD:$DD,Calc!$EB$5)) | C12: =Calc!$EB$13 | D12: =SUMIFS(Calc!$DD$6:$DD$183,Calc!$DO$6:$DO$183,YEAR(TODAY())) | F12: =Calc!$EA$97
A13: Family-paid living | B13: =IF(Calc!$EB$5=0,"",INDEX(Calc!$DE:$DE,Calc!$EB$5)) | C13: =Calc!$EB$14 | D13: =SUMIFS(Calc!$DE$6:$DE$183,Calc!$DO$6:$DO$183,YEAR(TODAY())) | F13: =Calc!$EA$98
A14: True cost of living | B14: =IF(Calc!$EB$5=0,"",INDEX(Calc!$DG:$DG,Calc!$EB$5)) | C14: =Calc!$EB$15 | D14: =SUMIFS(Calc!$DG$6:$DG$183,Calc!$DO$6:$DO$183,YEAR(TODAY())) | F14: =Calc!$EA$99
A15: …of which one-time | B15: =IF(Calc!$EB$5=0,"",INDEX(Calc!$DF:$DF,Calc!$EB$5)) | D15: =SUMIFS(Calc!$DF$6:$DF$183,Calc!$DO$6:$DO$183,YEAR(TODAY())) | F15: =Calc!$EA$100
A16: Tithe / charity given | B16: =IF(Calc!$EB$5=0,"",INDEX(Calc!$AA:$AA,Calc!$EB$5)) | C16: =Calc!$EB$25 | D16: =Calc!$EB$17 | F16: =Calc!$EA$101
A17: Invested | B17: =IF(Calc!$EB$5=0,"",INDEX(Calc!$AC:$AC,Calc!$EB$5)) | D17: =Calc!$EB$19 | F17: =Calc!$EA$102
A18: Saved (after giving) | B18: =IF(Calc!$EB$5=0,"",INDEX(Calc!$DK:$DK,Calc!$EB$5)) | D18: =Calc!$EB$21 | F18: =Calc!$EA$103
A20: TITHE BALANCE | B20: =Calc!$EB$24 | C20: ="This quarter: "&TEXT(Calc!$EB$23,"$#,##0")&" given of "&TEXT(Calc!$EB$22+0,"$#,##0")&" owed"
A22: Goals | I22: Accounts
A23: Goal | B23: Target | C23: Current | D23: Progress | E23: Remaining | F23: Status | G23: Note | I23: Account | J23: Type | K23: Value
A24: =IF(Calc!$EA$70="","",Calc!$EA$70) | B24: =IF(Calc!$EA$70="","",Calc!$ED$70) | C24: =IF(Calc!$EA$70="","",Calc!$EC$70) | D24: =IF(Calc!$EA$70="","",Calc!$EG$70) | E24: =IF(Calc!$EA$70="","",Calc!$EE$70) | F24: =IF(Calc!$EA$70="","",Calc!$EF$70) | G24: =IF(Calc!$EA$70="","",Calc!$EH$70) | I24: =IFERROR(INDEX(Calc!$EA$40:$EA$59,MATCH(1,Calc!$EI$40:$EI$59,0)),"") | J24: =IFERROR(INDEX(Calc!$EJ$40:$EJ$59,MATCH(1,Calc!$EI$40:$EI$59,0)),"") | K24: =IFERROR(INDEX(Calc!$EL$40:$EL$59,MATCH(1,Calc!$EI$40:$EI$59,0)),"") | L24: =IFERROR(INDEX(Calc!$EM$40:$EM$59,MATCH(1,Calc!$EI$40:$EI$59,0)),"")
A25: =IF(Calc!$EA$71="","",Calc!$EA$71) | B25: =IF(Calc!$EA$71="","",Calc!$ED$71) | C25: =IF(Calc!$EA$71="","",Calc!$EC$71) | D25: =IF(Calc!$EA$71="","",Calc!$EG$71) | E25: =IF(Calc!$EA$71="","",Calc!$EE$71) | F25: =IF(Calc!$EA$71="","",Calc!$EF$71) | G25: =IF(Calc!$EA$71="","",Calc!$EH$71) | I25: =IFERROR(INDEX(Calc!$EA$40:$EA$59,MATCH(2,Calc!$EI$40:$EI$59,0)),"") | J25: =IFERROR(INDEX(Calc!$EJ$40:$EJ$59,MATCH(2,Calc!$EI$40:$EI$59,0)),"") | K25: =IFERROR(INDEX(Calc!$EL$40:$EL$59,MATCH(2,Calc!$EI$40:$EI$59,0)),"") | L25: =IFERROR(INDEX(Calc!$EM$40:$EM$59,MATCH(2,Calc!$EI$40:$EI$59,0)),"")
A26: =IF(Calc!$EA$72="","",Calc!$EA$72) | B26: =IF(Calc!$EA$72="","",Calc!$ED$72) | C26: =IF(Calc!$EA$72="","",Calc!$EC$72) | D26: =IF(Calc!$EA$72="","",Calc!$EG$72) | E26: =IF(Calc!$EA$72="","",Calc!$EE$72) | F26: =IF(Calc!$EA$72="","",Calc!$EF$72) | G26: =IF(Calc!$EA$72="","",Calc!$EH$72) | I26: =IFERROR(INDEX(Calc!$EA$40:$EA$59,MATCH(3,Calc!$EI$40:$EI$59,0)),"") | J26: =IFERROR(INDEX(Calc!$EJ$40:$EJ$59,MATCH(3,Calc!$EI$40:$EI$59,0)),"") | K26: =IFERROR(INDEX(Calc!$EL$40:$EL$59,MATCH(3,Calc!$EI$40:$EI$59,0)),"") | L26: =IFERROR(INDEX(Calc!$EM$40:$EM$59,MATCH(3,Calc!$EI$40:$EI$59,0)),"")
A27: =IF(Calc!$EA$73="","",Calc!$EA$73) | B27: =IF(Calc!$EA$73="","",Calc!$ED$73) | C27: =IF(Calc!$EA$73="","",Calc!$EC$73) | D27: =IF(Calc!$EA$73="","",Calc!$EG$73) | E27: =IF(Calc!$EA$73="","",Calc!$EE$73) | F27: =IF(Calc!$EA$73="","",Calc!$EF$73) | G27: =IF(Calc!$EA$73="","",Calc!$EH$73) | I27: =IFERROR(INDEX(Calc!$EA$40:$EA$59,MATCH(4,Calc!$EI$40:$EI$59,0)),"") | J27: =IFERROR(INDEX(Calc!$EJ$40:$EJ$59,MATCH(4,Calc!$EI$40:$EI$59,0)),"") | K27: =IFERROR(INDEX(Calc!$EL$40:$EL$59,MATCH(4,Calc!$EI$40:$EI$59,0)),"") | L27: =IFERROR(INDEX(Calc!$EM$40:$EM$59,MATCH(4,Calc!$EI$40:$EI$59,0)),"")
A28: =IF(Calc!$EA$74="","",Calc!$EA$74) | B28: =IF(Calc!$EA$74="","",Calc!$ED$74) | C28: =IF(Calc!$EA$74="","",Calc!$EC$74) | D28: =IF(Calc!$EA$74="","",Calc!$EG$74) | E28: =IF(Calc!$EA$74="","",Calc!$EE$74) | F28: =IF(Calc!$EA$74="","",Calc!$EF$74) | G28: =IF(Calc!$EA$74="","",Calc!$EH$74) | I28: =IFERROR(INDEX(Calc!$EA$40:$EA$59,MATCH(5,Calc!$EI$40:$EI$59,0)),"") | J28: =IFERROR(INDEX(Calc!$EJ$40:$EJ$59,MATCH(5,Calc!$EI$40:$EI$59,0)),"") | K28: =IFERROR(INDEX(Calc!$EL$40:$EL$59,MATCH(5,Calc!$EI$40:$EI$59,0)),"") | L28: =IFERROR(INDEX(Calc!$EM$40:$EM$59,MATCH(5,Calc!$EI$40:$EI$59,0)),"")
A29: =IF(Calc!$EA$75="","",Calc!$EA$75) | B29: =IF(Calc!$EA$75="","",Calc!$ED$75) | C29: =IF(Calc!$EA$75="","",Calc!$EC$75) | D29: =IF(Calc!$EA$75="","",Calc!$EG$75) | E29: =IF(Calc!$EA$75="","",Calc!$EE$75) | F29: =IF(Calc!$EA$75="","",Calc!$EF$75) | G29: =IF(Calc!$EA$75="","",Calc!$EH$75) | I29: =IFERROR(INDEX(Calc!$EA$40:$EA$59,MATCH(6,Calc!$EI$40:$EI$59,0)),"") | J29: =IFERROR(INDEX(Calc!$EJ$40:$EJ$59,MATCH(6,Calc!$EI$40:$EI$59,0)),"") | K29: =IFERROR(INDEX(Calc!$EL$40:$EL$59,MATCH(6,Calc!$EI$40:$EI$59,0)),"") | L29: =IFERROR(INDEX(Calc!$EM$40:$EM$59,MATCH(6,Calc!$EI$40:$EI$59,0)),"")
A30: =IF(Calc!$EA$76="","",Calc!$EA$76) | B30: =IF(Calc!$EA$76="","",Calc!$ED$76) | C30: =IF(Calc!$EA$76="","",Calc!$EC$76) | D30: =IF(Calc!$EA$76="","",Calc!$EG$76) | E30: =IF(Calc!$EA$76="","",Calc!$EE$76) | F30: =IF(Calc!$EA$76="","",Calc!$EF$76) | G30: =IF(Calc!$EA$76="","",Calc!$EH$76) | I30: =IFERROR(INDEX(Calc!$EA$40:$EA$59,MATCH(7,Calc!$EI$40:$EI$59,0)),"") | J30: =IFERROR(INDEX(Calc!$EJ$40:$EJ$59,MATCH(7,Calc!$EI$40:$EI$59,0)),"") | K30: =IFERROR(INDEX(Calc!$EL$40:$EL$59,MATCH(7,Calc!$EI$40:$EI$59,0)),"") | L30: =IFERROR(INDEX(Calc!$EM$40:$EM$59,MATCH(7,Calc!$EI$40:$EI$59,0)),"")
A31: =IF(Calc!$EA$77="","",Calc!$EA$77) | B31: =IF(Calc!$EA$77="","",Calc!$ED$77) | C31: =IF(Calc!$EA$77="","",Calc!$EC$77) | D31: =IF(Calc!$EA$77="","",Calc!$EG$77) | E31: =IF(Calc!$EA$77="","",Calc!$EE$77) | F31: =IF(Calc!$EA$77="","",Calc!$EF$77) | G31: =IF(Calc!$EA$77="","",Calc!$EH$77) | I31: =IFERROR(INDEX(Calc!$EA$40:$EA$59,MATCH(8,Calc!$EI$40:$EI$59,0)),"") | J31: =IFERROR(INDEX(Calc!$EJ$40:$EJ$59,MATCH(8,Calc!$EI$40:$EI$59,0)),"") | K31: =IFERROR(INDEX(Calc!$EL$40:$EL$59,MATCH(8,Calc!$EI$40:$EI$59,0)),"") | L31: =IFERROR(INDEX(Calc!$EM$40:$EM$59,MATCH(8,Calc!$EI$40:$EI$59,0)),"")
A32: =IF(Calc!$EA$78="","",Calc!$EA$78) | B32: =IF(Calc!$EA$78="","",Calc!$ED$78) | C32: =IF(Calc!$EA$78="","",Calc!$EC$78) | D32: =IF(Calc!$EA$78="","",Calc!$EG$78) | E32: =IF(Calc!$EA$78="","",Calc!$EE$78) | F32: =IF(Calc!$EA$78="","",Calc!$EF$78) | G32: =IF(Calc!$EA$78="","",Calc!$EH$78) | I32: =IFERROR(INDEX(Calc!$EA$40:$EA$59,MATCH(9,Calc!$EI$40:$EI$59,0)),"") | J32: =IFERROR(INDEX(Calc!$EJ$40:$EJ$59,MATCH(9,Calc!$EI$40:$EI$59,0)),"") | K32: =IFERROR(INDEX(Calc!$EL$40:$EL$59,MATCH(9,Calc!$EI$40:$EI$59,0)),"") | L32: =IFERROR(INDEX(Calc!$EM$40:$EM$59,MATCH(9,Calc!$EI$40:$EI$59,0)),"")
A33: =IF(Calc!$EA$79="","",Calc!$EA$79) | B33: =IF(Calc!$EA$79="","",Calc!$ED$79) | C33: =IF(Calc!$EA$79="","",Calc!$EC$79) | D33: =IF(Calc!$EA$79="","",Calc!$EG$79) | E33: =IF(Calc!$EA$79="","",Calc!$EE$79) | F33: =IF(Calc!$EA$79="","",Calc!$EF$79) | G33: =IF(Calc!$EA$79="","",Calc!$EH$79) | I33: =IFERROR(INDEX(Calc!$EA$40:$EA$59,MATCH(10,Calc!$EI$40:$EI$59,0)),"") | J33: =IFERROR(INDEX(Calc!$EJ$40:$EJ$59,MATCH(10,Calc!$EI$40:$EI$59,0)),"") | K33: =IFERROR(INDEX(Calc!$EL$40:$EL$59,MATCH(10,Calc!$EI$40:$EI$59,0)),"") | L33: =IFERROR(INDEX(Calc!$EM$40:$EM$59,MATCH(10,Calc!$EI$40:$EI$59,0)),"")
A34: =IF(Calc!$EA$80="","",Calc!$EA$80) | B34: =IF(Calc!$EA$80="","",Calc!$ED$80) | C34: =IF(Calc!$EA$80="","",Calc!$EC$80) | D34: =IF(Calc!$EA$80="","",Calc!$EG$80) | E34: =IF(Calc!$EA$80="","",Calc!$EE$80) | F34: =IF(Calc!$EA$80="","",Calc!$EF$80) | G34: =IF(Calc!$EA$80="","",Calc!$EH$80) | I34: =IFERROR(INDEX(Calc!$EA$40:$EA$59,MATCH(11,Calc!$EI$40:$EI$59,0)),"") | J34: =IFERROR(INDEX(Calc!$EJ$40:$EJ$59,MATCH(11,Calc!$EI$40:$EI$59,0)),"") | K34: =IFERROR(INDEX(Calc!$EL$40:$EL$59,MATCH(11,Calc!$EI$40:$EI$59,0)),"") | L34: =IFERROR(INDEX(Calc!$EM$40:$EM$59,MATCH(11,Calc!$EI$40:$EI$59,0)),"")
A35: =IF(Calc!$EA$81="","",Calc!$EA$81) | B35: =IF(Calc!$EA$81="","",Calc!$ED$81) | C35: =IF(Calc!$EA$81="","",Calc!$EC$81) | D35: =IF(Calc!$EA$81="","",Calc!$EG$81) | E35: =IF(Calc!$EA$81="","",Calc!$EE$81) | F35: =IF(Calc!$EA$81="","",Calc!$EF$81) | G35: =IF(Calc!$EA$81="","",Calc!$EH$81) | I35: =IFERROR(INDEX(Calc!$EA$40:$EA$59,MATCH(12,Calc!$EI$40:$EI$59,0)),"") | J35: =IFERROR(INDEX(Calc!$EJ$40:$EJ$59,MATCH(12,Calc!$EI$40:$EI$59,0)),"") | K35: =IFERROR(INDEX(Calc!$EL$40:$EL$59,MATCH(12,Calc!$EI$40:$EI$59,0)),"") | L35: =IFERROR(INDEX(Calc!$EM$40:$EM$59,MATCH(12,Calc!$EI$40:$EI$59,0)),"")
A36: =IF(Calc!$EA$82="","",Calc!$EA$82) | B36: =IF(Calc!$EA$82="","",Calc!$ED$82) | C36: =IF(Calc!$EA$82="","",Calc!$EC$82) | D36: =IF(Calc!$EA$82="","",Calc!$EG$82) | E36: =IF(Calc!$EA$82="","",Calc!$EE$82) | F36: =IF(Calc!$EA$82="","",Calc!$EF$82) | G36: =IF(Calc!$EA$82="","",Calc!$EH$82) | I36: =IFERROR(INDEX(Calc!$EA$40:$EA$59,MATCH(13,Calc!$EI$40:$EI$59,0)),"") | J36: =IFERROR(INDEX(Calc!$EJ$40:$EJ$59,MATCH(13,Calc!$EI$40:$EI$59,0)),"") | K36: =IFERROR(INDEX(Calc!$EL$40:$EL$59,MATCH(13,Calc!$EI$40:$EI$59,0)),"") | L36: =IFERROR(INDEX(Calc!$EM$40:$EM$59,MATCH(13,Calc!$EI$40:$EI$59,0)),"")
A37: =IF(Calc!$EA$83="","",Calc!$EA$83) | B37: =IF(Calc!$EA$83="","",Calc!$ED$83) | C37: =IF(Calc!$EA$83="","",Calc!$EC$83) | D37: =IF(Calc!$EA$83="","",Calc!$EG$83) | E37: =IF(Calc!$EA$83="","",Calc!$EE$83) | F37: =IF(Calc!$EA$83="","",Calc!$EF$83) | G37: =IF(Calc!$EA$83="","",Calc!$EH$83) | I37: =IFERROR(INDEX(Calc!$EA$40:$EA$59,MATCH(14,Calc!$EI$40:$EI$59,0)),"") | J37: =IFERROR(INDEX(Calc!$EJ$40:$EJ$59,MATCH(14,Calc!$EI$40:$EI$59,0)),"") | K37: =IFERROR(INDEX(Calc!$EL$40:$EL$59,MATCH(14,Calc!$EI$40:$EI$59,0)),"") | L37: =IFERROR(INDEX(Calc!$EM$40:$EM$59,MATCH(14,Calc!$EI$40:$EI$59,0)),"")
A38: =IF(Calc!$EA$84="","",Calc!$EA$84) | B38: =IF(Calc!$EA$84="","",Calc!$ED$84) | C38: =IF(Calc!$EA$84="","",Calc!$EC$84) | D38: =IF(Calc!$EA$84="","",Calc!$EG$84) | E38: =IF(Calc!$EA$84="","",Calc!$EE$84) | F38: =IF(Calc!$EA$84="","",Calc!$EF$84) | G38: =IF(Calc!$EA$84="","",Calc!$EH$84) | I38: =IFERROR(INDEX(Calc!$EA$40:$EA$59,MATCH(15,Calc!$EI$40:$EI$59,0)),"") | J38: =IFERROR(INDEX(Calc!$EJ$40:$EJ$59,MATCH(15,Calc!$EI$40:$EI$59,0)),"") | K38: =IFERROR(INDEX(Calc!$EL$40:$EL$59,MATCH(15,Calc!$EI$40:$EI$59,0)),"") | L38: =IFERROR(INDEX(Calc!$EM$40:$EM$59,MATCH(15,Calc!$EI$40:$EI$59,0)),"")
A39: =IF(Calc!$EA$85="","",Calc!$EA$85) | B39: =IF(Calc!$EA$85="","",Calc!$ED$85) | C39: =IF(Calc!$EA$85="","",Calc!$EC$85) | D39: =IF(Calc!$EA$85="","",Calc!$EG$85) | E39: =IF(Calc!$EA$85="","",Calc!$EE$85) | F39: =IF(Calc!$EA$85="","",Calc!$EF$85) | G39: =IF(Calc!$EA$85="","",Calc!$EH$85) | I39: =IFERROR(INDEX(Calc!$EA$40:$EA$59,MATCH(16,Calc!$EI$40:$EI$59,0)),"") | J39: =IFERROR(INDEX(Calc!$EJ$40:$EJ$59,MATCH(16,Calc!$EI$40:$EI$59,0)),"") | K39: =IFERROR(INDEX(Calc!$EL$40:$EL$59,MATCH(16,Calc!$EI$40:$EI$59,0)),"") | L39: =IFERROR(INDEX(Calc!$EM$40:$EM$59,MATCH(16,Calc!$EI$40:$EI$59,0)),"")
A40: =IF(Calc!$EA$86="","",Calc!$EA$86) | B40: =IF(Calc!$EA$86="","",Calc!$ED$86) | C40: =IF(Calc!$EA$86="","",Calc!$EC$86) | D40: =IF(Calc!$EA$86="","",Calc!$EG$86) | E40: =IF(Calc!$EA$86="","",Calc!$EE$86) | F40: =IF(Calc!$EA$86="","",Calc!$EF$86) | G40: =IF(Calc!$EA$86="","",Calc!$EH$86) | I40: =IFERROR(INDEX(Calc!$EA$40:$EA$59,MATCH(17,Calc!$EI$40:$EI$59,0)),"") | J40: =IFERROR(INDEX(Calc!$EJ$40:$EJ$59,MATCH(17,Calc!$EI$40:$EI$59,0)),"") | K40: =IFERROR(INDEX(Calc!$EL$40:$EL$59,MATCH(17,Calc!$EI$40:$EI$59,0)),"") | L40: =IFERROR(INDEX(Calc!$EM$40:$EM$59,MATCH(17,Calc!$EI$40:$EI$59,0)),"")
A41: =IF(Calc!$EA$87="","",Calc!$EA$87) | B41: =IF(Calc!$EA$87="","",Calc!$ED$87) | C41: =IF(Calc!$EA$87="","",Calc!$EC$87) | D41: =IF(Calc!$EA$87="","",Calc!$EG$87) | E41: =IF(Calc!$EA$87="","",Calc!$EE$87) | F41: =IF(Calc!$EA$87="","",Calc!$EF$87) | G41: =IF(Calc!$EA$87="","",Calc!$EH$87) | I41: =IFERROR(INDEX(Calc!$EA$40:$EA$59,MATCH(18,Calc!$EI$40:$EI$59,0)),"") | J41: =IFERROR(INDEX(Calc!$EJ$40:$EJ$59,MATCH(18,Calc!$EI$40:$EI$59,0)),"") | K41: =IFERROR(INDEX(Calc!$EL$40:$EL$59,MATCH(18,Calc!$EI$40:$EI$59,0)),"") | L41: =IFERROR(INDEX(Calc!$EM$40:$EM$59,MATCH(18,Calc!$EI$40:$EI$59,0)),"")
A42: =IF(Calc!$EA$88="","",Calc!$EA$88) | B42: =IF(Calc!$EA$88="","",Calc!$ED$88) | C42: =IF(Calc!$EA$88="","",Calc!$EC$88) | D42: =IF(Calc!$EA$88="","",Calc!$EG$88) | E42: =IF(Calc!$EA$88="","",Calc!$EE$88) | F42: =IF(Calc!$EA$88="","",Calc!$EF$88) | G42: =IF(Calc!$EA$88="","",Calc!$EH$88) | I42: =IFERROR(INDEX(Calc!$EA$40:$EA$59,MATCH(19,Calc!$EI$40:$EI$59,0)),"") | J42: =IFERROR(INDEX(Calc!$EJ$40:$EJ$59,MATCH(19,Calc!$EI$40:$EI$59,0)),"") | K42: =IFERROR(INDEX(Calc!$EL$40:$EL$59,MATCH(19,Calc!$EI$40:$EI$59,0)),"") | L42: =IFERROR(INDEX(Calc!$EM$40:$EM$59,MATCH(19,Calc!$EI$40:$EI$59,0)),"")
A43: =IF(Calc!$EA$89="","",Calc!$EA$89) | B43: =IF(Calc!$EA$89="","",Calc!$ED$89) | C43: =IF(Calc!$EA$89="","",Calc!$EC$89) | D43: =IF(Calc!$EA$89="","",Calc!$EG$89) | E43: =IF(Calc!$EA$89="","",Calc!$EE$89) | F43: =IF(Calc!$EA$89="","",Calc!$EF$89) | G43: =IF(Calc!$EA$89="","",Calc!$EH$89) | I43: =IFERROR(INDEX(Calc!$EA$40:$EA$59,MATCH(20,Calc!$EI$40:$EI$59,0)),"") | J43: =IFERROR(INDEX(Calc!$EJ$40:$EJ$59,MATCH(20,Calc!$EI$40:$EI$59,0)),"") | K43: =IFERROR(INDEX(Calc!$EL$40:$EL$59,MATCH(20,Calc!$EI$40:$EI$59,0)),"") | L43: =IFERROR(INDEX(Calc!$EM$40:$EM$59,MATCH(20,Calc!$EI$40:$EI$59,0)),"")
I44: ="Values as of "&TEXT(Calc!$EB$34,"m/d/yy")
A46: Tax this year
A47: Taxable income received | B47: =Calc!$EB$62 | C47: Amounts received: for pay with tax withheld this is take-home pay, not the gross on a W-2
A48: …of which no tax withheld | B48: =Calc!$EB$63 | C48: Sources marked Taxable = Yes and Tax withheld = No (Settings)
A49: Tax-deductible giving | B49: =Calc!$EB$64 | C49: Giving rows and recurring donations marked Tax-deductible = Yes

Sheet Month-End
A1: Month-End
A2: One column a month, top to bottom. Early each month, fill LAST month’s column from the statements, in this order: 1 the blue “REQUIRED” balances, 2 income, 3 costs. Grey numbers are filled in for you (regular pay, unchanged balances) — type over one to change that month only. Section 5 shows the results. This month’s column is highlighted blue.
A4: Month | B4: How to fill | C4: 46082 | D4: 46113 | E4: 46143 | F4: 46174 | G4: 46204 | H4: 46235 | I4: 46266 | J4: 46296 | K4: 46327 | L4: 46357 | M4: 46388 | N4: 46419 | O4: 46447 | P4: 46478 | Q4: 46508 | R4: 46539 | S4: 46569 | T4: 46600 | U4: 46631 | V4: 46661 | W4: 46692 | X4: 46722 | Y4: 46753 | Z4: 46784 | AA4: 46813 | AB4: 46844 | AC4: 46874 | AD4: 46905 | AE4: 46935 | AF4: 46966 | AG4: 46997 | AH4: 47027 | AI4: 47058 | AJ4: 47088 | AK4: 47119 | AL4: 47150 | AM4: 47178 | AN4: 47209 | AO4: 47239 | AP4: 47270 | AQ4: 47300 | AR4: 47331 | AS4: 47362 | AT4: 47392 | AU4: 47423 | AV4: 47453 | AW4: 47484 | AX4: 47515 | AY4: 47543 | AZ4: 47574 | BA4: 47604 | BB4: 47635 | BC4: 47665 | BD4: 47696 | BE4: 47727 | BF4: 47757 | BG4: 47788 | BH4: 47818 | BI4: 47849 | BJ4: 47880 | BK4: 47908 | BL4: 47939 | BM4: 47969 | BN4: 48000 | BO4: 48030 | BP4: 48061 | BQ4: 48092 | BR4: 48122 | BS4: 48153 | BT4: 48183 | BU4: 48214 | BV4: 48245 | BW4: 48274 | BX4: 48305 | BY4: 48335 | BZ4: 48366 | CA4: 48396 | CB4: 48427 | CC4: 48458 | CD4: 48488 | CE4: 48519 | CF4: 48549 | CG4: 48580 | CH4: 48611 | CI4: 48639 | CJ4: 48670 | CK4: 48700 | CL4: 48731 | CM4: 48761 | CN4: 48792 | CO4: 48823 | CP4: 48853 | CQ4: 48884 | CR4: 48914 | CS4: 48945 | CT4: 48976 | CU4: 49004 | CV4: 49035 | CW4: 49065 | CX4: 49096 | CY4: 49126 | CZ4: 49157 | DA4: 49188 | DB4: 49218 | DC4: 49249 | DD4: 49279 | DE4: 49310 | DF4: 49341 | DG4: 49369 | DH4: 49400 | DI4: 49430 | DJ4: 49461 | DK4: 49491 | DL4: 49522 | DM4: 49553 | DN4: 49583 | DO4: 49614 | DP4: 49644 | DQ4: 49675 | DR4: 49706 | DS4: 49735 | DT4: 49766 | DU4: 49796 | DV4: 49827 | DW4: 49857 | DX4: 49888 | DY4: 49919 | DZ4: 49949 | EA4: 49980 | EB4: 50010 | EC4: 50041 | ED4: 50072 | EE4: 50100 | EF4: 50131 | EG4: 50161 | EH4: 50192 | EI4: 50222 | EJ4: 50253 | EK4: 50284 | EL4: 50314 | EM4: 50345 | EN4: 50375 | EO4: 50406 | EP4: 50437 | EQ4: 50465 | ER4: 50496 | ES4: 50526 | ET4: 50557 | EU4: 50587 | EV4: 50618 | EW4: 50649 | EX4: 50679 | EY4: 50710 | EZ4: 50740 | FA4: 50771 | FB4: 50802 | FC4: 50830 | FD4: 50861 | FE4: 50891 | FF4: 50922 | FG4: 50952 | FH4: 50983 | FI4: 51014 | FJ4: 51044 | FK4: 51075 | FL4: 51105 | FM4: 51136 | FN4: 51167 | FO4: 51196 | FP4: 51227 | FQ4: 51257 | FR4: 51288 | FS4: 51318 | FT4: 51349 | FU4: 51380 | FV4: 51410 | FW4: 51441 | FX4: 51471
A5: Status | C5: =Calc!$DN$6 | D5: =Calc!$DN$7 | E5: =Calc!$DN$8 | F5: =Calc!$DN$9 | G5: =Calc!$DN$10 | H5: =Calc!$DN$11 | I5: =Calc!$DN$12 | J5: =Calc!$DN$13 | K5: =Calc!$DN$14 | L5: =Calc!$DN$15 | M5: =Calc!$DN$16 | N5: =Calc!$DN$17 | O5: =Calc!$DN$18 | P5: =Calc!$DN$19 | Q5: =Calc!$DN$20 | R5: =Calc!$DN$21 | S5: =Calc!$DN$22 | T5: =Calc!$DN$23 | U5: =Calc!$DN$24 | V5: =Calc!$DN$25 | W5: =Calc!$DN$26 | X5: =Calc!$DN$27 | Y5: =Calc!$DN$28 | Z5: =Calc!$DN$29 | AA5: =Calc!$DN$30 | AB5: =Calc!$DN$31 | AC5: =Calc!$DN$32 | AD5: =Calc!$DN$33 | AE5: =Calc!$DN$34 | AF5: =Calc!$DN$35 | AG5: =Calc!$DN$36 | AH5: =Calc!$DN$37 | AI5: =Calc!$DN$38 | AJ5: =Calc!$DN$39 | AK5: =Calc!$DN$40 | AL5: =Calc!$DN$41 | AM5: =Calc!$DN$42 | AN5: =Calc!$DN$43 | AO5: =Calc!$DN$44 | AP5: =Calc!$DN$45 | AQ5: =Calc!$DN$46 | AR5: =Calc!$DN$47 | AS5: =Calc!$DN$48 | AT5: =Calc!$DN$49 | AU5: =Calc!$DN$50 | AV5: =Calc!$DN$51 | AW5: =Calc!$DN$52 | AX5: =Calc!$DN$53 | AY5: =Calc!$DN$54 | AZ5: =Calc!$DN$55 | BA5: =Calc!$DN$56 | BB5: =Calc!$DN$57 | BC5: =Calc!$DN$58 | BD5: =Calc!$DN$59 | BE5: =Calc!$DN$60 | BF5: =Calc!$DN$61 | BG5: =Calc!$DN$62 | BH5: =Calc!$DN$63 | BI5: =Calc!$DN$64 | BJ5: =Calc!$DN$65 | BK5: =Calc!$DN$66 | BL5: =Calc!$DN$67 | BM5: =Calc!$DN$68 | BN5: =Calc!$DN$69 | BO5: =Calc!$DN$70 | BP5: =Calc!$DN$71 | BQ5: =Calc!$DN$72 | BR5: =Calc!$DN$73 | BS5: =Calc!$DN$74 | BT5: =Calc!$DN$75 | BU5: =Calc!$DN$76 | BV5: =Calc!$DN$77 | BW5: =Calc!$DN$78 | BX5: =Calc!$DN$79 | BY5: =Calc!$DN$80 | BZ5: =Calc!$DN$81 | CA5: =Calc!$DN$82 | CB5: =Calc!$DN$83 | CC5: =Calc!$DN$84 | CD5: =Calc!$DN$85 | CE5: =Calc!$DN$86 | CF5: =Calc!$DN$87 | CG5: =Calc!$DN$88 | CH5: =Calc!$DN$89 | CI5: =Calc!$DN$90 | CJ5: =Calc!$DN$91 | CK5: =Calc!$DN$92 | CL5: =Calc!$DN$93 | CM5: =Calc!$DN$94 | CN5: =Calc!$DN$95 | CO5: =Calc!$DN$96 | CP5: =Calc!$DN$97 | CQ5: =Calc!$DN$98 | CR5: =Calc!$DN$99 | CS5: =Calc!$DN$100 | CT5: =Calc!$DN$101 | CU5: =Calc!$DN$102 | CV5: =Calc!$DN$103 | CW5: =Calc!$DN$104 | CX5: =Calc!$DN$105 | CY5: =Calc!$DN$106 | CZ5: =Calc!$DN$107 | DA5: =Calc!$DN$108 | DB5: =Calc!$DN$109 | DC5: =Calc!$DN$110 | DD5: =Calc!$DN$111 | DE5: =Calc!$DN$112 | DF5: =Calc!$DN$113 | DG5: =Calc!$DN$114 | DH5: =Calc!$DN$115 | DI5: =Calc!$DN$116 | DJ5: =Calc!$DN$117 | DK5: =Calc!$DN$118 | DL5: =Calc!$DN$119 | DM5: =Calc!$DN$120 | DN5: =Calc!$DN$121 | DO5: =Calc!$DN$122 | DP5: =Calc!$DN$123 | DQ5: =Calc!$DN$124 | DR5: =Calc!$DN$125 | DS5: =Calc!$DN$126 | DT5: =Calc!$DN$127 | DU5: =Calc!$DN$128 | DV5: =Calc!$DN$129 | DW5: =Calc!$DN$130 | DX5: =Calc!$DN$131 | DY5: =Calc!$DN$132 | DZ5: =Calc!$DN$133 | EA5: =Calc!$DN$134 | EB5: =Calc!$DN$135 | EC5: =Calc!$DN$136 | ED5: =Calc!$DN$137 | EE5: =Calc!$DN$138 | EF5: =Calc!$DN$139 | EG5: =Calc!$DN$140 | EH5: =Calc!$DN$141 | EI5: =Calc!$DN$142 | EJ5: =Calc!$DN$143 | EK5: =Calc!$DN$144 | EL5: =Calc!$DN$145 | EM5: =Calc!$DN$146 | EN5: =Calc!$DN$147 | EO5: =Calc!$DN$148 | EP5: =Calc!$DN$149 | EQ5: =Calc!$DN$150 | ER5: =Calc!$DN$151 | ES5: =Calc!$DN$152 | ET5: =Calc!$DN$153 | EU5: =Calc!$DN$154 | EV5: =Calc!$DN$155 | EW5: =Calc!$DN$156 | EX5: =Calc!$DN$157 | EY5: =Calc!$DN$158 | EZ5: =Calc!$DN$159 | FA5: =Calc!$DN$160 | FB5: =Calc!$DN$161 | FC5: =Calc!$DN$162 | FD5: =Calc!$DN$163 | FE5: =Calc!$DN$164 | FF5: =Calc!$DN$165 | FG5: =Calc!$DN$166 | FH5: =Calc!$DN$167 | FI5: =Calc!$DN$168 | FJ5: =Calc!$DN$169 | FK5: =Calc!$DN$170 | FL5: =Calc!$DN$171 | FM5: =Calc!$DN$172 | FN5: =Calc!$DN$173 | FO5: =Calc!$DN$174 | FP5: =Calc!$DN$175 | FQ5: =Calc!$DN$176 | FR5: =Calc!$DN$177 | FS5: =Calc!$DN$178 | FT5: =Calc!$DN$179 | FU5: =Calc!$DN$180 | FV5: =Calc!$DN$181 | FW5: =Calc!$DN$182 | FX5: =Calc!$DN$183
A6: 1 · Month-end balances — bank, cash, cards (cards: amount owed)
A7: =IF(Settings!$A$19="","(unused)",Settings!$A$19&IF(Settings!$E$19="No"," (retired)","")) | B7: =IF(Settings!$A$19="","",IF(Settings!$F$19="Yes","REQUIRED","optional · grey = unchanged")&IF(OR(Settings!$B$19="Card",Settings!$B$19="Loan")," · amount owed","")) | C7: =IF(OR(Settings!$A$19="",Settings!$F$19="Yes",OR(EOMONTH(C$4,0)<=Settings!$B$5,C$4>TODAY())),"",N(Settings!$C$19)) | D7: =IF(OR(Settings!$A$19="",Settings!$F$19="Yes",OR(EOMONTH(D$4,0)<=Settings!$B$5,D$4>TODAY())),"",IF(EOMONTH(C$4,0)<=Settings!$B$5,N(Settings!$C$19),N(Calc!$AE$6))) | E7: =IF(OR(Settings!$A$19="",Settings!$F$19="Yes",OR(EOMONTH(E$4,0)<=Settings!$B$5,E$4>TODAY())),"",IF(EOMONTH(D$4,0)<=Settings!$B$5,N(Settings!$C$19),N(Calc!$AE$7))) | F7: =IF(OR(Settings!$A$19="",Settings!$F$19="Yes",OR(EOMONTH(F$4,0)<=Settings!$B$5,F$4>TODAY())),"",IF(EOMONTH(E$4,0)<=Settings!$B$5,N(Settings!$C$19),N(Calc!$AE$8))) | G7: =IF(OR(Settings!$A$19="",Settings!$F$19="Yes",OR(EOMONTH(G$4,0)<=Settings!$B$5,G$4>TODAY())),"",IF(EOMONTH(F$4,0)<=Settings!$B$5,N(Settings!$C$19),N(Calc!$AE$9))) | H7: =IF(OR(Settings!$A$19="",Settings!$F$19="Yes",OR(EOMONTH(H$4,0)<=Settings!$B$5,H$4>TODAY())),"",IF(EOMONTH(G$4,0)<=Settings!$B$5,N(Settings!$C$19),N(Calc!$AE$10))) | I7: =IF(OR(Settings!$A$19="",Settings!$F$19="Yes",OR(EOMONTH(I$4,0)<=Settings!$B$5,I$4>TODAY())),"",IF(EOMONTH(H$4,0)<=Settings!$B$5,N(Settings!$C$19),N(Calc!$AE$11))) | J7: =IF(OR(Settings!$A$19="",Settings!$F$19="Yes",OR(EOMONTH(J$4,0)<=Settings!$B$5,J$4>TODAY())),"",IF(EOMONTH(I$4,0)<=Settings!$B$5,N(Settings!$C$19),N(Calc!$AE$12))) | K7: =IF(OR(Settings!$A$19="",Settings!$F$19="Yes",OR(EOMONTH(K$4,0)<=Settings!$B$5,K$4>TODAY())),"",IF(EOMONTH(J$4,0)<=Settings!$B$5,N(Settings!$C$19),N(Calc!$AE$13))) | L7: =IF(OR(Settings!$A$19="",Settings!$F$19="Yes",OR(EOMONTH(L$4,0)<=Settings!$B$5,L$4>TODAY())),"",IF(EOMONTH(K$4,0)<=Settings!$B$5,N(Settings!$C$19),N(Calc!$AE$14))) | M7: =IF(OR(Settings!$A$19="",Settings!$F$19="Yes",OR(EOMONTH(M$4,0)<=Settings!$B$5,M$4>TODAY())),"",IF(EOMONTH(L$4,0)<=Settings!$B$5,N(Settings!$C$19),N(Calc!$AE$15))) | N7: =IF(OR(Settings!$A$19="",Settings!$F$19="Yes",OR(EOMONTH(N$4,0)<=Settings!$B$5,N$4>TODAY())),"",IF(EOMONTH(M$4,0)<=Settings!$B$5,N(Settings!$C$19),N(Calc!$AE$16))) | O7: =IF(OR(Settings!$A$19="",Settings!$F$19="Yes",OR(EOMONTH(O$4,0)<=Settings!$B$5,O$4>TODAY())),"",IF(EOMONTH(N$4,0)<=Settings!$B$5,N(Settings!$C$19),N(Calc!$AE$17))) | P7: =IF(OR(Settings!$A$19="",Settings!$F$19="Yes",OR(EOMONTH(P$4,0)<=Settings!$B$5,P$4>TODAY())),"",IF(EOMONTH(O$4,0)<=Settings!$B$5,N(Settings!$C$19),N(Calc!$AE$18))) | Q7: =IF(OR(Settings!$A$19="",Settings!$F$19="Yes",OR(EOMONTH(Q$4,0)<=Settings!$B$5,Q$4>TODAY())),"",IF(EOMONTH(P$4,0)<=Settings!$B$5,N(Settings!$C$19),N(Calc!$AE$19))) | R7: =IF(OR(Settings!$A$19="",Settings!$F$19="Yes",OR(EOMONTH(R$4,0)<=Settings!$B$5,R$4>TODAY())),"",IF(EOMONTH(Q$4,0)<=Settings!$B$5,N(Settings!$C$19),N(Calc!$AE$20))) | S7: =IF(OR(Settings!$A$19="",Settings!$F$19="Yes",OR(EOMONTH(S$4,0)<=Settings!$B$5,S$4>TODAY())),"",IF(EOMONTH(R$4,0)<=Settings!$B$5,N(Settings!$C$19),N(Calc!$AE$21))) | T7: =IF(OR(Settings!$A$19="",Settings!$F$19="Yes",OR(EOMONTH(T$4,0)<=Settings!$B$5,T$4>TODAY())),"",IF(EOMONTH(S$4,0)<=Settings!$B$5,N(Settings!$C$19),N(Calc!$AE$22))) | U7: =IF(OR(Settings!$A$19="",Settings!$F$19="Yes",OR(EOMONTH(U$4,0)<=Settings!$B$5,U$4>TODAY())),"",IF(EOMONTH(T$4,0)<=Settings!$B$5,N(Settings!$C$19),N(Calc!$AE$23))) | V7: =IF(OR(Settings!$A$19="",Settings!$F$19="Yes",OR(EOMONTH(V$4,0)<=Settings!$B$5,V$4>TODAY())),"",IF(EOMONTH(U$4,0)<=Settings!$B$5,N(Settings!$C$19),N(Calc!$AE$24))) | W7: =IF(OR(Settings!$A$19="",Settings!$F$19="Yes",OR(EOMONTH(W$4,0)<=Settings!$B$5,W$4>TODAY())),"",IF(EOMONTH(V$4,0)<=Settings!$B$5,N(Settings!$C$19),N(Calc!$AE$25))) | X7: =IF(OR(Settings!$A$19="",Settings!$F$19="Yes",OR(EOMONTH(X$4,0)<=Settings!$B$5,X$4>TODAY())),"",IF(EOMONTH(W$4,0)<=Settings!$B$5,N(Settings!$C$19),N(Calc!$AE$26))) | Y7: =IF(OR(Settings!$A$19="",Settings!$F$19="Yes",OR(EOMONTH(Y$4,0)<=Settings!$B$5,Y$4>TODAY())),"",IF(EOMONTH(X$4,0)<=Settings!$B$5,N(Settings!$C$19),N(Calc!$AE$27))) | Z7: =IF(OR(Settings!$A$19="",Settings!$F$19="Yes",OR(EOMONTH(Z$4,0)<=Settings!$B$5,Z$4>TODAY())),"",IF(EOMONTH(Y$4,0)<=Settings!$B$5,N(Settings!$C$19),N(Calc!$AE$28))) | AA7: =IF(OR(Settings!$A$19="",Settings!$F$19="Yes",OR(EOMONTH(AA$4,0)<=Settings!$B$5,AA$4>TODAY())),"",IF(EOMONTH(Z$4,0)<=Settings!$B$5,N(Settings!$C$19),N(Calc!$AE$29))) | AB7: =IF(OR(Settings!$A$19="",Settings!$F$19="Yes",OR(EOMONTH(AB$4,0)<=Settings!$B$5,AB$4>TODAY())),"",IF(EOMONTH(AA$4,0)<=Settings!$B$5,N(Settings!$C$19),N(Calc!$AE$30))) | AC7: =IF(OR(Settings!$A$19="",Settings!$F$19="Yes",OR(EOMONTH(AC$4,0)<=Settings!$B$5,AC$4>TODAY())),"",IF(EOMONTH(AB$4,0)<=Settings!$B$5,N(Settings!$C$19),N(Calc!$AE$31))) | AD7: =IF(OR(Settings!$A$19="",Settings!$F$19="Yes",OR(EOMONTH(AD$4,0)<=Settings!$B$5,AD$4>TODAY())),"",IF(EOMONTH(AC$4,0)<=Settings!$B$5,N(Settings!$C$19),N(Calc!$AE$32))) | AE7: =IF(OR(Settings!$A$19="",Settings!$F$19="Yes",OR(EOMONTH(AE$4,0)<=Settings!$B$5,AE$4>TODAY())),"",IF(EOMONTH(AD$4,0)<=Settings!$B$5,N(Settings!$C$19),N(Calc!$AE$33))) | AF7: =IF(OR(Settings!$A$19="",Settings!$F$19="Yes",OR(EOMONTH(AF$4,0)<=Settings!$B$5,AF$4>TODAY())),"",IF(EOMONTH(AE$4,0)<=Settings!$B$5,N(Settings!$C$19),N(Calc!$AE$34))) | AG7: =IF(OR(Settings!$A$19="",Settings!$F$19="Yes",OR(EOMONTH(AG$4,0)<=Settings!$B$5,AG$4>TODAY())),"",IF(EOMONTH(AF$4,0)<=Settings!$B$5,N(Settings!$C$19),N(Calc!$AE$35))) | AH7: =IF(OR(Settings!$A$19="",Settings!$F$19="Yes",OR(EOMONTH(AH$4,0)<=Settings!$B$5,AH$4>TODAY())),"",IF(EOMONTH(AG$4,0)<=Settings!$B$5,N(Settings!$C$19),N(Calc!$AE$36))) | AI7: =IF(OR(Settings!$A$19="",Settings!$F$19="Yes",OR(EOMONTH(AI$4,0)<=Settings!$B$5,AI$4>TODAY())),"",IF(EOMONTH(AH$4,0)<=Settings!$B$5,N(Settings!$C$19),N(Calc!$AE$37))) | AJ7: =IF(OR(Settings!$A$19="",Settings!$F$19="Yes",OR(EOMONTH(AJ$4,0)<=Settings!$B$5,AJ$4>TODAY())),"",IF(EOMONTH(AI$4,0)<=Settings!$B$5,N(Settings!$C$19),N(Calc!$AE$38))) | AK7: =IF(OR(Settings!$A$19="",Settings!$F$19="Yes",OR(EOMONTH(AK$4,0)<=Settings!$B$5,AK$4>TODAY())),"",IF(EOMONTH(AJ$4,0)<=Settings!$B$5,N(Settings!$C$19),N(Calc!$AE$39))) | AL7: =IF(OR(Settings!$A$19="",Settings!$F$19="Yes",OR(EOMONTH(AL$4,0)<=Settings!$B$5,AL$4>TODAY())),"",IF(EOMONTH(AK$4,0)<=Settings!$B$5,N(Settings!$C$19),N(Calc!$AE$40))) | AM7: =IF(OR(Settings!$A$19="",Settings!$F$19="Yes",OR(EOMONTH(AM$4,0)<=Settings!$B$5,AM$4>TODAY())),"",IF(EOMONTH(AL$4,0)<=Settings!$B$5,N(Settings!$C$19),N(Calc!$AE$41))) | AN7: =IF(OR(Settings!$A$19="",Settings!$F$19="Yes",OR(EOMONTH(AN$4,0)<=Settings!$B$5,AN$4>TODAY())),"",IF(EOMONTH(AM$4,0)<=Settings!$B$5,N(Settings!$C$19),N(Calc!$AE$42))) | AO7: =IF(OR(Settings!$A$19="",Settings!$F$19="Yes",OR(EOMONTH(AO$4,0)<=Settings!$B$5,AO$4>TODAY())),"",IF(EOMONTH(AN$4,0)<=Settings!$B$5,N(Settings!$C$19),N(Calc!$AE$43))) | AP7: =IF(OR(Settings!$A$19="",Settings!$F$19="Yes",OR(EOMONTH(AP$4,0)<=Settings!$B$5,AP$4>TODAY())),"",IF(EOMONTH(AO$4,0)<=Settings!$B$5,N(Settings!$C$19),N(Calc!$AE$44))) | AQ7: =IF(OR(Settings!$A$19="",Settings!$F$19="Yes",OR(EOMONTH(AQ$4,0)<=Settings!$B$5,AQ$4>TODAY())),"",IF(EOMONTH(AP$4,0)<=Settings!$B$5,N(Settings!$C$19),N(Calc!$AE$45))) | AR7: =IF(OR(Settings!$A$19="",Settings!$F$19="Yes",OR(EOMONTH(AR$4,0)<=Settings!$B$5,AR$4>TODAY())),"",IF(EOMONTH(AQ$4,0)<=Settings!$B$5,N(Settings!$C$19),N(Calc!$AE$46))) | AS7: =IF(OR(Settings!$A$19="",Settings!$F$19="Yes",OR(EOMONTH(AS$4,0)<=Settings!$B$5,AS$4>TODAY())),"",IF(EOMONTH(AR$4,0)<=Settings!$B$5,N(Settings!$C$19),N(Calc!$AE$47))) | AT7: =IF(OR(Settings!$A$19="",Settings!$F$19="Yes",OR(EOMONTH(AT$4,0)<=Settings!$B$5,AT$4>TODAY())),"",IF(EOMONTH(AS$4,0)<=Settings!$B$5,N(Settings!$C$19),N(Calc!$AE$48))) | AU7: =IF(OR(Settings!$A$19="",Settings!$F$19="Yes",OR(EOMONTH(AU$4,0)<=Settings!$B$5,AU$4>TODAY())),"",IF(EOMONTH(AT$4,0)<=Settings!$B$5,N(Settings!$C$19),N(Calc!$AE$49))) | AV7: =IF(OR(Settings!$A$19="",Settings!$F$19="Yes",OR(EOMONTH(AV$4,0)<=Settings!$B$5,AV$4>TODAY())),"",IF(EOMONTH(AU$4,0)<=Settings!$B$5,N(Settings!$C$19),N(Calc!$AE$50))) | AW7: =IF(OR(Settings!$A$19="",Settings!$F$19="Yes",OR(EOMONTH(AW$4,0)<=Settings!$B$5,AW$4>TODAY())),"",IF(EOMONTH(AV$4,0)<=Settings!$B$5,N(Settings!$C$19),N(Calc!$AE$51))) | AX7: =IF(OR(Settings!$A$19="",Settings!$F$19="Yes",OR(EOMONTH(AX$4,0)<=Settings!$B$5,AX$4>TODAY())),"",IF(EOMONTH(AW$4,0)<=Settings!$B$5,N(Settings!$C$19),N(Calc!$AE$52))) | AY7: =IF(OR(Settings!$A$19="",Settings!$F$19="Yes",OR(EOMONTH(AY$4,0)<=Settings!$B$5,AY$4>TODAY())),"",IF(EOMONTH(AX$4,0)<=Settings!$B$5,N(Settings!$C$19),N(Calc!$AE$53))) | AZ7: =IF(OR(Settings!$A$19="",Settings!$F$19="Yes",OR(EOMONTH(AZ$4,0)<=Settings!$B$5,AZ$4>TODAY())),"",IF(EOMONTH(AY$4,0)<=Settings!$B$5,N(Settings!$C$19),N(Calc!$AE$54))) | BA7: =IF(OR(Settings!$A$19="",Settings!$F$19="Yes",OR(EOMONTH(BA$4,0)<=Settings!$B$5,BA$4>TODAY())),"",IF(EOMONTH(AZ$4,0)<=Settings!$B$5,N(Settings!$C$19),N(Calc!$AE$55))) | BB7: =IF(OR(Settings!$A$19="",Settings!$F$19="Yes",OR(EOMONTH(BB$4,0)<=Settings!$B$5,BB$4>TODAY())),"",IF(EOMONTH(BA$4,0)<=Settings!$B$5,N(Settings!$C$19),N(Calc!$AE$56))) | BC7: =IF(OR(Settings!$A$19="",Settings!$F$19="Yes",OR(EOMONTH(BC$4,0)<=Settings!$B$5,BC$4>TODAY())),"",IF(EOMONTH(BB$4,0)<=Settings!$B$5,N(Settings!$C$19),N(Calc!$AE$57))) | BD7: =IF(OR(Settings!$A$19="",Settings!$F$19="Yes",OR(EOMONTH(BD$4,0)<=Settings!$B$5,BD$4>TODAY())),"",IF(EOMONTH(BC$4,0)<=Settings!$B$5,N(Settings!$C$19),N(Calc!$AE$58))) | BE7: =IF(OR(Settings!$A$19="",Settings!$F$19="Yes",OR(EOMONTH(BE$4,0)<=Settings!$B$5,BE$4>TODAY())),"",IF(EOMONTH(BD$4,0)<=Settings!$B$5,N(Settings!$C$19),N(Calc!$AE$59))) | BF7: =IF(OR(Settings!$A$19="",Settings!$F$19="Yes",OR(EOMONTH(BF$4,0)<=Settings!$B$5,BF$4>TODAY())),"",IF(EOMONTH(BE$4,0)<=Settings!$B$5,N(Settings!$C$19),N(Calc!$AE$60))) | BG7: =IF(OR(Settings!$A$19="",Settings!$F$19="Yes",OR(EOMONTH(BG$4,0)<=Settings!$B$5,BG$4>TODAY())),"",IF(EOMONTH(BF$4,0)<=Settings!$B$5,N(Settings!$C$19),N(Calc!$AE$61))) | BH7: =IF(OR(Settings!$A$19="",Settings!$F$19="Yes",OR(EOMONTH(BH$4,0)<=Settings!$B$5,BH$4>TODAY())),"",IF(EOMONTH(BG$4,0)<=Settings!$B$5,N(Settings!$C$19),N(Calc!$AE$62))) | BI7: =IF(OR(Settings!$A$19="",Settings!$F$19="Yes",OR(EOMONTH(BI$4,0)<=Settings!$B$5,BI$4>TODAY())),"",IF(EOMONTH(BH$4,0)<=Settings!$B$5,N(Settings!$C$19),N(Calc!$AE$63))) | BJ7: =IF(OR(Settings!$A$19="",Settings!$F$19="Yes",OR(EOMONTH(BJ$4,0)<=Settings!$B$5,BJ$4>TODAY())),"",IF(EOMONTH(BI$4,0)<=Settings!$B$5,N(Settings!$C$19),N(Calc!$AE$64))) | BK7: =IF(OR(Settings!$A$19="",Settings!$F$19="Yes",OR(EOMONTH(BK$4,0)<=Settings!$B$5,BK$4>TODAY())),"",IF(EOMONTH(BJ$4,0)<=Settings!$B$5,N(Settings!$C$19),N(Calc!$AE$65))) | BL7: =IF(OR(Settings!$A$19="",Settings!$F$19="Yes",OR(EOMONTH(BL$4,0)<=Settings!$B$5,BL$4>TODAY())),"",IF(EOMONTH(BK$4,0)<=Settings!$B$5,N(Settings!$C$19),N(Calc!$AE$66))) | BM7: =IF(OR(Settings!$A$19="",Settings!$F$19="Yes",OR(EOMONTH(BM$4,0)<=Settings!$B$5,BM$4>TODAY())),"",IF(EOMONTH(BL$4,0)<=Settings!$B$5,N(Settings!$C$19),N(Calc!$AE$67))) | BN7: =IF(OR(Settings!$A$19="",Settings!$F$19="Yes",OR(EOMONTH(BN$4,0)<=Settings!$B$5,BN$4>TODAY())),"",IF(EOMONTH(BM$4,0)<=Settings!$B$5,N(Settings!$C$19),N(Calc!$AE$68))) | BO7: =IF(OR(Settings!$A$19="",Settings!$F$19="Yes",OR(EOMONTH(BO$4,0)<=Settings!$B$5,BO$4>TODAY())),"",IF(EOMONTH(BN$4,0)<=Settings!$B$5,N(Settings!$C$19),N(Calc!$AE$69))) | BP7: =IF(OR(Settings!$A$19="",Settings!$F$19="Yes",OR(EOMONTH(BP$4,0)<=Settings!$B$5,BP$4>TODAY())),"",IF(EOMONTH(BO$4,0)<=Settings!$B$5,N(Settings!$C$19),N(Calc!$AE$70))) | BQ7: =IF(OR(Settings!$A$19="",Settings!$F$19="Yes",OR(EOMONTH(BQ$4,0)<=Settings!$B$5,BQ$4>TODAY())),"",IF(EOMONTH(BP$4,0)<=Settings!$B$5,N(Settings!$C$19),N(Calc!$AE$71))) | BR7: =IF(OR(Settings!$A$19="",Settings!$F$19="Yes",OR(EOMONTH(BR$4,0)<=Settings!$B$5,BR$4>TODAY())),"",IF(EOMONTH(BQ$4,0)<=Settings!$B$5,N(Settings!$C$19),N(Calc!$AE$72))) | BS7: =IF(OR(Settings!$A$19="",Settings!$F$19="Yes",OR(EOMONTH(BS$4,0)<=Settings!$B$5,BS$4>TODAY())),"",IF(EOMONTH(BR$4,0)<=Settings!$B$5,N(Settings!$C$19),N(Calc!$AE$73))) | BT7: =IF(OR(Settings!$A$19="",Settings!$F$19="Yes",OR(EOMONTH(BT$4,0)<=Settings!$B$5,BT$4>TODAY())),"",IF(EOMONTH(BS$4,0)<=Settings!$B$5,N(Settings!$C$19),N(Calc!$AE$74))) | BU7: =IF(OR(Settings!$A$19="",Settings!$F$19="Yes",OR(EOMONTH(BU$4,0)<=Settings!$B$5,BU$4>TODAY())),"",IF(EOMONTH(BT$4,0)<=Settings!$B$5,N(Settings!$C$19),N(Calc!$AE$75))) | BV7: =IF(OR(Settings!$A$19="",Settings!$F$19="Yes",OR(EOMONTH(BV$4,0)<=Settings!$B$5,BV$4>TODAY())),"",IF(EOMONTH(BU$4,0)<=Settings!$B$5,N(Settings!$C$19),N(Calc!$AE$76))) | BW7: =IF(OR(Settings!$A$19="",Settings!$F$19="Yes",OR(EOMONTH(BW$4,0)<=Settings!$B$5,BW$4>TODAY())),"",IF(EOMONTH(BV$4,0)<=Settings!$B$5,N(Settings!$C$19),N(Calc!$AE$77))) | BX7: =IF(OR(Settings!$A$19="",Settings!$F$19="Yes",OR(EOMONTH(BX$4,0)<=Settings!$B$5,BX$4>TODAY())),"",IF(EOMONTH(BW$4,0)<=Settings!$B$5,N(Settings!$C$19),N(Calc!$AE$78))) | BY7: =IF(OR(Settings!$A$19="",Settings!$F$19="Yes",OR(EOMONTH(BY$4,0)<=Settings!$B$5,BY$4>TODAY())),"",IF(EOMONTH(BX$4,0)<=Settings!$B$5,N(Settings!$C$19),N(Calc!$AE$79))) | BZ7: =IF(OR(Settings!$A$19="",Settings!$F$19="Yes",OR(EOMONTH(BZ$4,0)<=Settings!$B$5,BZ$4>TODAY())),"",IF(EOMONTH(BY$4,0)<=Settings!$B$5,N(Settings!$C$19),N(Calc!$AE$80))) | CA7: =IF(OR(Settings!$A$19="",Settings!$F$19="Yes",OR(EOMONTH(CA$4,0)<=Settings!$B$5,CA$4>TODAY())),"",IF(EOMONTH(BZ$4,0)<=Settings!$B$5,N(Settings!$C$19),N(Calc!$AE$81))) | CB7: =IF(OR(Settings!$A$19="",Settings!$F$19="Yes",OR(EOMONTH(CB$4,0)<=Settings!$B$5,CB$4>TODAY())),"",IF(EOMONTH(CA$4,0)<=Settings!$B$5,N(Settings!$C$19),N(Calc!$AE$82))) | CC7: =IF(OR(Settings!$A$19="",Settings!$F$19="Yes",OR(EOMONTH(CC$4,0)<=Settings!$B$5,CC$4>TODAY())),"",IF(EOMONTH(CB$4,0)<=Settings!$B$5,N(Settings!$C$19),N(Calc!$AE$83))) | CD7: =IF(OR(Settings!$A$19="",Settings!$F$19="Yes",OR(EOMONTH(CD$4,0)<=Settings!$B$5,CD$4>TODAY())),"",IF(EOMONTH(CC$4,0)<=Settings!$B$5,N(Settings!$C$19),N(Calc!$AE$84))) | CE7: =IF(OR(Settings!$A$19="",Settings!$F$19="Yes",OR(EOMONTH(CE$4,0)<=Settings!$B$5,CE$4>TODAY())),"",IF(EOMONTH(CD$4,0)<=Settings!$B$5,N(Settings!$C$19),N(Calc!$AE$85))) | CF7: =IF(OR(Settings!$A$19="",Settings!$F$19="Yes",OR(EOMONTH(CF$4,0)<=Settings!$B$5,CF$4>TODAY())),"",IF(EOMONTH(CE$4,0)<=Settings!$B$5,N(Settings!$C$19),N(Calc!$AE$86))) | CG7: =IF(OR(Settings!$A$19="",Settings!$F$19="Yes",OR(EOMONTH(CG$4,0)<=Settings!$B$5,CG$4>TODAY())),"",IF(EOMONTH(CF$4,0)<=Settings!$B$5,N(Settings!$C$19),N(Calc!$AE$87))) | CH7: =IF(OR(Settings!$A$19="",Settings!$F$19="Yes",OR(EOMONTH(CH$4,0)<=Settings!$B$5,CH$4>TODAY())),"",IF(EOMONTH(CG$4,0)<=Settings!$B$5,N(Settings!$C$19),N(Calc!$AE$88))) | CI7: =IF(OR(Settings!$A$19="",Settings!$F$19="Yes",OR(EOMONTH(CI$4,0)<=Settings!$B$5,CI$4>TODAY())),"",IF(EOMONTH(CH$4,0)<=Settings!$B$5,N(Settings!$C$19),N(Calc!$AE$89))) | CJ7: =IF(OR(Settings!$A$19="",Settings!$F$19="Yes",OR(EOMONTH(CJ$4,0)<=Settings!$B$5,CJ$4>TODAY())),"",IF(EOMONTH(CI$4,0)<=Settings!$B$5,N(Settings!$C$19),N(Calc!$AE$90))) | CK7: =IF(OR(Settings!$A$19="",Settings!$F$19="Yes",OR(EOMONTH(CK$4,0)<=Settings!$B$5,CK$4>TODAY())),"",IF(EOMONTH(CJ$4,0)<=Settings!$B$5,N(Settings!$C$19),N(Calc!$AE$91))) | CL7: =IF(OR(Settings!$A$19="",Settings!$F$19="Yes",OR(EOMONTH(CL$4,0)<=Settings!$B$5,CL$4>TODAY())),"",IF(EOMONTH(CK$4,0)<=Settings!$B$5,N(Settings!$C$19),N(Calc!$AE$92))) | CM7: =IF(OR(Settings!$A$19="",Settings!$F$19="Yes",OR(EOMONTH(CM$4,0)<=Settings!$B$5,CM$4>TODAY())),"",IF(EOMONTH(CL$4,0)<=Settings!$B$5,N(Settings!$C$19),N(Calc!$AE$93))) | CN7: =IF(OR(Settings!$A$19="",Settings!$F$19="Yes",OR(EOMONTH(CN$4,0)<=Settings!$B$5,CN$4>TODAY())),"",IF(EOMONTH(CM$4,0)<=Settings!$B$5,N(Settings!$C$19),N(Calc!$AE$94))) | CO7: =IF(OR(Settings!$A$19="",Settings!$F$19="Yes",OR(EOMONTH(CO$4,0)<=Settings!$B$5,CO$4>TODAY())),"",IF(EOMONTH(CN$4,0)<=Settings!$B$5,N(Settings!$C$19),N(Calc!$AE$95))) | CP7: =IF(OR(Settings!$A$19="",Settings!$F$19="Yes",OR(EOMONTH(CP$4,0)<=Settings!$B$5,CP$4>TODAY())),"",IF(EOMONTH(CO$4,0)<=Settings!$B$5,N(Settings!$C$19),N(Calc!$AE$96))) | CQ7: =IF(OR(Settings!$A$19="",Settings!$F$19="Yes",OR(EOMONTH(CQ$4,0)<=Settings!$B$5,CQ$4>TODAY())),"",IF(EOMONTH(CP$4,0)<=Settings!$B$5,N(Settings!$C$19),N(Calc!$AE$97))) | CR7: =IF(OR(Settings!$A$19="",Settings!$F$19="Yes",OR(EOMONTH(CR$4,0)<=Settings!$B$5,CR$4>TODAY())),"",IF(EOMONTH(CQ$4,0)<=Settings!$B$5,N(Settings!$C$19),N(Calc!$AE$98))) | CS7: =IF(OR(Settings!$A$19="",Settings!$F$19="Yes",OR(EOMONTH(CS$4,0)<=Settings!$B$5,CS$4>TODAY())),"",IF(EOMONTH(CR$4,0)<=Settings!$B$5,N(Settings!$C$19),N(Calc!$AE$99))) | CT7: =IF(OR(Settings!$A$19="",Settings!$F$19="Yes",OR(EOMONTH(CT$4,0)<=Settings!$B$5,CT$4>TODAY())),"",IF(EOMONTH(CS$4,0)<=Settings!$B$5,N(Settings!$C$19),N(Calc!$AE$100))) | CU7: =IF(OR(Settings!$A$19="",Settings!$F$19="Yes",OR(EOMONTH(CU$4,0)<=Settings!$B$5,CU$4>TODAY())),"",IF(EOMONTH(CT$4,0)<=Settings!$B$5,N(Settings!$C$19),N(Calc!$AE$101))) | CV7: =IF(OR(Settings!$A$19="",Settings!$F$19="Yes",OR(EOMONTH(CV$4,0)<=Settings!$B$5,CV$4>TODAY())),"",IF(EOMONTH(CU$4,0)<=Settings!$B$5,N(Settings!$C$19),N(Calc!$AE$102))) | CW7: =IF(OR(Settings!$A$19="",Settings!$F$19="Yes",OR(EOMONTH(CW$4,0)<=Settings!$B$5,CW$4>TODAY())),"",IF(EOMONTH(CV$4,0)<=Settings!$B$5,N(Settings!$C$19),N(Calc!$AE$103))) | CX7: =IF(OR(Settings!$A$19="",Settings!$F$19="Yes",OR(EOMONTH(CX$4,0)<=Settings!$B$5,CX$4>TODAY())),"",IF(EOMONTH(CW$4,0)<=Settings!$B$5,N(Settings!$C$19),N(Calc!$AE$104))) | CY7: =IF(OR(Settings!$A$19="",Settings!$F$19="Yes",OR(EOMONTH(CY$4,0)<=Settings!$B$5,CY$4>TODAY())),"",IF(EOMONTH(CX$4,0)<=Settings!$B$5,N(Settings!$C$19),N(Calc!$AE$105))) | CZ7: =IF(OR(Settings!$A$19="",Settings!$F$19="Yes",OR(EOMONTH(CZ$4,0)<=Settings!$B$5,CZ$4>TODAY())),"",IF(EOMONTH(CY$4,0)<=Settings!$B$5,N(Settings!$C$19),N(Calc!$AE$106))) | DA7: =IF(OR(Settings!$A$19="",Settings!$F$19="Yes",OR(EOMONTH(DA$4,0)<=Settings!$B$5,DA$4>TODAY())),"",IF(EOMONTH(CZ$4,0)<=Settings!$B$5,N(Settings!$C$19),N(Calc!$AE$107))) | DB7: =IF(OR(Settings!$A$19="",Settings!$F$19="Yes",OR(EOMONTH(DB$4,0)<=Settings!$B$5,DB$4>TODAY())),"",IF(EOMONTH(DA$4,0)<=Settings!$B$5,N(Settings!$C$19),N(Calc!$AE$108))) | DC7: =IF(OR(Settings!$A$19="",Settings!$F$19="Yes",OR(EOMONTH(DC$4,0)<=Settings!$B$5,DC$4>TODAY())),"",IF(EOMONTH(DB$4,0)<=Settings!$B$5,N(Settings!$C$19),N(Calc!$AE$109))) | DD7: =IF(OR(Settings!$A$19="",Settings!$F$19="Yes",OR(EOMONTH(DD$4,0)<=Settings!$B$5,DD$4>TODAY())),"",IF(EOMONTH(DC$4,0)<=Settings!$B$5,N(Settings!$C$19),N(Calc!$AE$110))) | DE7: =IF(OR(Settings!$A$19="",Settings!$F$19="Yes",OR(EOMONTH(DE$4,0)<=Settings!$B$5,DE$4>TODAY())),"",IF(EOMONTH(DD$4,0)<=Settings!$B$5,N(Settings!$C$19),N(Calc!$AE$111))) | DF7: =IF(OR(Settings!$A$19="",Settings!$F$19="Yes",OR(EOMONTH(DF$4,0)<=Settings!$B$5,DF$4>TODAY())),"",IF(EOMONTH(DE$4,0)<=Settings!$B$5,N(Settings!$C$19),N(Calc!$AE$112))) | DG7: =IF(OR(Settings!$A$19="",Settings!$F$19="Yes",OR(EOMONTH(DG$4,0)<=Settings!$B$5,DG$4>TODAY())),"",IF(EOMONTH(DF$4,0)<=Settings!$B$5,N(Settings!$C$19),N(Calc!$AE$113))) | DH7: =IF(OR(Settings!$A$19="",Settings!$F$19="Yes",OR(EOMONTH(DH$4,0)<=Settings!$B$5,DH$4>TODAY())),"",IF(EOMONTH(DG$4,0)<=Settings!$B$5,N(Settings!$C$19),N(Calc!$AE$114))) | DI7: =IF(OR(Settings!$A$19="",Settings!$F$19="Yes",OR(EOMONTH(DI$4,0)<=Settings!$B$5,DI$4>TODAY())),"",IF(EOMONTH(DH$4,0)<=Settings!$B$5,N(Settings!$C$19),N(Calc!$AE$115))) | DJ7: =IF(OR(Settings!$A$19="",Settings!$F$19="Yes",OR(EOMONTH(DJ$4,0)<=Settings!$B$5,DJ$4>TODAY())),"",IF(EOMONTH(DI$4,0)<=Settings!$B$5,N(Settings!$C$19),N(Calc!$AE$116))) | DK7: =IF(OR(Settings!$A$19="",Settings!$F$19="Yes",OR(EOMONTH(DK$4,0)<=Settings!$B$5,DK$4>TODAY())),"",IF(EOMONTH(DJ$4,0)<=Settings!$B$5,N(Settings!$C$19),N(Calc!$AE$117))) | DL7: =IF(OR(Settings!$A$19="",Settings!$F$19="Yes",OR(EOMONTH(DL$4,0)<=Settings!$B$5,DL$4>TODAY())),"",IF(EOMONTH(DK$4,0)<=Settings!$B$5,N(Settings!$C$19),N(Calc!$AE$118))) | DM7: =IF(OR(Settings!$A$19="",Settings!$F$19="Yes",OR(EOMONTH(DM$4,0)<=Settings!$B$5,DM$4>TODAY())),"",IF(EOMONTH(DL$4,0)<=Settings!$B$5,N(Settings!$C$19),N(Calc!$AE$119))) | DN7: =IF(OR(Settings!$A$19="",Settings!$F$19="Yes",OR(EOMONTH(DN$4,0)<=Settings!$B$5,DN$4>TODAY())),"",IF(EOMONTH(DM$4,0)<=Settings!$B$5,N(Settings!$C$19),N(Calc!$AE$120))) | DO7: =IF(OR(Settings!$A$19="",Settings!$F$19="Yes",OR(EOMONTH(DO$4,0)<=Settings!$B$5,DO$4>TODAY())),"",IF(EOMONTH(DN$4,0)<=Settings!$B$5,N(Settings!$C$19),N(Calc!$AE$121))) | DP7: =IF(OR(Settings!$A$19="",Settings!$F$19="Yes",OR(EOMONTH(DP$4,0)<=Settings!$B$5,DP$4>TODAY())),"",IF(EOMONTH(DO$4,0)<=Settings!$B$5,N(Settings!$C$19),N(Calc!$AE$122))) | DQ7: =IF(OR(Settings!$A$19="",Settings!$F$19="Yes",OR(EOMONTH(DQ$4,0)<=Settings!$B$5,DQ$4>TODAY())),"",IF(EOMONTH(DP$4,0)<=Settings!$B$5,N(Settings!$C$19),N(Calc!$AE$123))) | DR7: =IF(OR(Settings!$A$19="",Settings!$F$19="Yes",OR(EOMONTH(DR$4,0)<=Settings!$B$5,DR$4>TODAY())),"",IF(EOMONTH(DQ$4,0)<=Settings!$B$5,N(Settings!$C$19),N(Calc!$AE$124))) | DS7: =IF(OR(Settings!$A$19="",Settings!$F$19="Yes",OR(EOMONTH(DS$4,0)<=Settings!$B$5,DS$4>TODAY())),"",IF(EOMONTH(DR$4,0)<=Settings!$B$5,N(Settings!$C$19),N(Calc!$AE$125))) | DT7: =IF(OR(Settings!$A$19="",Settings!$F$19="Yes",OR(EOMONTH(DT$4,0)<=Settings!$B$5,DT$4>TODAY())),"",IF(EOMONTH(DS$4,0)<=Settings!$B$5,N(Settings!$C$19),N(Calc!$AE$126))) | DU7: =IF(OR(Settings!$A$19="",Settings!$F$19="Yes",OR(EOMONTH(DU$4,0)<=Settings!$B$5,DU$4>TODAY())),"",IF(EOMONTH(DT$4,0)<=Settings!$B$5,N(Settings!$C$19),N(Calc!$AE$127))) | DV7: =IF(OR(Settings!$A$19="",Settings!$F$19="Yes",OR(EOMONTH(DV$4,0)<=Settings!$B$5,DV$4>TODAY())),"",IF(EOMONTH(DU$4,0)<=Settings!$B$5,N(Settings!$C$19),N(Calc!$AE$128))) | DW7: =IF(OR(Settings!$A$19="",Settings!$F$19="Yes",OR(EOMONTH(DW$4,0)<=Settings!$B$5,DW$4>TODAY())),"",IF(EOMONTH(DV$4,0)<=Settings!$B$5,N(Settings!$C$19),N(Calc!$AE$129))) | DX7: =IF(OR(Settings!$A$19="",Settings!$F$19="Yes",OR(EOMONTH(DX$4,0)<=Settings!$B$5,DX$4>TODAY())),"",IF(EOMONTH(DW$4,0)<=Settings!$B$5,N(Settings!$C$19),N(Calc!$AE$130))) | DY7: =IF(OR(Settings!$A$19="",Settings!$F$19="Yes",OR(EOMONTH(DY$4,0)<=Settings!$B$5,DY$4>TODAY())),"",IF(EOMONTH(DX$4,0)<=Settings!$B$5,N(Settings!$C$19),N(Calc!$AE$131))) | DZ7: =IF(OR(Settings!$A$19="",Settings!$F$19="Yes",OR(EOMONTH(DZ$4,0)<=Settings!$B$5,DZ$4>TODAY())),"",IF(EOMONTH(DY$4,0)<=Settings!$B$5,N(Settings!$C$19),N(Calc!$AE$132))) | EA7: =IF(OR(Settings!$A$19="",Settings!$F$19="Yes",OR(EOMONTH(EA$4,0)<=Settings!$B$5,EA$4>TODAY())),"",IF(EOMONTH(DZ$4,0)<=Settings!$B$5,N(Settings!$C$19),N(Calc!$AE$133))) | EB7: =IF(OR(Settings!$A$19="",Settings!$F$19="Yes",OR(EOMONTH(EB$4,0)<=Settings!$B$5,EB$4>TODAY())),"",IF(EOMONTH(EA$4,0)<=Settings!$B$5,N(Settings!$C$19),N(Calc!$AE$134))) | EC7: =IF(OR(Settings!$A$19="",Settings!$F$19="Yes",OR(EOMONTH(EC$4,0)<=Settings!$B$5,EC$4>TODAY())),"",IF(EOMONTH(EB$4,0)<=Settings!$B$5,N(Settings!$C$19),N(Calc!$AE$135))) | ED7: =IF(OR(Settings!$A$19="",Settings!$F$19="Yes",OR(EOMONTH(ED$4,0)<=Settings!$B$5,ED$4>TODAY())),"",IF(EOMONTH(EC$4,0)<=Settings!$B$5,N(Settings!$C$19),N(Calc!$AE$136))) | EE7: =IF(OR(Settings!$A$19="",Settings!$F$19="Yes",OR(EOMONTH(EE$4,0)<=Settings!$B$5,EE$4>TODAY())),"",IF(EOMONTH(ED$4,0)<=Settings!$B$5,N(Settings!$C$19),N(Calc!$AE$137))) | EF7: =IF(OR(Settings!$A$19="",Settings!$F$19="Yes",OR(EOMONTH(EF$4,0)<=Settings!$B$5,EF$4>TODAY())),"",IF(EOMONTH(EE$4,0)<=Settings!$B$5,N(Settings!$C$19),N(Calc!$AE$138))) | EG7: =IF(OR(Settings!$A$19="",Settings!$F$19="Yes",OR(EOMONTH(EG$4,0)<=Settings!$B$5,EG$4>TODAY())),"",IF(EOMONTH(EF$4,0)<=Settings!$B$5,N(Settings!$C$19),N(Calc!$AE$139))) | EH7: =IF(OR(Settings!$A$19="",Settings!$F$19="Yes",OR(EOMONTH(EH$4,0)<=Settings!$B$5,EH$4>TODAY())),"",IF(EOMONTH(EG$4,0)<=Settings!$B$5,N(Settings!$C$19),N(Calc!$AE$140))) | EI7: =IF(OR(Settings!$A$19="",Settings!$F$19="Yes",OR(EOMONTH(EI$4,0)<=Settings!$B$5,EI$4>TODAY())),"",IF(EOMONTH(EH$4,0)<=Settings!$B$5,N(Settings!$C$19),N(Calc!$AE$141))) | EJ7: =IF(OR(Settings!$A$19="",Settings!$F$19="Yes",OR(EOMONTH(EJ$4,0)<=Settings!$B$5,EJ$4>TODAY())),"",IF(EOMONTH(EI$4,0)<=Settings!$B$5,N(Settings!$C$19),N(Calc!$AE$142))) | EK7: =IF(OR(Settings!$A$19="",Settings!$F$19="Yes",OR(EOMONTH(EK$4,0)<=Settings!$B$5,EK$4>TODAY())),"",IF(EOMONTH(EJ$4,0)<=Settings!$B$5,N(Settings!$C$19),N(Calc!$AE$143))) | EL7: =IF(OR(Settings!$A$19="",Settings!$F$19="Yes",OR(EOMONTH(EL$4,0)<=Settings!$B$5,EL$4>TODAY())),"",IF(EOMONTH(EK$4,0)<=Settings!$B$5,N(Settings!$C$19),N(Calc!$AE$144))) | EM7: =IF(OR(Settings!$A$19="",Settings!$F$19="Yes",OR(EOMONTH(EM$4,0)<=Settings!$B$5,EM$4>TODAY())),"",IF(EOMONTH(EL$4,0)<=Settings!$B$5,N(Settings!$C$19),N(Calc!$AE$145))) | EN7: =IF(OR(Settings!$A$19="",Settings!$F$19="Yes",OR(EOMONTH(EN$4,0)<=Settings!$B$5,EN$4>TODAY())),"",IF(EOMONTH(EM$4,0)<=Settings!$B$5,N(Settings!$C$19),N(Calc!$AE$146))) | EO7: =IF(OR(Settings!$A$19="",Settings!$F$19="Yes",OR(EOMONTH(EO$4,0)<=Settings!$B$5,EO$4>TODAY())),"",IF(EOMONTH(EN$4,0)<=Settings!$B$5,N(Settings!$C$19),N(Calc!$AE$147))) | EP7: =IF(OR(Settings!$A$19="",Settings!$F$19="Yes",OR(EOMONTH(EP$4,0)<=Settings!$B$5,EP$4>TODAY())),"",IF(EOMONTH(EO$4,0)<=Settings!$B$5,N(Settings!$C$19),N(Calc!$AE$148))) | EQ7: =IF(OR(Settings!$A$19="",Settings!$F$19="Yes",OR(EOMONTH(EQ$4,0)<=Settings!$B$5,EQ$4>TODAY())),"",IF(EOMONTH(EP$4,0)<=Settings!$B$5,N(Settings!$C$19),N(Calc!$AE$149))) | ER7: =IF(OR(Settings!$A$19="",Settings!$F$19="Yes",OR(EOMONTH(ER$4,0)<=Settings!$B$5,ER$4>TODAY())),"",IF(EOMONTH(EQ$4,0)<=Settings!$B$5,N(Settings!$C$19),N(Calc!$AE$150))) | ES7: =IF(OR(Settings!$A$19="",Settings!$F$19="Yes",OR(EOMONTH(ES$4,0)<=Settings!$B$5,ES$4>TODAY())),"",IF(EOMONTH(ER$4,0)<=Settings!$B$5,N(Settings!$C$19),N(Calc!$AE$151))) | ET7: =IF(OR(Settings!$A$19="",Settings!$F$19="Yes",OR(EOMONTH(ET$4,0)<=Settings!$B$5,ET$4>TODAY())),"",IF(EOMONTH(ES$4,0)<=Settings!$B$5,N(Settings!$C$19),N(Calc!$AE$152))) | EU7: =IF(OR(Settings!$A$19="",Settings!$F$19="Yes",OR(EOMONTH(EU$4,0)<=Settings!$B$5,EU$4>TODAY())),"",IF(EOMONTH(ET$4,0)<=Settings!$B$5,N(Settings!$C$19),N(Calc!$AE$153))) | EV7: =IF(OR(Settings!$A$19="",Settings!$F$19="Yes",OR(EOMONTH(EV$4,0)<=Settings!$B$5,EV$4>TODAY())),"",IF(EOMONTH(EU$4,0)<=Settings!$B$5,N(Settings!$C$19),N(Calc!$AE$154))) | EW7: =IF(OR(Settings!$A$19="",Settings!$F$19="Yes",OR(EOMONTH(EW$4,0)<=Settings!$B$5,EW$4>TODAY())),"",IF(EOMONTH(EV$4,0)<=Settings!$B$5,N(Settings!$C$19),N(Calc!$AE$155))) | EX7: =IF(OR(Settings!$A$19="",Settings!$F$19="Yes",OR(EOMONTH(EX$4,0)<=Settings!$B$5,EX$4>TODAY())),"",IF(EOMONTH(EW$4,0)<=Settings!$B$5,N(Settings!$C$19),N(Calc!$AE$156))) | EY7: =IF(OR(Settings!$A$19="",Settings!$F$19="Yes",OR(EOMONTH(EY$4,0)<=Settings!$B$5,EY$4>TODAY())),"",IF(EOMONTH(EX$4,0)<=Settings!$B$5,N(Settings!$C$19),N(Calc!$AE$157))) | EZ7: =IF(OR(Settings!$A$19="",Settings!$F$19="Yes",OR(EOMONTH(EZ$4,0)<=Settings!$B$5,EZ$4>TODAY())),"",IF(EOMONTH(EY$4,0)<=Settings!$B$5,N(Settings!$C$19),N(Calc!$AE$158))) | FA7: =IF(OR(Settings!$A$19="",Settings!$F$19="Yes",OR(EOMONTH(FA$4,0)<=Settings!$B$5,FA$4>TODAY())),"",IF(EOMONTH(EZ$4,0)<=Settings!$B$5,N(Settings!$C$19),N(Calc!$AE$159))) | FB7: =IF(OR(Settings!$A$19="",Settings!$F$19="Yes",OR(EOMONTH(FB$4,0)<=Settings!$B$5,FB$4>TODAY())),"",IF(EOMONTH(FA$4,0)<=Settings!$B$5,N(Settings!$C$19),N(Calc!$AE$160))) | FC7: =IF(OR(Settings!$A$19="",Settings!$F$19="Yes",OR(EOMONTH(FC$4,0)<=Settings!$B$5,FC$4>TODAY())),"",IF(EOMONTH(FB$4,0)<=Settings!$B$5,N(Settings!$C$19),N(Calc!$AE$161))) | FD7: =IF(OR(Settings!$A$19="",Settings!$F$19="Yes",OR(EOMONTH(FD$4,0)<=Settings!$B$5,FD$4>TODAY())),"",IF(EOMONTH(FC$4,0)<=Settings!$B$5,N(Settings!$C$19),N(Calc!$AE$162))) | FE7: =IF(OR(Settings!$A$19="",Settings!$F$19="Yes",OR(EOMONTH(FE$4,0)<=Settings!$B$5,FE$4>TODAY())),"",IF(EOMONTH(FD$4,0)<=Settings!$B$5,N(Settings!$C$19),N(Calc!$AE$163))) | FF7: =IF(OR(Settings!$A$19="",Settings!$F$19="Yes",OR(EOMONTH(FF$4,0)<=Settings!$B$5,FF$4>TODAY())),"",IF(EOMONTH(FE$4,0)<=Settings!$B$5,N(Settings!$C$19),N(Calc!$AE$164))) | FG7: =IF(OR(Settings!$A$19="",Settings!$F$19="Yes",OR(EOMONTH(FG$4,0)<=Settings!$B$5,FG$4>TODAY())),"",IF(EOMONTH(FF$4,0)<=Settings!$B$5,N(Settings!$C$19),N(Calc!$AE$165))) | FH7: =IF(OR(Settings!$A$19="",Settings!$F$19="Yes",OR(EOMONTH(FH$4,0)<=Settings!$B$5,FH$4>TODAY())),"",IF(EOMONTH(FG$4,0)<=Settings!$B$5,N(Settings!$C$19),N(Calc!$AE$166))) | FI7: =IF(OR(Settings!$A$19="",Settings!$F$19="Yes",OR(EOMONTH(FI$4,0)<=Settings!$B$5,FI$4>TODAY())),"",IF(EOMONTH(FH$4,0)<=Settings!$B$5,N(Settings!$C$19),N(Calc!$AE$167))) | FJ7: =IF(OR(Settings!$A$19="",Settings!$F$19="Yes",OR(EOMONTH(FJ$4,0)<=Settings!$B$5,FJ$4>TODAY())),"",IF(EOMONTH(FI$4,0)<=Settings!$B$5,N(Settings!$C$19),N(Calc!$AE$168))) | FK7: =IF(OR(Settings!$A$19="",Settings!$F$19="Yes",OR(EOMONTH(FK$4,0)<=Settings!$B$5,FK$4>TODAY())),"",IF(EOMONTH(FJ$4,0)<=Settings!$B$5,N(Settings!$C$19),N(Calc!$AE$169))) | FL7: =IF(OR(Settings!$A$19="",Settings!$F$19="Yes",OR(EOMONTH(FL$4,0)<=Settings!$B$5,FL$4>TODAY())),"",IF(EOMONTH(FK$4,0)<=Settings!$B$5,N(Settings!$C$19),N(Calc!$AE$170))) | FM7: =IF(OR(Settings!$A$19="",Settings!$F$19="Yes",OR(EOMONTH(FM$4,0)<=Settings!$B$5,FM$4>TODAY())),"",IF(EOMONTH(FL$4,0)<=Settings!$B$5,N(Settings!$C$19),N(Calc!$AE$171))) | FN7: =IF(OR(Settings!$A$19="",Settings!$F$19="Yes",OR(EOMONTH(FN$4,0)<=Settings!$B$5,FN$4>TODAY())),"",IF(EOMONTH(FM$4,0)<=Settings!$B$5,N(Settings!$C$19),N(Calc!$AE$172))) | FO7: =IF(OR(Settings!$A$19="",Settings!$F$19="Yes",OR(EOMONTH(FO$4,0)<=Settings!$B$5,FO$4>TODAY())),"",IF(EOMONTH(FN$4,0)<=Settings!$B$5,N(Settings!$C$19),N(Calc!$AE$173))) | FP7: =IF(OR(Settings!$A$19="",Settings!$F$19="Yes",OR(EOMONTH(FP$4,0)<=Settings!$B$5,FP$4>TODAY())),"",IF(EOMONTH(FO$4,0)<=Settings!$B$5,N(Settings!$C$19),N(Calc!$AE$174))) | FQ7: =IF(OR(Settings!$A$19="",Settings!$F$19="Yes",OR(EOMONTH(FQ$4,0)<=Settings!$B$5,FQ$4>TODAY())),"",IF(EOMONTH(FP$4,0)<=Settings!$B$5,N(Settings!$C$19),N(Calc!$AE$175))) | FR7: =IF(OR(Settings!$A$19="",Settings!$F$19="Yes",OR(EOMONTH(FR$4,0)<=Settings!$B$5,FR$4>TODAY())),"",IF(EOMONTH(FQ$4,0)<=Settings!$B$5,N(Settings!$C$19),N(Calc!$AE$176))) | FS7: =IF(OR(Settings!$A$19="",Settings!$F$19="Yes",OR(EOMONTH(FS$4,0)<=Settings!$B$5,FS$4>TODAY())),"",IF(EOMONTH(FR$4,0)<=Settings!$B$5,N(Settings!$C$19),N(Calc!$AE$177))) | FT7: =IF(OR(Settings!$A$19="",Settings!$F$19="Yes",OR(EOMONTH(FT$4,0)<=Settings!$B$5,FT$4>TODAY())),"",IF(EOMONTH(FS$4,0)<=Settings!$B$5,N(Settings!$C$19),N(Calc!$AE$178))) | FU7: =IF(OR(Settings!$A$19="",Settings!$F$19="Yes",OR(EOMONTH(FU$4,0)<=Settings!$B$5,FU$4>TODAY())),"",IF(EOMONTH(FT$4,0)<=Settings!$B$5,N(Settings!$C$19),N(Calc!$AE$179))) | FV7: =IF(OR(Settings!$A$19="",Settings!$F$19="Yes",OR(EOMONTH(FV$4,0)<=Settings!$B$5,FV$4>TODAY())),"",IF(EOMONTH(FU$4,0)<=Settings!$B$5,N(Settings!$C$19),N(Calc!$AE$180))) | FW7: =IF(OR(Settings!$A$19="",Settings!$F$19="Yes",OR(EOMONTH(FW$4,0)<=Settings!$B$5,FW$4>TODAY())),"",IF(EOMONTH(FV$4,0)<=Settings!$B$5,N(Settings!$C$19),N(Calc!$AE$181))) | FX7: =IF(OR(Settings!$A$19="",Settings!$F$19="Yes",OR(EOMONTH(FX$4,0)<=Settings!$B$5,FX$4>TODAY())),"",IF(EOMONTH(FW$4,0)<=Settings!$B$5,N(Settings!$C$19),N(Calc!$AE$182)))
A8: =IF(Settings!$A$20="","(unused)",Settings!$A$20&IF(Settings!$E$20="No"," (retired)","")) | B8: =IF(Settings!$A$20="","",IF(Settings!$F$20="Yes","REQUIRED","optional · grey = unchanged")&IF(OR(Settings!$B$20="Card",Settings!$B$20="Loan")," · amount owed","")) | C8: =IF(OR(Settings!$A$20="",Settings!$F$20="Yes",OR(EOMONTH(C$4,0)<=Settings!$B$5,C$4>TODAY())),"",N(Settings!$C$20)) | D8: =IF(OR(Settings!$A$20="",Settings!$F$20="Yes",OR(EOMONTH(D$4,0)<=Settings!$B$5,D$4>TODAY())),"",IF(EOMONTH(C$4,0)<=Settings!$B$5,N(Settings!$C$20),N(Calc!$AF$6))) | E8: =IF(OR(Settings!$A$20="",Settings!$F$20="Yes",OR(EOMONTH(E$4,0)<=Settings!$B$5,E$4>TODAY())),"",IF(EOMONTH(D$4,0)<=Settings!$B$5,N(Settings!$C$20),N(Calc!$AF$7))) | F8: =IF(OR(Settings!$A$20="",Settings!$F$20="Yes",OR(EOMONTH(F$4,0)<=Settings!$B$5,F$4>TODAY())),"",IF(EOMONTH(E$4,0)<=Settings!$B$5,N(Settings!$C$20),N(Calc!$AF$8))) | G8: =IF(OR(Settings!$A$20="",Settings!$F$20="Yes",OR(EOMONTH(G$4,0)<=Settings!$B$5,G$4>TODAY())),"",IF(EOMONTH(F$4,0)<=Settings!$B$5,N(Settings!$C$20),N(Calc!$AF$9))) | H8: =IF(OR(Settings!$A$20="",Settings!$F$20="Yes",OR(EOMONTH(H$4,0)<=Settings!$B$5,H$4>TODAY())),"",IF(EOMONTH(G$4,0)<=Settings!$B$5,N(Settings!$C$20),N(Calc!$AF$10))) | I8: =IF(OR(Settings!$A$20="",Settings!$F$20="Yes",OR(EOMONTH(I$4,0)<=Settings!$B$5,I$4>TODAY())),"",IF(EOMONTH(H$4,0)<=Settings!$B$5,N(Settings!$C$20),N(Calc!$AF$11))) | J8: =IF(OR(Settings!$A$20="",Settings!$F$20="Yes",OR(EOMONTH(J$4,0)<=Settings!$B$5,J$4>TODAY())),"",IF(EOMONTH(I$4,0)<=Settings!$B$5,N(Settings!$C$20),N(Calc!$AF$12))) | K8: =IF(OR(Settings!$A$20="",Settings!$F$20="Yes",OR(EOMONTH(K$4,0)<=Settings!$B$5,K$4>TODAY())),"",IF(EOMONTH(J$4,0)<=Settings!$B$5,N(Settings!$C$20),N(Calc!$AF$13))) | L8: =IF(OR(Settings!$A$20="",Settings!$F$20="Yes",OR(EOMONTH(L$4,0)<=Settings!$B$5,L$4>TODAY())),"",IF(EOMONTH(K$4,0)<=Settings!$B$5,N(Settings!$C$20),N(Calc!$AF$14))) | M8: =IF(OR(Settings!$A$20="",Settings!$F$20="Yes",OR(EOMONTH(M$4,0)<=Settings!$B$5,M$4>TODAY())),"",IF(EOMONTH(L$4,0)<=Settings!$B$5,N(Settings!$C$20),N(Calc!$AF$15))) | N8: =IF(OR(Settings!$A$20="",Settings!$F$20="Yes",OR(EOMONTH(N$4,0)<=Settings!$B$5,N$4>TODAY())),"",IF(EOMONTH(M$4,0)<=Settings!$B$5,N(Settings!$C$20),N(Calc!$AF$16))) | O8: =IF(OR(Settings!$A$20="",Settings!$F$20="Yes",OR(EOMONTH(O$4,0)<=Settings!$B$5,O$4>TODAY())),"",IF(EOMONTH(N$4,0)<=Settings!$B$5,N(Settings!$C$20),N(Calc!$AF$17))) | P8: =IF(OR(Settings!$A$20="",Settings!$F$20="Yes",OR(EOMONTH(P$4,0)<=Settings!$B$5,P$4>TODAY())),"",IF(EOMONTH(O$4,0)<=Settings!$B$5,N(Settings!$C$20),N(Calc!$AF$18))) | Q8: =IF(OR(Settings!$A$20="",Settings!$F$20="Yes",OR(EOMONTH(Q$4,0)<=Settings!$B$5,Q$4>TODAY())),"",IF(EOMONTH(P$4,0)<=Settings!$B$5,N(Settings!$C$20),N(Calc!$AF$19))) | R8: =IF(OR(Settings!$A$20="",Settings!$F$20="Yes",OR(EOMONTH(R$4,0)<=Settings!$B$5,R$4>TODAY())),"",IF(EOMONTH(Q$4,0)<=Settings!$B$5,N(Settings!$C$20),N(Calc!$AF$20))) | S8: =IF(OR(Settings!$A$20="",Settings!$F$20="Yes",OR(EOMONTH(S$4,0)<=Settings!$B$5,S$4>TODAY())),"",IF(EOMONTH(R$4,0)<=Settings!$B$5,N(Settings!$C$20),N(Calc!$AF$21))) | T8: =IF(OR(Settings!$A$20="",Settings!$F$20="Yes",OR(EOMONTH(T$4,0)<=Settings!$B$5,T$4>TODAY())),"",IF(EOMONTH(S$4,0)<=Settings!$B$5,N(Settings!$C$20),N(Calc!$AF$22))) | U8: =IF(OR(Settings!$A$20="",Settings!$F$20="Yes",OR(EOMONTH(U$4,0)<=Settings!$B$5,U$4>TODAY())),"",IF(EOMONTH(T$4,0)<=Settings!$B$5,N(Settings!$C$20),N(Calc!$AF$23))) | V8: =IF(OR(Settings!$A$20="",Settings!$F$20="Yes",OR(EOMONTH(V$4,0)<=Settings!$B$5,V$4>TODAY())),"",IF(EOMONTH(U$4,0)<=Settings!$B$5,N(Settings!$C$20),N(Calc!$AF$24))) | W8: =IF(OR(Settings!$A$20="",Settings!$F$20="Yes",OR(EOMONTH(W$4,0)<=Settings!$B$5,W$4>TODAY())),"",IF(EOMONTH(V$4,0)<=Settings!$B$5,N(Settings!$C$20),N(Calc!$AF$25))) | X8: =IF(OR(Settings!$A$20="",Settings!$F$20="Yes",OR(EOMONTH(X$4,0)<=Settings!$B$5,X$4>TODAY())),"",IF(EOMONTH(W$4,0)<=Settings!$B$5,N(Settings!$C$20),N(Calc!$AF$26))) | Y8: =IF(OR(Settings!$A$20="",Settings!$F$20="Yes",OR(EOMONTH(Y$4,0)<=Settings!$B$5,Y$4>TODAY())),"",IF(EOMONTH(X$4,0)<=Settings!$B$5,N(Settings!$C$20),N(Calc!$AF$27))) | Z8: =IF(OR(Settings!$A$20="",Settings!$F$20="Yes",OR(EOMONTH(Z$4,0)<=Settings!$B$5,Z$4>TODAY())),"",IF(EOMONTH(Y$4,0)<=Settings!$B$5,N(Settings!$C$20),N(Calc!$AF$28))) | AA8: =IF(OR(Settings!$A$20="",Settings!$F$20="Yes",OR(EOMONTH(AA$4,0)<=Settings!$B$5,AA$4>TODAY())),"",IF(EOMONTH(Z$4,0)<=Settings!$B$5,N(Settings!$C$20),N(Calc!$AF$29))) | AB8: =IF(OR(Settings!$A$20="",Settings!$F$20="Yes",OR(EOMONTH(AB$4,0)<=Settings!$B$5,AB$4>TODAY())),"",IF(EOMONTH(AA$4,0)<=Settings!$B$5,N(Settings!$C$20),N(Calc!$AF$30))) | AC8: =IF(OR(Settings!$A$20="",Settings!$F$20="Yes",OR(EOMONTH(AC$4,0)<=Settings!$B$5,AC$4>TODAY())),"",IF(EOMONTH(AB$4,0)<=Settings!$B$5,N(Settings!$C$20),N(Calc!$AF$31))) | AD8: =IF(OR(Settings!$A$20="",Settings!$F$20="Yes",OR(EOMONTH(AD$4,0)<=Settings!$B$5,AD$4>TODAY())),"",IF(EOMONTH(AC$4,0)<=Settings!$B$5,N(Settings!$C$20),N(Calc!$AF$32))) | AE8: =IF(OR(Settings!$A$20="",Settings!$F$20="Yes",OR(EOMONTH(AE$4,0)<=Settings!$B$5,AE$4>TODAY())),"",IF(EOMONTH(AD$4,0)<=Settings!$B$5,N(Settings!$C$20),N(Calc!$AF$33))) | AF8: =IF(OR(Settings!$A$20="",Settings!$F$20="Yes",OR(EOMONTH(AF$4,0)<=Settings!$B$5,AF$4>TODAY())),"",IF(EOMONTH(AE$4,0)<=Settings!$B$5,N(Settings!$C$20),N(Calc!$AF$34))) | AG8: =IF(OR(Settings!$A$20="",Settings!$F$20="Yes",OR(EOMONTH(AG$4,0)<=Settings!$B$5,AG$4>TODAY())),"",IF(EOMONTH(AF$4,0)<=Settings!$B$5,N(Settings!$C$20),N(Calc!$AF$35))) | AH8: =IF(OR(Settings!$A$20="",Settings!$F$20="Yes",OR(EOMONTH(AH$4,0)<=Settings!$B$5,AH$4>TODAY())),"",IF(EOMONTH(AG$4,0)<=Settings!$B$5,N(Settings!$C$20),N(Calc!$AF$36))) | AI8: =IF(OR(Settings!$A$20="",Settings!$F$20="Yes",OR(EOMONTH(AI$4,0)<=Settings!$B$5,AI$4>TODAY())),"",IF(EOMONTH(AH$4,0)<=Settings!$B$5,N(Settings!$C$20),N(Calc!$AF$37))) | AJ8: =IF(OR(Settings!$A$20="",Settings!$F$20="Yes",OR(EOMONTH(AJ$4,0)<=Settings!$B$5,AJ$4>TODAY())),"",IF(EOMONTH(AI$4,0)<=Settings!$B$5,N(Settings!$C$20),N(Calc!$AF$38))) | AK8: =IF(OR(Settings!$A$20="",Settings!$F$20="Yes",OR(EOMONTH(AK$4,0)<=Settings!$B$5,AK$4>TODAY())),"",IF(EOMONTH(AJ$4,0)<=Settings!$B$5,N(Settings!$C$20),N(Calc!$AF$39))) | AL8: =IF(OR(Settings!$A$20="",Settings!$F$20="Yes",OR(EOMONTH(AL$4,0)<=Settings!$B$5,AL$4>TODAY())),"",IF(EOMONTH(AK$4,0)<=Settings!$B$5,N(Settings!$C$20),N(Calc!$AF$40))) | AM8: =IF(OR(Settings!$A$20="",Settings!$F$20="Yes",OR(EOMONTH(AM$4,0)<=Settings!$B$5,AM$4>TODAY())),"",IF(EOMONTH(AL$4,0)<=Settings!$B$5,N(Settings!$C$20),N(Calc!$AF$41))) | AN8: =IF(OR(Settings!$A$20="",Settings!$F$20="Yes",OR(EOMONTH(AN$4,0)<=Settings!$B$5,AN$4>TODAY())),"",IF(EOMONTH(AM$4,0)<=Settings!$B$5,N(Settings!$C$20),N(Calc!$AF$42))) | AO8: =IF(OR(Settings!$A$20="",Settings!$F$20="Yes",OR(EOMONTH(AO$4,0)<=Settings!$B$5,AO$4>TODAY())),"",IF(EOMONTH(AN$4,0)<=Settings!$B$5,N(Settings!$C$20),N(Calc!$AF$43))) | AP8: =IF(OR(Settings!$A$20="",Settings!$F$20="Yes",OR(EOMONTH(AP$4,0)<=Settings!$B$5,AP$4>TODAY())),"",IF(EOMONTH(AO$4,0)<=Settings!$B$5,N(Settings!$C$20),N(Calc!$AF$44))) | AQ8: =IF(OR(Settings!$A$20="",Settings!$F$20="Yes",OR(EOMONTH(AQ$4,0)<=Settings!$B$5,AQ$4>TODAY())),"",IF(EOMONTH(AP$4,0)<=Settings!$B$5,N(Settings!$C$20),N(Calc!$AF$45))) | AR8: =IF(OR(Settings!$A$20="",Settings!$F$20="Yes",OR(EOMONTH(AR$4,0)<=Settings!$B$5,AR$4>TODAY())),"",IF(EOMONTH(AQ$4,0)<=Settings!$B$5,N(Settings!$C$20),N(Calc!$AF$46))) | AS8: =IF(OR(Settings!$A$20="",Settings!$F$20="Yes",OR(EOMONTH(AS$4,0)<=Settings!$B$5,AS$4>TODAY())),"",IF(EOMONTH(AR$4,0)<=Settings!$B$5,N(Settings!$C$20),N(Calc!$AF$47))) | AT8: =IF(OR(Settings!$A$20="",Settings!$F$20="Yes",OR(EOMONTH(AT$4,0)<=Settings!$B$5,AT$4>TODAY())),"",IF(EOMONTH(AS$4,0)<=Settings!$B$5,N(Settings!$C$20),N(Calc!$AF$48))) | AU8: =IF(OR(Settings!$A$20="",Settings!$F$20="Yes",OR(EOMONTH(AU$4,0)<=Settings!$B$5,AU$4>TODAY())),"",IF(EOMONTH(AT$4,0)<=Settings!$B$5,N(Settings!$C$20),N(Calc!$AF$49))) | AV8: =IF(OR(Settings!$A$20="",Settings!$F$20="Yes",OR(EOMONTH(AV$4,0)<=Settings!$B$5,AV$4>TODAY())),"",IF(EOMONTH(AU$4,0)<=Settings!$B$5,N(Settings!$C$20),N(Calc!$AF$50))) | AW8: =IF(OR(Settings!$A$20="",Settings!$F$20="Yes",OR(EOMONTH(AW$4,0)<=Settings!$B$5,AW$4>TODAY())),"",IF(EOMONTH(AV$4,0)<=Settings!$B$5,N(Settings!$C$20),N(Calc!$AF$51))) | AX8: =IF(OR(Settings!$A$20="",Settings!$F$20="Yes",OR(EOMONTH(AX$4,0)<=Settings!$B$5,AX$4>TODAY())),"",IF(EOMONTH(AW$4,0)<=Settings!$B$5,N(Settings!$C$20),N(Calc!$AF$52))) | AY8: =IF(OR(Settings!$A$20="",Settings!$F$20="Yes",OR(EOMONTH(AY$4,0)<=Settings!$B$5,AY$4>TODAY())),"",IF(EOMONTH(AX$4,0)<=Settings!$B$5,N(Settings!$C$20),N(Calc!$AF$53))) | AZ8: =IF(OR(Settings!$A$20="",Settings!$F$20="Yes",OR(EOMONTH(AZ$4,0)<=Settings!$B$5,AZ$4>TODAY())),"",IF(EOMONTH(AY$4,0)<=Settings!$B$5,N(Settings!$C$20),N(Calc!$AF$54))) | BA8: =IF(OR(Settings!$A$20="",Settings!$F$20="Yes",OR(EOMONTH(BA$4,0)<=Settings!$B$5,BA$4>TODAY())),"",IF(EOMONTH(AZ$4,0)<=Settings!$B$5,N(Settings!$C$20),N(Calc!$AF$55))) | BB8: =IF(OR(Settings!$A$20="",Settings!$F$20="Yes",OR(EOMONTH(BB$4,0)<=Settings!$B$5,BB$4>TODAY())),"",IF(EOMONTH(BA$4,0)<=Settings!$B$5,N(Settings!$C$20),N(Calc!$AF$56))) | BC8: =IF(OR(Settings!$A$20="",Settings!$F$20="Yes",OR(EOMONTH(BC$4,0)<=Settings!$B$5,BC$4>TODAY())),"",IF(EOMONTH(BB$4,0)<=Settings!$B$5,N(Settings!$C$20),N(Calc!$AF$57))) | BD8: =IF(OR(Settings!$A$20="",Settings!$F$20="Yes",OR(EOMONTH(BD$4,0)<=Settings!$B$5,BD$4>TODAY())),"",IF(EOMONTH(BC$4,0)<=Settings!$B$5,N(Settings!$C$20),N(Calc!$AF$58))) | BE8: =IF(OR(Settings!$A$20="",Settings!$F$20="Yes",OR(EOMONTH(BE$4,0)<=Settings!$B$5,BE$4>TODAY())),"",IF(EOMONTH(BD$4,0)<=Settings!$B$5,N(Settings!$C$20),N(Calc!$AF$59))) | BF8: =IF(OR(Settings!$A$20="",Settings!$F$20="Yes",OR(EOMONTH(BF$4,0)<=Settings!$B$5,BF$4>TODAY())),"",IF(EOMONTH(BE$4,0)<=Settings!$B$5,N(Settings!$C$20),N(Calc!$AF$60))) | BG8: =IF(OR(Settings!$A$20="",Settings!$F$20="Yes",OR(EOMONTH(BG$4,0)<=Settings!$B$5,BG$4>TODAY())),"",IF(EOMONTH(BF$4,0)<=Settings!$B$5,N(Settings!$C$20),N(Calc!$AF$61))) | BH8: =IF(OR(Settings!$A$20="",Settings!$F$20="Yes",OR(EOMONTH(BH$4,0)<=Settings!$B$5,BH$4>TODAY())),"",IF(EOMONTH(BG$4,0)<=Settings!$B$5,N(Settings!$C$20),N(Calc!$AF$62))) | BI8: =IF(OR(Settings!$A$20="",Settings!$F$20="Yes",OR(EOMONTH(BI$4,0)<=Settings!$B$5,BI$4>TODAY())),"",IF(EOMONTH(BH$4,0)<=Settings!$B$5,N(Settings!$C$20),N(Calc!$AF$63))) | BJ8: =IF(OR(Settings!$A$20="",Settings!$F$20="Yes",OR(EOMONTH(BJ$4,0)<=Settings!$B$5,BJ$4>TODAY())),"",IF(EOMONTH(BI$4,0)<=Settings!$B$5,N(Settings!$C$20),N(Calc!$AF$64))) | BK8: =IF(OR(Settings!$A$20="",Settings!$F$20="Yes",OR(EOMONTH(BK$4,0)<=Settings!$B$5,BK$4>TODAY())),"",IF(EOMONTH(BJ$4,0)<=Settings!$B$5,N(Settings!$C$20),N(Calc!$AF$65))) | BL8: =IF(OR(Settings!$A$20="",Settings!$F$20="Yes",OR(EOMONTH(BL$4,0)<=Settings!$B$5,BL$4>TODAY())),"",IF(EOMONTH(BK$4,0)<=Settings!$B$5,N(Settings!$C$20),N(Calc!$AF$66))) | BM8: =IF(OR(Settings!$A$20="",Settings!$F$20="Yes",OR(EOMONTH(BM$4,0)<=Settings!$B$5,BM$4>TODAY())),"",IF(EOMONTH(BL$4,0)<=Settings!$B$5,N(Settings!$C$20),N(Calc!$AF$67))) | BN8: =IF(OR(Settings!$A$20="",Settings!$F$20="Yes",OR(EOMONTH(BN$4,0)<=Settings!$B$5,BN$4>TODAY())),"",IF(EOMONTH(BM$4,0)<=Settings!$B$5,N(Settings!$C$20),N(Calc!$AF$68))) | BO8: =IF(OR(Settings!$A$20="",Settings!$F$20="Yes",OR(EOMONTH(BO$4,0)<=Settings!$B$5,BO$4>TODAY())),"",IF(EOMONTH(BN$4,0)<=Settings!$B$5,N(Settings!$C$20),N(Calc!$AF$69))) | BP8: =IF(OR(Settings!$A$20="",Settings!$F$20="Yes",OR(EOMONTH(BP$4,0)<=Settings!$B$5,BP$4>TODAY())),"",IF(EOMONTH(BO$4,0)<=Settings!$B$5,N(Settings!$C$20),N(Calc!$AF$70))) | BQ8: =IF(OR(Settings!$A$20="",Settings!$F$20="Yes",OR(EOMONTH(BQ$4,0)<=Settings!$B$5,BQ$4>TODAY())),"",IF(EOMONTH(BP$4,0)<=Settings!$B$5,N(Settings!$C$20),N(Calc!$AF$71))) | BR8: =IF(OR(Settings!$A$20="",Settings!$F$20="Yes",OR(EOMONTH(BR$4,0)<=Settings!$B$5,BR$4>TODAY())),"",IF(EOMONTH(BQ$4,0)<=Settings!$B$5,N(Settings!$C$20),N(Calc!$AF$72))) | BS8: =IF(OR(Settings!$A$20="",Settings!$F$20="Yes",OR(EOMONTH(BS$4,0)<=Settings!$B$5,BS$4>TODAY())),"",IF(EOMONTH(BR$4,0)<=Settings!$B$5,N(Settings!$C$20),N(Calc!$AF$73))) | BT8: =IF(OR(Settings!$A$20="",Settings!$F$20="Yes",OR(EOMONTH(BT$4,0)<=Settings!$B$5,BT$4>TODAY())),"",IF(EOMONTH(BS$4,0)<=Settings!$B$5,N(Settings!$C$20),N(Calc!$AF$74))) | BU8: =IF(OR(Settings!$A$20="",Settings!$F$20="Yes",OR(EOMONTH(BU$4,0)<=Settings!$B$5,BU$4>TODAY())),"",IF(EOMONTH(BT$4,0)<=Settings!$B$5,N(Settings!$C$20),N(Calc!$AF$75))) | BV8: =IF(OR(Settings!$A$20="",Settings!$F$20="Yes",OR(EOMONTH(BV$4,0)<=Settings!$B$5,BV$4>TODAY())),"",IF(EOMONTH(BU$4,0)<=Settings!$B$5,N(Settings!$C$20),N(Calc!$AF$76))) | BW8: =IF(OR(Settings!$A$20="",Settings!$F$20="Yes",OR(EOMONTH(BW$4,0)<=Settings!$B$5,BW$4>TODAY())),"",IF(EOMONTH(BV$4,0)<=Settings!$B$5,N(Settings!$C$20),N(Calc!$AF$77))) | BX8: =IF(OR(Settings!$A$20="",Settings!$F$20="Yes",OR(EOMONTH(BX$4,0)<=Settings!$B$5,BX$4>TODAY())),"",IF(EOMONTH(BW$4,0)<=Settings!$B$5,N(Settings!$C$20),N(Calc!$AF$78))) | BY8: =IF(OR(Settings!$A$20="",Settings!$F$20="Yes",OR(EOMONTH(BY$4,0)<=Settings!$B$5,BY$4>TODAY())),"",IF(EOMONTH(BX$4,0)<=Settings!$B$5,N(Settings!$C$20),N(Calc!$AF$79))) | BZ8: =IF(OR(Settings!$A$20="",Settings!$F$20="Yes",OR(EOMONTH(BZ$4,0)<=Settings!$B$5,BZ$4>TODAY())),"",IF(EOMONTH(BY$4,0)<=Settings!$B$5,N(Settings!$C$20),N(Calc!$AF$80))) | CA8: =IF(OR(Settings!$A$20="",Settings!$F$20="Yes",OR(EOMONTH(CA$4,0)<=Settings!$B$5,CA$4>TODAY())),"",IF(EOMONTH(BZ$4,0)<=Settings!$B$5,N(Settings!$C$20),N(Calc!$AF$81))) | CB8: =IF(OR(Settings!$A$20="",Settings!$F$20="Yes",OR(EOMONTH(CB$4,0)<=Settings!$B$5,CB$4>TODAY())),"",IF(EOMONTH(CA$4,0)<=Settings!$B$5,N(Settings!$C$20),N(Calc!$AF$82))) | CC8: =IF(OR(Settings!$A$20="",Settings!$F$20="Yes",OR(EOMONTH(CC$4,0)<=Settings!$B$5,CC$4>TODAY())),"",IF(EOMONTH(CB$4,0)<=Settings!$B$5,N(Settings!$C$20),N(Calc!$AF$83))) | CD8: =IF(OR(Settings!$A$20="",Settings!$F$20="Yes",OR(EOMONTH(CD$4,0)<=Settings!$B$5,CD$4>TODAY())),"",IF(EOMONTH(CC$4,0)<=Settings!$B$5,N(Settings!$C$20),N(Calc!$AF$84))) | CE8: =IF(OR(Settings!$A$20="",Settings!$F$20="Yes",OR(EOMONTH(CE$4,0)<=Settings!$B$5,CE$4>TODAY())),"",IF(EOMONTH(CD$4,0)<=Settings!$B$5,N(Settings!$C$20),N(Calc!$AF$85))) | CF8: =IF(OR(Settings!$A$20="",Settings!$F$20="Yes",OR(EOMONTH(CF$4,0)<=Settings!$B$5,CF$4>TODAY())),"",IF(EOMONTH(CE$4,0)<=Settings!$B$5,N(Settings!$C$20),N(Calc!$AF$86))) | CG8: =IF(OR(Settings!$A$20="",Settings!$F$20="Yes",OR(EOMONTH(CG$4,0)<=Settings!$B$5,CG$4>TODAY())),"",IF(EOMONTH(CF$4,0)<=Settings!$B$5,N(Settings!$C$20),N(Calc!$AF$87))) | CH8: =IF(OR(Settings!$A$20="",Settings!$F$20="Yes",OR(EOMONTH(CH$4,0)<=Settings!$B$5,CH$4>TODAY())),"",IF(EOMONTH(CG$4,0)<=Settings!$B$5,N(Settings!$C$20),N(Calc!$AF$88))) | CI8: =IF(OR(Settings!$A$20="",Settings!$F$20="Yes",OR(EOMONTH(CI$4,0)<=Settings!$B$5,CI$4>TODAY())),"",IF(EOMONTH(CH$4,0)<=Settings!$B$5,N(Settings!$C$20),N(Calc!$AF$89))) | CJ8: =IF(OR(Settings!$A$20="",Settings!$F$20="Yes",OR(EOMONTH(CJ$4,0)<=Settings!$B$5,CJ$4>TODAY())),"",IF(EOMONTH(CI$4,0)<=Settings!$B$5,N(Settings!$C$20),N(Calc!$AF$90))) | CK8: =IF(OR(Settings!$A$20="",Settings!$F$20="Yes",OR(EOMONTH(CK$4,0)<=Settings!$B$5,CK$4>TODAY())),"",IF(EOMONTH(CJ$4,0)<=Settings!$B$5,N(Settings!$C$20),N(Calc!$AF$91))) | CL8: =IF(OR(Settings!$A$20="",Settings!$F$20="Yes",OR(EOMONTH(CL$4,0)<=Settings!$B$5,CL$4>TODAY())),"",IF(EOMONTH(CK$4,0)<=Settings!$B$5,N(Settings!$C$20),N(Calc!$AF$92))) | CM8: =IF(OR(Settings!$A$20="",Settings!$F$20="Yes",OR(EOMONTH(CM$4,0)<=Settings!$B$5,CM$4>TODAY())),"",IF(EOMONTH(CL$4,0)<=Settings!$B$5,N(Settings!$C$20),N(Calc!$AF$93))) | CN8: =IF(OR(Settings!$A$20="",Settings!$F$20="Yes",OR(EOMONTH(CN$4,0)<=Settings!$B$5,CN$4>TODAY())),"",IF(EOMONTH(CM$4,0)<=Settings!$B$5,N(Settings!$C$20),N(Calc!$AF$94))) | CO8: =IF(OR(Settings!$A$20="",Settings!$F$20="Yes",OR(EOMONTH(CO$4,0)<=Settings!$B$5,CO$4>TODAY())),"",IF(EOMONTH(CN$4,0)<=Settings!$B$5,N(Settings!$C$20),N(Calc!$AF$95))) | CP8: =IF(OR(Settings!$A$20="",Settings!$F$20="Yes",OR(EOMONTH(CP$4,0)<=Settings!$B$5,CP$4>TODAY())),"",IF(EOMONTH(CO$4,0)<=Settings!$B$5,N(Settings!$C$20),N(Calc!$AF$96))) | CQ8: =IF(OR(Settings!$A$20="",Settings!$F$20="Yes",OR(EOMONTH(CQ$4,0)<=Settings!$B$5,CQ$4>TODAY())),"",IF(EOMONTH(CP$4,0)<=Settings!$B$5,N(Settings!$C$20),N(Calc!$AF$97))) | CR8: =IF(OR(Settings!$A$20="",Settings!$F$20="Yes",OR(EOMONTH(CR$4,0)<=Settings!$B$5,CR$4>TODAY())),"",IF(EOMONTH(CQ$4,0)<=Settings!$B$5,N(Settings!$C$20),N(Calc!$AF$98))) | CS8: =IF(OR(Settings!$A$20="",Settings!$F$20="Yes",OR(EOMONTH(CS$4,0)<=Settings!$B$5,CS$4>TODAY())),"",IF(EOMONTH(CR$4,0)<=Settings!$B$5,N(Settings!$C$20),N(Calc!$AF$99))) | CT8: =IF(OR(Settings!$A$20="",Settings!$F$20="Yes",OR(EOMONTH(CT$4,0)<=Settings!$B$5,CT$4>TODAY())),"",IF(EOMONTH(CS$4,0)<=Settings!$B$5,N(Settings!$C$20),N(Calc!$AF$100))) | CU8: =IF(OR(Settings!$A$20="",Settings!$F$20="Yes",OR(EOMONTH(CU$4,0)<=Settings!$B$5,CU$4>TODAY())),"",IF(EOMONTH(CT$4,0)<=Settings!$B$5,N(Settings!$C$20),N(Calc!$AF$101))) | CV8: =IF(OR(Settings!$A$20="",Settings!$F$20="Yes",OR(EOMONTH(CV$4,0)<=Settings!$B$5,CV$4>TODAY())),"",IF(EOMONTH(CU$4,0)<=Settings!$B$5,N(Settings!$C$20),N(Calc!$AF$102))) | CW8: =IF(OR(Settings!$A$20="",Settings!$F$20="Yes",OR(EOMONTH(CW$4,0)<=Settings!$B$5,CW$4>TODAY())),"",IF(EOMONTH(CV$4,0)<=Settings!$B$5,N(Settings!$C$20),N(Calc!$AF$103))) | CX8: =IF(OR(Settings!$A$20="",Settings!$F$20="Yes",OR(EOMONTH(CX$4,0)<=Settings!$B$5,CX$4>TODAY())),"",IF(EOMONTH(CW$4,0)<=Settings!$B$5,N(Settings!$C$20),N(Calc!$AF$104))) | CY8: =IF(OR(Settings!$A$20="",Settings!$F$20="Yes",OR(EOMONTH(CY$4,0)<=Settings!$B$5,CY$4>TODAY())),"",IF(EOMONTH(CX$4,0)<=Settings!$B$5,N(Settings!$C$20),N(Calc!$AF$105))) | CZ8: =IF(OR(Settings!$A$20="",Settings!$F$20="Yes",OR(EOMONTH(CZ$4,0)<=Settings!$B$5,CZ$4>TODAY())),"",IF(EOMONTH(CY$4,0)<=Settings!$B$5,N(Settings!$C$20),N(Calc!$AF$106))) | DA8: =IF(OR(Settings!$A$20="",Settings!$F$20="Yes",OR(EOMONTH(DA$4,0)<=Settings!$B$5,DA$4>TODAY())),"",IF(EOMONTH(CZ$4,0)<=Settings!$B$5,N(Settings!$C$20),N(Calc!$AF$107))) | DB8: =IF(OR(Settings!$A$20="",Settings!$F$20="Yes",OR(EOMONTH(DB$4,0)<=Settings!$B$5,DB$4>TODAY())),"",IF(EOMONTH(DA$4,0)<=Settings!$B$5,N(Settings!$C$20),N(Calc!$AF$108))) | DC8: =IF(OR(Settings!$A$20="",Settings!$F$20="Yes",OR(EOMONTH(DC$4,0)<=Settings!$B$5,DC$4>TODAY())),"",IF(EOMONTH(DB$4,0)<=Settings!$B$5,N(Settings!$C$20),N(Calc!$AF$109))) | DD8: =IF(OR(Settings!$A$20="",Settings!$F$20="Yes",OR(EOMONTH(DD$4,0)<=Settings!$B$5,DD$4>TODAY())),"",IF(EOMONTH(DC$4,0)<=Settings!$B$5,N(Settings!$C$20),N(Calc!$AF$110))) | DE8: =IF(OR(Settings!$A$20="",Settings!$F$20="Yes",OR(EOMONTH(DE$4,0)<=Settings!$B$5,DE$4>TODAY())),"",IF(EOMONTH(DD$4,0)<=Settings!$B$5,N(Settings!$C$20),N(Calc!$AF$111))) | DF8: =IF(OR(Settings!$A$20="",Settings!$F$20="Yes",OR(EOMONTH(DF$4,0)<=Settings!$B$5,DF$4>TODAY())),"",IF(EOMONTH(DE$4,0)<=Settings!$B$5,N(Settings!$C$20),N(Calc!$AF$112))) | DG8: =IF(OR(Settings!$A$20="",Settings!$F$20="Yes",OR(EOMONTH(DG$4,0)<=Settings!$B$5,DG$4>TODAY())),"",IF(EOMONTH(DF$4,0)<=Settings!$B$5,N(Settings!$C$20),N(Calc!$AF$113))) | DH8: =IF(OR(Settings!$A$20="",Settings!$F$20="Yes",OR(EOMONTH(DH$4,0)<=Settings!$B$5,DH$4>TODAY())),"",IF(EOMONTH(DG$4,0)<=Settings!$B$5,N(Settings!$C$20),N(Calc!$AF$114))) | DI8: =IF(OR(Settings!$A$20="",Settings!$F$20="Yes",OR(EOMONTH(DI$4,0)<=Settings!$B$5,DI$4>TODAY())),"",IF(EOMONTH(DH$4,0)<=Settings!$B$5,N(Settings!$C$20),N(Calc!$AF$115))) | DJ8: =IF(OR(Settings!$A$20="",Settings!$F$20="Yes",OR(EOMONTH(DJ$4,0)<=Settings!$B$5,DJ$4>TODAY())),"",IF(EOMONTH(DI$4,0)<=Settings!$B$5,N(Settings!$C$20),N(Calc!$AF$116))) | DK8: =IF(OR(Settings!$A$20="",Settings!$F$20="Yes",OR(EOMONTH(DK$4,0)<=Settings!$B$5,DK$4>TODAY())),"",IF(EOMONTH(DJ$4,0)<=Settings!$B$5,N(Settings!$C$20),N(Calc!$AF$117))) | DL8: =IF(OR(Settings!$A$20="",Settings!$F$20="Yes",OR(EOMONTH(DL$4,0)<=Settings!$B$5,DL$4>TODAY())),"",IF(EOMONTH(DK$4,0)<=Settings!$B$5,N(Settings!$C$20),N(Calc!$AF$118))) | DM8: =IF(OR(Settings!$A$20="",Settings!$F$20="Yes",OR(EOMONTH(DM$4,0)<=Settings!$B$5,DM$4>TODAY())),"",IF(EOMONTH(DL$4,0)<=Settings!$B$5,N(Settings!$C$20),N(Calc!$AF$119))) | DN8: =IF(OR(Settings!$A$20="",Settings!$F$20="Yes",OR(EOMONTH(DN$4,0)<=Settings!$B$5,DN$4>TODAY())),"",IF(EOMONTH(DM$4,0)<=Settings!$B$5,N(Settings!$C$20),N(Calc!$AF$120))) | DO8: =IF(OR(Settings!$A$20="",Settings!$F$20="Yes",OR(EOMONTH(DO$4,0)<=Settings!$B$5,DO$4>TODAY())),"",IF(EOMONTH(DN$4,0)<=Settings!$B$5,N(Settings!$C$20),N(Calc!$AF$121))) | DP8: =IF(OR(Settings!$A$20="",Settings!$F$20="Yes",OR(EOMONTH(DP$4,0)<=Settings!$B$5,DP$4>TODAY())),"",IF(EOMONTH(DO$4,0)<=Settings!$B$5,N(Settings!$C$20),N(Calc!$AF$122))) | DQ8: =IF(OR(Settings!$A$20="",Settings!$F$20="Yes",OR(EOMONTH(DQ$4,0)<=Settings!$B$5,DQ$4>TODAY())),"",IF(EOMONTH(DP$4,0)<=Settings!$B$5,N(Settings!$C$20),N(Calc!$AF$123))) | DR8: =IF(OR(Settings!$A$20="",Settings!$F$20="Yes",OR(EOMONTH(DR$4,0)<=Settings!$B$5,DR$4>TODAY())),"",IF(EOMONTH(DQ$4,0)<=Settings!$B$5,N(Settings!$C$20),N(Calc!$AF$124))) | DS8: =IF(OR(Settings!$A$20="",Settings!$F$20="Yes",OR(EOMONTH(DS$4,0)<=Settings!$B$5,DS$4>TODAY())),"",IF(EOMONTH(DR$4,0)<=Settings!$B$5,N(Settings!$C$20),N(Calc!$AF$125))) | DT8: =IF(OR(Settings!$A$20="",Settings!$F$20="Yes",OR(EOMONTH(DT$4,0)<=Settings!$B$5,DT$4>TODAY())),"",IF(EOMONTH(DS$4,0)<=Settings!$B$5,N(Settings!$C$20),N(Calc!$AF$126))) | DU8: =IF(OR(Settings!$A$20="",Settings!$F$20="Yes",OR(EOMONTH(DU$4,0)<=Settings!$B$5,DU$4>TODAY())),"",IF(EOMONTH(DT$4,0)<=Settings!$B$5,N(Settings!$C$20),N(Calc!$AF$127))) | DV8: =IF(OR(Settings!$A$20="",Settings!$F$20="Yes",OR(EOMONTH(DV$4,0)<=Settings!$B$5,DV$4>TODAY())),"",IF(EOMONTH(DU$4,0)<=Settings!$B$5,N(Settings!$C$20),N(Calc!$AF$128))) | DW8: =IF(OR(Settings!$A$20="",Settings!$F$20="Yes",OR(EOMONTH(DW$4,0)<=Settings!$B$5,DW$4>TODAY())),"",IF(EOMONTH(DV$4,0)<=Settings!$B$5,N(Settings!$C$20),N(Calc!$AF$129))) | DX8: =IF(OR(Settings!$A$20="",Settings!$F$20="Yes",OR(EOMONTH(DX$4,0)<=Settings!$B$5,DX$4>TODAY())),"",IF(EOMONTH(DW$4,0)<=Settings!$B$5,N(Settings!$C$20),N(Calc!$AF$130))) | DY8: =IF(OR(Settings!$A$20="",Settings!$F$20="Yes",OR(EOMONTH(DY$4,0)<=Settings!$B$5,DY$4>TODAY())),"",IF(EOMONTH(DX$4,0)<=Settings!$B$5,N(Settings!$C$20),N(Calc!$AF$131))) | DZ8: =IF(OR(Settings!$A$20="",Settings!$F$20="Yes",OR(EOMONTH(DZ$4,0)<=Settings!$B$5,DZ$4>TODAY())),"",IF(EOMONTH(DY$4,0)<=Settings!$B$5,N(Settings!$C$20),N(Calc!$AF$132))) | EA8: =IF(OR(Settings!$A$20="",Settings!$F$20="Yes",OR(EOMONTH(EA$4,0)<=Settings!$B$5,EA$4>TODAY())),"",IF(EOMONTH(DZ$4,0)<=Settings!$B$5,N(Settings!$C$20),N(Calc!$AF$133))) | EB8: =IF(OR(Settings!$A$20="",Settings!$F$20="Yes",OR(EOMONTH(EB$4,0)<=Settings!$B$5,EB$4>TODAY())),"",IF(EOMONTH(EA$4,0)<=Settings!$B$5,N(Settings!$C$20),N(Calc!$AF$134))) | EC8: =IF(OR(Settings!$A$20="",Settings!$F$20="Yes",OR(EOMONTH(EC$4,0)<=Settings!$B$5,EC$4>TODAY())),"",IF(EOMONTH(EB$4,0)<=Settings!$B$5,N(Settings!$C$20),N(Calc!$AF$135))) | ED8: =IF(OR(Settings!$A$20="",Settings!$F$20="Yes",OR(EOMONTH(ED$4,0)<=Settings!$B$5,ED$4>TODAY())),"",IF(EOMONTH(EC$4,0)<=Settings!$B$5,N(Settings!$C$20),N(Calc!$AF$136))) | EE8: =IF(OR(Settings!$A$20="",Settings!$F$20="Yes",OR(EOMONTH(EE$4,0)<=Settings!$B$5,EE$4>TODAY())),"",IF(EOMONTH(ED$4,0)<=Settings!$B$5,N(Settings!$C$20),N(Calc!$AF$137))) | EF8: =IF(OR(Settings!$A$20="",Settings!$F$20="Yes",OR(EOMONTH(EF$4,0)<=Settings!$B$5,EF$4>TODAY())),"",IF(EOMONTH(EE$4,0)<=Settings!$B$5,N(Settings!$C$20),N(Calc!$AF$138))) | EG8: =IF(OR(Settings!$A$20="",Settings!$F$20="Yes",OR(EOMONTH(EG$4,0)<=Settings!$B$5,EG$4>TODAY())),"",IF(EOMONTH(EF$4,0)<=Settings!$B$5,N(Settings!$C$20),N(Calc!$AF$139))) | EH8: =IF(OR(Settings!$A$20="",Settings!$F$20="Yes",OR(EOMONTH(EH$4,0)<=Settings!$B$5,EH$4>TODAY())),"",IF(EOMONTH(EG$4,0)<=Settings!$B$5,N(Settings!$C$20),N(Calc!$AF$140))) | EI8: =IF(OR(Settings!$A$20="",Settings!$F$20="Yes",OR(EOMONTH(EI$4,0)<=Settings!$B$5,EI$4>TODAY())),"",IF(EOMONTH(EH$4,0)<=Settings!$B$5,N(Settings!$C$20),N(Calc!$AF$141))) | EJ8: =IF(OR(Settings!$A$20="",Settings!$F$20="Yes",OR(EOMONTH(EJ$4,0)<=Settings!$B$5,EJ$4>TODAY())),"",IF(EOMONTH(EI$4,0)<=Settings!$B$5,N(Settings!$C$20),N(Calc!$AF$142))) | EK8: =IF(OR(Settings!$A$20="",Settings!$F$20="Yes",OR(EOMONTH(EK$4,0)<=Settings!$B$5,EK$4>TODAY())),"",IF(EOMONTH(EJ$4,0)<=Settings!$B$5,N(Settings!$C$20),N(Calc!$AF$143))) | EL8: =IF(OR(Settings!$A$20="",Settings!$F$20="Yes",OR(EOMONTH(EL$4,0)<=Settings!$B$5,EL$4>TODAY())),"",IF(EOMONTH(EK$4,0)<=Settings!$B$5,N(Settings!$C$20),N(Calc!$AF$144))) | EM8: =IF(OR(Settings!$A$20="",Settings!$F$20="Yes",OR(EOMONTH(EM$4,0)<=Settings!$B$5,EM$4>TODAY())),"",IF(EOMONTH(EL$4,0)<=Settings!$B$5,N(Settings!$C$20),N(Calc!$AF$145))) | EN8: =IF(OR(Settings!$A$20="",Settings!$F$20="Yes",OR(EOMONTH(EN$4,0)<=Settings!$B$5,EN$4>TODAY())),"",IF(EOMONTH(EM$4,0)<=Settings!$B$5,N(Settings!$C$20),N(Calc!$AF$146))) | EO8: =IF(OR(Settings!$A$20="",Settings!$F$20="Yes",OR(EOMONTH(EO$4,0)<=Settings!$B$5,EO$4>TODAY())),"",IF(EOMONTH(EN$4,0)<=Settings!$B$5,N(Settings!$C$20),N(Calc!$AF$147))) | EP8: =IF(OR(Settings!$A$20="",Settings!$F$20="Yes",OR(EOMONTH(EP$4,0)<=Settings!$B$5,EP$4>TODAY())),"",IF(EOMONTH(EO$4,0)<=Settings!$B$5,N(Settings!$C$20),N(Calc!$AF$148))) | EQ8: =IF(OR(Settings!$A$20="",Settings!$F$20="Yes",OR(EOMONTH(EQ$4,0)<=Settings!$B$5,EQ$4>TODAY())),"",IF(EOMONTH(EP$4,0)<=Settings!$B$5,N(Settings!$C$20),N(Calc!$AF$149))) | ER8: =IF(OR(Settings!$A$20="",Settings!$F$20="Yes",OR(EOMONTH(ER$4,0)<=Settings!$B$5,ER$4>TODAY())),"",IF(EOMONTH(EQ$4,0)<=Settings!$B$5,N(Settings!$C$20),N(Calc!$AF$150))) | ES8: =IF(OR(Settings!$A$20="",Settings!$F$20="Yes",OR(EOMONTH(ES$4,0)<=Settings!$B$5,ES$4>TODAY())),"",IF(EOMONTH(ER$4,0)<=Settings!$B$5,N(Settings!$C$20),N(Calc!$AF$151))) | ET8: =IF(OR(Settings!$A$20="",Settings!$F$20="Yes",OR(EOMONTH(ET$4,0)<=Settings!$B$5,ET$4>TODAY())),"",IF(EOMONTH(ES$4,0)<=Settings!$B$5,N(Settings!$C$20),N(Calc!$AF$152))) | EU8: =IF(OR(Settings!$A$20="",Settings!$F$20="Yes",OR(EOMONTH(EU$4,0)<=Settings!$B$5,EU$4>TODAY())),"",IF(EOMONTH(ET$4,0)<=Settings!$B$5,N(Settings!$C$20),N(Calc!$AF$153))) | EV8: =IF(OR(Settings!$A$20="",Settings!$F$20="Yes",OR(EOMONTH(EV$4,0)<=Settings!$B$5,EV$4>TODAY())),"",IF(EOMONTH(EU$4,0)<=Settings!$B$5,N(Settings!$C$20),N(Calc!$AF$154))) | EW8: =IF(OR(Settings!$A$20="",Settings!$F$20="Yes",OR(EOMONTH(EW$4,0)<=Settings!$B$5,EW$4>TODAY())),"",IF(EOMONTH(EV$4,0)<=Settings!$B$5,N(Settings!$C$20),N(Calc!$AF$155))) | EX8: =IF(OR(Settings!$A$20="",Settings!$F$20="Yes",OR(EOMONTH(EX$4,0)<=Settings!$B$5,EX$4>TODAY())),"",IF(EOMONTH(EW$4,0)<=Settings!$B$5,N(Settings!$C$20),N(Calc!$AF$156))) | EY8: =IF(OR(Settings!$A$20="",Settings!$F$20="Yes",OR(EOMONTH(EY$4,0)<=Settings!$B$5,EY$4>TODAY())),"",IF(EOMONTH(EX$4,0)<=Settings!$B$5,N(Settings!$C$20),N(Calc!$AF$157))) | EZ8: =IF(OR(Settings!$A$20="",Settings!$F$20="Yes",OR(EOMONTH(EZ$4,0)<=Settings!$B$5,EZ$4>TODAY())),"",IF(EOMONTH(EY$4,0)<=Settings!$B$5,N(Settings!$C$20),N(Calc!$AF$158))) | FA8: =IF(OR(Settings!$A$20="",Settings!$F$20="Yes",OR(EOMONTH(FA$4,0)<=Settings!$B$5,FA$4>TODAY())),"",IF(EOMONTH(EZ$4,0)<=Settings!$B$5,N(Settings!$C$20),N(Calc!$AF$159))) | FB8: =IF(OR(Settings!$A$20="",Settings!$F$20="Yes",OR(EOMONTH(FB$4,0)<=Settings!$B$5,FB$4>TODAY())),"",IF(EOMONTH(FA$4,0)<=Settings!$B$5,N(Settings!$C$20),N(Calc!$AF$160))) | FC8: =IF(OR(Settings!$A$20="",Settings!$F$20="Yes",OR(EOMONTH(FC$4,0)<=Settings!$B$5,FC$4>TODAY())),"",IF(EOMONTH(FB$4,0)<=Settings!$B$5,N(Settings!$C$20),N(Calc!$AF$161))) | FD8: =IF(OR(Settings!$A$20="",Settings!$F$20="Yes",OR(EOMONTH(FD$4,0)<=Settings!$B$5,FD$4>TODAY())),"",IF(EOMONTH(FC$4,0)<=Settings!$B$5,N(Settings!$C$20),N(Calc!$AF$162))) | FE8: =IF(OR(Settings!$A$20="",Settings!$F$20="Yes",OR(EOMONTH(FE$4,0)<=Settings!$B$5,FE$4>TODAY())),"",IF(EOMONTH(FD$4,0)<=Settings!$B$5,N(Settings!$C$20),N(Calc!$AF$163))) | FF8: =IF(OR(Settings!$A$20="",Settings!$F$20="Yes",OR(EOMONTH(FF$4,0)<=Settings!$B$5,FF$4>TODAY())),"",IF(EOMONTH(FE$4,0)<=Settings!$B$5,N(Settings!$C$20),N(Calc!$AF$164))) | FG8: =IF(OR(Settings!$A$20="",Settings!$F$20="Yes",OR(EOMONTH(FG$4,0)<=Settings!$B$5,FG$4>TODAY())),"",IF(EOMONTH(FF$4,0)<=Settings!$B$5,N(Settings!$C$20),N(Calc!$AF$165))) | FH8: =IF(OR(Settings!$A$20="",Settings!$F$20="Yes",OR(EOMONTH(FH$4,0)<=Settings!$B$5,FH$4>TODAY())),"",IF(EOMONTH(FG$4,0)<=Settings!$B$5,N(Settings!$C$20),N(Calc!$AF$166))) | FI8: =IF(OR(Settings!$A$20="",Settings!$F$20="Yes",OR(EOMONTH(FI$4,0)<=Settings!$B$5,FI$4>TODAY())),"",IF(EOMONTH(FH$4,0)<=Settings!$B$5,N(Settings!$C$20),N(Calc!$AF$167))) | FJ8: =IF(OR(Settings!$A$20="",Settings!$F$20="Yes",OR(EOMONTH(FJ$4,0)<=Settings!$B$5,FJ$4>TODAY())),"",IF(EOMONTH(FI$4,0)<=Settings!$B$5,N(Settings!$C$20),N(Calc!$AF$168))) | FK8: =IF(OR(Settings!$A$20="",Settings!$F$20="Yes",OR(EOMONTH(FK$4,0)<=Settings!$B$5,FK$4>TODAY())),"",IF(EOMONTH(FJ$4,0)<=Settings!$B$5,N(Settings!$C$20),N(Calc!$AF$169))) | FL8: =IF(OR(Settings!$A$20="",Settings!$F$20="Yes",OR(EOMONTH(FL$4,0)<=Settings!$B$5,FL$4>TODAY())),"",IF(EOMONTH(FK$4,0)<=Settings!$B$5,N(Settings!$C$20),N(Calc!$AF$170))) | FM8: =IF(OR(Settings!$A$20="",Settings!$F$20="Yes",OR(EOMONTH(FM$4,0)<=Settings!$B$5,FM$4>TODAY())),"",IF(EOMONTH(FL$4,0)<=Settings!$B$5,N(Settings!$C$20),N(Calc!$AF$171))) | FN8: =IF(OR(Settings!$A$20="",Settings!$F$20="Yes",OR(EOMONTH(FN$4,0)<=Settings!$B$5,FN$4>TODAY())),"",IF(EOMONTH(FM$4,0)<=Settings!$B$5,N(Settings!$C$20),N(Calc!$AF$172))) | FO8: =IF(OR(Settings!$A$20="",Settings!$F$20="Yes",OR(EOMONTH(FO$4,0)<=Settings!$B$5,FO$4>TODAY())),"",IF(EOMONTH(FN$4,0)<=Settings!$B$5,N(Settings!$C$20),N(Calc!$AF$173))) | FP8: =IF(OR(Settings!$A$20="",Settings!$F$20="Yes",OR(EOMONTH(FP$4,0)<=Settings!$B$5,FP$4>TODAY())),"",IF(EOMONTH(FO$4,0)<=Settings!$B$5,N(Settings!$C$20),N(Calc!$AF$174))) | FQ8: =IF(OR(Settings!$A$20="",Settings!$F$20="Yes",OR(EOMONTH(FQ$4,0)<=Settings!$B$5,FQ$4>TODAY())),"",IF(EOMONTH(FP$4,0)<=Settings!$B$5,N(Settings!$C$20),N(Calc!$AF$175))) | FR8: =IF(OR(Settings!$A$20="",Settings!$F$20="Yes",OR(EOMONTH(FR$4,0)<=Settings!$B$5,FR$4>TODAY())),"",IF(EOMONTH(FQ$4,0)<=Settings!$B$5,N(Settings!$C$20),N(Calc!$AF$176))) | FS8: =IF(OR(Settings!$A$20="",Settings!$F$20="Yes",OR(EOMONTH(FS$4,0)<=Settings!$B$5,FS$4>TODAY())),"",IF(EOMONTH(FR$4,0)<=Settings!$B$5,N(Settings!$C$20),N(Calc!$AF$177))) | FT8: =IF(OR(Settings!$A$20="",Settings!$F$20="Yes",OR(EOMONTH(FT$4,0)<=Settings!$B$5,FT$4>TODAY())),"",IF(EOMONTH(FS$4,0)<=Settings!$B$5,N(Settings!$C$20),N(Calc!$AF$178))) | FU8: =IF(OR(Settings!$A$20="",Settings!$F$20="Yes",OR(EOMONTH(FU$4,0)<=Settings!$B$5,FU$4>TODAY())),"",IF(EOMONTH(FT$4,0)<=Settings!$B$5,N(Settings!$C$20),N(Calc!$AF$179))) | FV8: =IF(OR(Settings!$A$20="",Settings!$F$20="Yes",OR(EOMONTH(FV$4,0)<=Settings!$B$5,FV$4>TODAY())),"",IF(EOMONTH(FU$4,0)<=Settings!$B$5,N(Settings!$C$20),N(Calc!$AF$180))) | FW8: =IF(OR(Settings!$A$20="",Settings!$F$20="Yes",OR(EOMONTH(FW$4,0)<=Settings!$B$5,FW$4>TODAY())),"",IF(EOMONTH(FV$4,0)<=Settings!$B$5,N(Settings!$C$20),N(Calc!$AF$181))) | FX8: =IF(OR(Settings!$A$20="",Settings!$F$20="Yes",OR(EOMONTH(FX$4,0)<=Settings!$B$5,FX$4>TODAY())),"",IF(EOMONTH(FW$4,0)<=Settings!$B$5,N(Settings!$C$20),N(Calc!$AF$182)))
A9: =IF(Settings!$A$21="","(unused)",Settings!$A$21&IF(Settings!$E$21="No"," (retired)","")) | B9: =IF(Settings!$A$21="","",IF(Settings!$F$21="Yes","REQUIRED","optional · grey = unchanged")&IF(OR(Settings!$B$21="Card",Settings!$B$21="Loan")," · amount owed","")) | C9: =IF(OR(Settings!$A$21="",Settings!$F$21="Yes",OR(EOMONTH(C$4,0)<=Settings!$B$5,C$4>TODAY())),"",N(Settings!$C$21)) | D9: =IF(OR(Settings!$A$21="",Settings!$F$21="Yes",OR(EOMONTH(D$4,0)<=Settings!$B$5,D$4>TODAY())),"",IF(EOMONTH(C$4,0)<=Settings!$B$5,N(Settings!$C$21),N(Calc!$AG$6))) | E9: =IF(OR(Settings!$A$21="",Settings!$F$21="Yes",OR(EOMONTH(E$4,0)<=Settings!$B$5,E$4>TODAY())),"",IF(EOMONTH(D$4,0)<=Settings!$B$5,N(Settings!$C$21),N(Calc!$AG$7))) | F9: =IF(OR(Settings!$A$21="",Settings!$F$21="Yes",OR(EOMONTH(F$4,0)<=Settings!$B$5,F$4>TODAY())),"",IF(EOMONTH(E$4,0)<=Settings!$B$5,N(Settings!$C$21),N(Calc!$AG$8))) | G9: =IF(OR(Settings!$A$21="",Settings!$F$21="Yes",OR(EOMONTH(G$4,0)<=Settings!$B$5,G$4>TODAY())),"",IF(EOMONTH(F$4,0)<=Settings!$B$5,N(Settings!$C$21),N(Calc!$AG$9))) | H9: =IF(OR(Settings!$A$21="",Settings!$F$21="Yes",OR(EOMONTH(H$4,0)<=Settings!$B$5,H$4>TODAY())),"",IF(EOMONTH(G$4,0)<=Settings!$B$5,N(Settings!$C$21),N(Calc!$AG$10))) | I9: =IF(OR(Settings!$A$21="",Settings!$F$21="Yes",OR(EOMONTH(I$4,0)<=Settings!$B$5,I$4>TODAY())),"",IF(EOMONTH(H$4,0)<=Settings!$B$5,N(Settings!$C$21),N(Calc!$AG$11))) | J9: =IF(OR(Settings!$A$21="",Settings!$F$21="Yes",OR(EOMONTH(J$4,0)<=Settings!$B$5,J$4>TODAY())),"",IF(EOMONTH(I$4,0)<=Settings!$B$5,N(Settings!$C$21),N(Calc!$AG$12))) | K9: =IF(OR(Settings!$A$21="",Settings!$F$21="Yes",OR(EOMONTH(K$4,0)<=Settings!$B$5,K$4>TODAY())),"",IF(EOMONTH(J$4,0)<=Settings!$B$5,N(Settings!$C$21),N(Calc!$AG$13))) | L9: =IF(OR(Settings!$A$21="",Settings!$F$21="Yes",OR(EOMONTH(L$4,0)<=Settings!$B$5,L$4>TODAY())),"",IF(EOMONTH(K$4,0)<=Settings!$B$5,N(Settings!$C$21),N(Calc!$AG$14))) | M9: =IF(OR(Settings!$A$21="",Settings!$F$21="Yes",OR(EOMONTH(M$4,0)<=Settings!$B$5,M$4>TODAY())),"",IF(EOMONTH(L$4,0)<=Settings!$B$5,N(Settings!$C$21),N(Calc!$AG$15))) | N9: =IF(OR(Settings!$A$21="",Settings!$F$21="Yes",OR(EOMONTH(N$4,0)<=Settings!$B$5,N$4>TODAY())),"",IF(EOMONTH(M$4,0)<=Settings!$B$5,N(Settings!$C$21),N(Calc!$AG$16))) | O9: =IF(OR(Settings!$A$21="",Settings!$F$21="Yes",OR(EOMONTH(O$4,0)<=Settings!$B$5,O$4>TODAY())),"",IF(EOMONTH(N$4,0)<=Settings!$B$5,N(Settings!$C$21),N(Calc!$AG$17))) | P9: =IF(OR(Settings!$A$21="",Settings!$F$21="Yes",OR(EOMONTH(P$4,0)<=Settings!$B$5,P$4>TODAY())),"",IF(EOMONTH(O$4,0)<=Settings!$B$5,N(Settings!$C$21),N(Calc!$AG$18))) | Q9: =IF(OR(Settings!$A$21="",Settings!$F$21="Yes",OR(EOMONTH(Q$4,0)<=Settings!$B$5,Q$4>TODAY())),"",IF(EOMONTH(P$4,0)<=Settings!$B$5,N(Settings!$C$21),N(Calc!$AG$19))) | R9: =IF(OR(Settings!$A$21="",Settings!$F$21="Yes",OR(EOMONTH(R$4,0)<=Settings!$B$5,R$4>TODAY())),"",IF(EOMONTH(Q$4,0)<=Settings!$B$5,N(Settings!$C$21),N(Calc!$AG$20))) | S9: =IF(OR(Settings!$A$21="",Settings!$F$21="Yes",OR(EOMONTH(S$4,0)<=Settings!$B$5,S$4>TODAY())),"",IF(EOMONTH(R$4,0)<=Settings!$B$5,N(Settings!$C$21),N(Calc!$AG$21))) | T9: =IF(OR(Settings!$A$21="",Settings!$F$21="Yes",OR(EOMONTH(T$4,0)<=Settings!$B$5,T$4>TODAY())),"",IF(EOMONTH(S$4,0)<=Settings!$B$5,N(Settings!$C$21),N(Calc!$AG$22))) | U9: =IF(OR(Settings!$A$21="",Settings!$F$21="Yes",OR(EOMONTH(U$4,0)<=Settings!$B$5,U$4>TODAY())),"",IF(EOMONTH(T$4,0)<=Settings!$B$5,N(Settings!$C$21),N(Calc!$AG$23))) | V9: =IF(OR(Settings!$A$21="",Settings!$F$21="Yes",OR(EOMONTH(V$4,0)<=Settings!$B$5,V$4>TODAY())),"",IF(EOMONTH(U$4,0)<=Settings!$B$5,N(Settings!$C$21),N(Calc!$AG$24))) | W9: =IF(OR(Settings!$A$21="",Settings!$F$21="Yes",OR(EOMONTH(W$4,0)<=Settings!$B$5,W$4>TODAY())),"",IF(EOMONTH(V$4,0)<=Settings!$B$5,N(Settings!$C$21),N(Calc!$AG$25))) | X9: =IF(OR(Settings!$A$21="",Settings!$F$21="Yes",OR(EOMONTH(X$4,0)<=Settings!$B$5,X$4>TODAY())),"",IF(EOMONTH(W$4,0)<=Settings!$B$5,N(Settings!$C$21),N(Calc!$AG$26))) | Y9: =IF(OR(Settings!$A$21="",Settings!$F$21="Yes",OR(EOMONTH(Y$4,0)<=Settings!$B$5,Y$4>TODAY())),"",IF(EOMONTH(X$4,0)<=Settings!$B$5,N(Settings!$C$21),N(Calc!$AG$27))) | Z9: =IF(OR(Settings!$A$21="",Settings!$F$21="Yes",OR(EOMONTH(Z$4,0)<=Settings!$B$5,Z$4>TODAY())),"",IF(EOMONTH(Y$4,0)<=Settings!$B$5,N(Settings!$C$21),N(Calc!$AG$28))) | AA9: =IF(OR(Settings!$A$21="",Settings!$F$21="Yes",OR(EOMONTH(AA$4,0)<=Settings!$B$5,AA$4>TODAY())),"",IF(EOMONTH(Z$4,0)<=Settings!$B$5,N(Settings!$C$21),N(Calc!$AG$29))) | AB9: =IF(OR(Settings!$A$21="",Settings!$F$21="Yes",OR(EOMONTH(AB$4,0)<=Settings!$B$5,AB$4>TODAY())),"",IF(EOMONTH(AA$4,0)<=Settings!$B$5,N(Settings!$C$21),N(Calc!$AG$30))) | AC9: =IF(OR(Settings!$A$21="",Settings!$F$21="Yes",OR(EOMONTH(AC$4,0)<=Settings!$B$5,AC$4>TODAY())),"",IF(EOMONTH(AB$4,0)<=Settings!$B$5,N(Settings!$C$21),N(Calc!$AG$31))) | AD9: =IF(OR(Settings!$A$21="",Settings!$F$21="Yes",OR(EOMONTH(AD$4,0)<=Settings!$B$5,AD$4>TODAY())),"",IF(EOMONTH(AC$4,0)<=Settings!$B$5,N(Settings!$C$21),N(Calc!$AG$32))) | AE9: =IF(OR(Settings!$A$21="",Settings!$F$21="Yes",OR(EOMONTH(AE$4,0)<=Settings!$B$5,AE$4>TODAY())),"",IF(EOMONTH(AD$4,0)<=Settings!$B$5,N(Settings!$C$21),N(Calc!$AG$33))) | AF9: =IF(OR(Settings!$A$21="",Settings!$F$21="Yes",OR(EOMONTH(AF$4,0)<=Settings!$B$5,AF$4>TODAY())),"",IF(EOMONTH(AE$4,0)<=Settings!$B$5,N(Settings!$C$21),N(Calc!$AG$34))) | AG9: =IF(OR(Settings!$A$21="",Settings!$F$21="Yes",OR(EOMONTH(AG$4,0)<=Settings!$B$5,AG$4>TODAY())),"",IF(EOMONTH(AF$4,0)<=Settings!$B$5,N(Settings!$C$21),N(Calc!$AG$35))) | AH9: =IF(OR(Settings!$A$21="",Settings!$F$21="Yes",OR(EOMONTH(AH$4,0)<=Settings!$B$5,AH$4>TODAY())),"",IF(EOMONTH(AG$4,0)<=Settings!$B$5,N(Settings!$C$21),N(Calc!$AG$36))) | AI9: =IF(OR(Settings!$A$21="",Settings!$F$21="Yes",OR(EOMONTH(AI$4,0)<=Settings!$B$5,AI$4>TODAY())),"",IF(EOMONTH(AH$4,0)<=Settings!$B$5,N(Settings!$C$21),N(Calc!$AG$37))) | AJ9: =IF(OR(Settings!$A$21="",Settings!$F$21="Yes",OR(EOMONTH(AJ$4,0)<=Settings!$B$5,AJ$4>TODAY())),"",IF(EOMONTH(AI$4,0)<=Settings!$B$5,N(Settings!$C$21),N(Calc!$AG$38))) | AK9: =IF(OR(Settings!$A$21="",Settings!$F$21="Yes",OR(EOMONTH(AK$4,0)<=Settings!$B$5,AK$4>TODAY())),"",IF(EOMONTH(AJ$4,0)<=Settings!$B$5,N(Settings!$C$21),N(Calc!$AG$39))) | AL9: =IF(OR(Settings!$A$21="",Settings!$F$21="Yes",OR(EOMONTH(AL$4,0)<=Settings!$B$5,AL$4>TODAY())),"",IF(EOMONTH(AK$4,0)<=Settings!$B$5,N(Settings!$C$21),N(Calc!$AG$40))) | AM9: =IF(OR(Settings!$A$21="",Settings!$F$21="Yes",OR(EOMONTH(AM$4,0)<=Settings!$B$5,AM$4>TODAY())),"",IF(EOMONTH(AL$4,0)<=Settings!$B$5,N(Settings!$C$21),N(Calc!$AG$41))) | AN9: =IF(OR(Settings!$A$21="",Settings!$F$21="Yes",OR(EOMONTH(AN$4,0)<=Settings!$B$5,AN$4>TODAY())),"",IF(EOMONTH(AM$4,0)<=Settings!$B$5,N(Settings!$C$21),N(Calc!$AG$42))) | AO9: =IF(OR(Settings!$A$21="",Settings!$F$21="Yes",OR(EOMONTH(AO$4,0)<=Settings!$B$5,AO$4>TODAY())),"",IF(EOMONTH(AN$4,0)<=Settings!$B$5,N(Settings!$C$21),N(Calc!$AG$43))) | AP9: =IF(OR(Settings!$A$21="",Settings!$F$21="Yes",OR(EOMONTH(AP$4,0)<=Settings!$B$5,AP$4>TODAY())),"",IF(EOMONTH(AO$4,0)<=Settings!$B$5,N(Settings!$C$21),N(Calc!$AG$44))) | AQ9: =IF(OR(Settings!$A$21="",Settings!$F$21="Yes",OR(EOMONTH(AQ$4,0)<=Settings!$B$5,AQ$4>TODAY())),"",IF(EOMONTH(AP$4,0)<=Settings!$B$5,N(Settings!$C$21),N(Calc!$AG$45))) | AR9: =IF(OR(Settings!$A$21="",Settings!$F$21="Yes",OR(EOMONTH(AR$4,0)<=Settings!$B$5,AR$4>TODAY())),"",IF(EOMONTH(AQ$4,0)<=Settings!$B$5,N(Settings!$C$21),N(Calc!$AG$46))) | AS9: =IF(OR(Settings!$A$21="",Settings!$F$21="Yes",OR(EOMONTH(AS$4,0)<=Settings!$B$5,AS$4>TODAY())),"",IF(EOMONTH(AR$4,0)<=Settings!$B$5,N(Settings!$C$21),N(Calc!$AG$47))) | AT9: =IF(OR(Settings!$A$21="",Settings!$F$21="Yes",OR(EOMONTH(AT$4,0)<=Settings!$B$5,AT$4>TODAY())),"",IF(EOMONTH(AS$4,0)<=Settings!$B$5,N(Settings!$C$21),N(Calc!$AG$48))) | AU9: =IF(OR(Settings!$A$21="",Settings!$F$21="Yes",OR(EOMONTH(AU$4,0)<=Settings!$B$5,AU$4>TODAY())),"",IF(EOMONTH(AT$4,0)<=Settings!$B$5,N(Settings!$C$21),N(Calc!$AG$49))) | AV9: =IF(OR(Settings!$A$21="",Settings!$F$21="Yes",OR(EOMONTH(AV$4,0)<=Settings!$B$5,AV$4>TODAY())),"",IF(EOMONTH(AU$4,0)<=Settings!$B$5,N(Settings!$C$21),N(Calc!$AG$50))) | AW9: =IF(OR(Settings!$A$21="",Settings!$F$21="Yes",OR(EOMONTH(AW$4,0)<=Settings!$B$5,AW$4>TODAY())),"",IF(EOMONTH(AV$4,0)<=Settings!$B$5,N(Settings!$C$21),N(Calc!$AG$51))) | AX9: =IF(OR(Settings!$A$21="",Settings!$F$21="Yes",OR(EOMONTH(AX$4,0)<=Settings!$B$5,AX$4>TODAY())),"",IF(EOMONTH(AW$4,0)<=Settings!$B$5,N(Settings!$C$21),N(Calc!$AG$52))) | AY9: =IF(OR(Settings!$A$21="",Settings!$F$21="Yes",OR(EOMONTH(AY$4,0)<=Settings!$B$5,AY$4>TODAY())),"",IF(EOMONTH(AX$4,0)<=Settings!$B$5,N(Settings!$C$21),N(Calc!$AG$53))) | AZ9: =IF(OR(Settings!$A$21="",Settings!$F$21="Yes",OR(EOMONTH(AZ$4,0)<=Settings!$B$5,AZ$4>TODAY())),"",IF(EOMONTH(AY$4,0)<=Settings!$B$5,N(Settings!$C$21),N(Calc!$AG$54))) | BA9: =IF(OR(Settings!$A$21="",Settings!$F$21="Yes",OR(EOMONTH(BA$4,0)<=Settings!$B$5,BA$4>TODAY())),"",IF(EOMONTH(AZ$4,0)<=Settings!$B$5,N(Settings!$C$21),N(Calc!$AG$55))) | BB9: =IF(OR(Settings!$A$21="",Settings!$F$21="Yes",OR(EOMONTH(BB$4,0)<=Settings!$B$5,BB$4>TODAY())),"",IF(EOMONTH(BA$4,0)<=Settings!$B$5,N(Settings!$C$21),N(Calc!$AG$56))) | BC9: =IF(OR(Settings!$A$21="",Settings!$F$21="Yes",OR(EOMONTH(BC$4,0)<=Settings!$B$5,BC$4>TODAY())),"",IF(EOMONTH(BB$4,0)<=Settings!$B$5,N(Settings!$C$21),N(Calc!$AG$57))) | BD9: =IF(OR(Settings!$A$21="",Settings!$F$21="Yes",OR(EOMONTH(BD$4,0)<=Settings!$B$5,BD$4>TODAY())),"",IF(EOMONTH(BC$4,0)<=Settings!$B$5,N(Settings!$C$21),N(Calc!$AG$58))) | BE9: =IF(OR(Settings!$A$21="",Settings!$F$21="Yes",OR(EOMONTH(BE$4,0)<=Settings!$B$5,BE$4>TODAY())),"",IF(EOMONTH(BD$4,0)<=Settings!$B$5,N(Settings!$C$21),N(Calc!$AG$59))) | BF9: =IF(OR(Settings!$A$21="",Settings!$F$21="Yes",OR(EOMONTH(BF$4,0)<=Settings!$B$5,BF$4>TODAY())),"",IF(EOMONTH(BE$4,0)<=Settings!$B$5,N(Settings!$C$21),N(Calc!$AG$60))) | BG9: =IF(OR(Settings!$A$21="",Settings!$F$21="Yes",OR(EOMONTH(BG$4,0)<=Settings!$B$5,BG$4>TODAY())),"",IF(EOMONTH(BF$4,0)<=Settings!$B$5,N(Settings!$C$21),N(Calc!$AG$61))) | BH9: =IF(OR(Settings!$A$21="",Settings!$F$21="Yes",OR(EOMONTH(BH$4,0)<=Settings!$B$5,BH$4>TODAY())),"",IF(EOMONTH(BG$4,0)<=Settings!$B$5,N(Settings!$C$21),N(Calc!$AG$62))) | BI9: =IF(OR(Settings!$A$21="",Settings!$F$21="Yes",OR(EOMONTH(BI$4,0)<=Settings!$B$5,BI$4>TODAY())),"",IF(EOMONTH(BH$4,0)<=Settings!$B$5,N(Settings!$C$21),N(Calc!$AG$63))) | BJ9: =IF(OR(Settings!$A$21="",Settings!$F$21="Yes",OR(EOMONTH(BJ$4,0)<=Settings!$B$5,BJ$4>TODAY())),"",IF(EOMONTH(BI$4,0)<=Settings!$B$5,N(Settings!$C$21),N(Calc!$AG$64))) | BK9: =IF(OR(Settings!$A$21="",Settings!$F$21="Yes",OR(EOMONTH(BK$4,0)<=Settings!$B$5,BK$4>TODAY())),"",IF(EOMONTH(BJ$4,0)<=Settings!$B$5,N(Settings!$C$21),N(Calc!$AG$65))) | BL9: =IF(OR(Settings!$A$21="",Settings!$F$21="Yes",OR(EOMONTH(BL$4,0)<=Settings!$B$5,BL$4>TODAY())),"",IF(EOMONTH(BK$4,0)<=Settings!$B$5,N(Settings!$C$21),N(Calc!$AG$66))) | BM9: =IF(OR(Settings!$A$21="",Settings!$F$21="Yes",OR(EOMONTH(BM$4,0)<=Settings!$B$5,BM$4>TODAY())),"",IF(EOMONTH(BL$4,0)<=Settings!$B$5,N(Settings!$C$21),N(Calc!$AG$67))) | BN9: =IF(OR(Settings!$A$21="",Settings!$F$21="Yes",OR(EOMONTH(BN$4,0)<=Settings!$B$5,BN$4>TODAY())),"",IF(EOMONTH(BM$4,0)<=Settings!$B$5,N(Settings!$C$21),N(Calc!$AG$68))) | BO9: =IF(OR(Settings!$A$21="",Settings!$F$21="Yes",OR(EOMONTH(BO$4,0)<=Settings!$B$5,BO$4>TODAY())),"",IF(EOMONTH(BN$4,0)<=Settings!$B$5,N(Settings!$C$21),N(Calc!$AG$69))) | BP9: =IF(OR(Settings!$A$21="",Settings!$F$21="Yes",OR(EOMONTH(BP$4,0)<=Settings!$B$5,BP$4>TODAY())),"",IF(EOMONTH(BO$4,0)<=Settings!$B$5,N(Settings!$C$21),N(Calc!$AG$70))) | BQ9: =IF(OR(Settings!$A$21="",Settings!$F$21="Yes",OR(EOMONTH(BQ$4,0)<=Settings!$B$5,BQ$4>TODAY())),"",IF(EOMONTH(BP$4,0)<=Settings!$B$5,N(Settings!$C$21),N(Calc!$AG$71))) | BR9: =IF(OR(Settings!$A$21="",Settings!$F$21="Yes",OR(EOMONTH(BR$4,0)<=Settings!$B$5,BR$4>TODAY())),"",IF(EOMONTH(BQ$4,0)<=Settings!$B$5,N(Settings!$C$21),N(Calc!$AG$72))) | BS9: =IF(OR(Settings!$A$21="",Settings!$F$21="Yes",OR(EOMONTH(BS$4,0)<=Settings!$B$5,BS$4>TODAY())),"",IF(EOMONTH(BR$4,0)<=Settings!$B$5,N(Settings!$C$21),N(Calc!$AG$73))) | BT9: =IF(OR(Settings!$A$21="",Settings!$F$21="Yes",OR(EOMONTH(BT$4,0)<=Settings!$B$5,BT$4>TODAY())),"",IF(EOMONTH(BS$4,0)<=Settings!$B$5,N(Settings!$C$21),N(Calc!$AG$74))) | BU9: =IF(OR(Settings!$A$21="",Settings!$F$21="Yes",OR(EOMONTH(BU$4,0)<=Settings!$B$5,BU$4>TODAY())),"",IF(EOMONTH(BT$4,0)<=Settings!$B$5,N(Settings!$C$21),N(Calc!$AG$75))) | BV9: =IF(OR(Settings!$A$21="",Settings!$F$21="Yes",OR(EOMONTH(BV$4,0)<=Settings!$B$5,BV$4>TODAY())),"",IF(EOMONTH(BU$4,0)<=Settings!$B$5,N(Settings!$C$21),N(Calc!$AG$76))) | BW9: =IF(OR(Settings!$A$21="",Settings!$F$21="Yes",OR(EOMONTH(BW$4,0)<=Settings!$B$5,BW$4>TODAY())),"",IF(EOMONTH(BV$4,0)<=Settings!$B$5,N(Settings!$C$21),N(Calc!$AG$77))) | BX9: =IF(OR(Settings!$A$21="",Settings!$F$21="Yes",OR(EOMONTH(BX$4,0)<=Settings!$B$5,BX$4>TODAY())),"",IF(EOMONTH(BW$4,0)<=Settings!$B$5,N(Settings!$C$21),N(Calc!$AG$78))) | BY9: =IF(OR(Settings!$A$21="",Settings!$F$21="Yes",OR(EOMONTH(BY$4,0)<=Settings!$B$5,BY$4>TODAY())),"",IF(EOMONTH(BX$4,0)<=Settings!$B$5,N(Settings!$C$21),N(Calc!$AG$79))) | BZ9: =IF(OR(Settings!$A$21="",Settings!$F$21="Yes",OR(EOMONTH(BZ$4,0)<=Settings!$B$5,BZ$4>TODAY())),"",IF(EOMONTH(BY$4,0)<=Settings!$B$5,N(Settings!$C$21),N(Calc!$AG$80))) | CA9: =IF(OR(Settings!$A$21="",Settings!$F$21="Yes",OR(EOMONTH(CA$4,0)<=Settings!$B$5,CA$4>TODAY())),"",IF(EOMONTH(BZ$4,0)<=Settings!$B$5,N(Settings!$C$21),N(Calc!$AG$81))) | CB9: =IF(OR(Settings!$A$21="",Settings!$F$21="Yes",OR(EOMONTH(CB$4,0)<=Settings!$B$5,CB$4>TODAY())),"",IF(EOMONTH(CA$4,0)<=Settings!$B$5,N(Settings!$C$21),N(Calc!$AG$82))) | CC9: =IF(OR(Settings!$A$21="",Settings!$F$21="Yes",OR(EOMONTH(CC$4,0)<=Settings!$B$5,CC$4>TODAY())),"",IF(EOMONTH(CB$4,0)<=Settings!$B$5,N(Settings!$C$21),N(Calc!$AG$83))) | CD9: =IF(OR(Settings!$A$21="",Settings!$F$21="Yes",OR(EOMONTH(CD$4,0)<=Settings!$B$5,CD$4>TODAY())),"",IF(EOMONTH(CC$4,0)<=Settings!$B$5,N(Settings!$C$21),N(Calc!$AG$84))) | CE9: =IF(OR(Settings!$A$21="",Settings!$F$21="Yes",OR(EOMONTH(CE$4,0)<=Settings!$B$5,CE$4>TODAY())),"",IF(EOMONTH(CD$4,0)<=Settings!$B$5,N(Settings!$C$21),N(Calc!$AG$85))) | CF9: =IF(OR(Settings!$A$21="",Settings!$F$21="Yes",OR(EOMONTH(CF$4,0)<=Settings!$B$5,CF$4>TODAY())),"",IF(EOMONTH(CE$4,0)<=Settings!$B$5,N(Settings!$C$21),N(Calc!$AG$86))) | CG9: =IF(OR(Settings!$A$21="",Settings!$F$21="Yes",OR(EOMONTH(CG$4,0)<=Settings!$B$5,CG$4>TODAY())),"",IF(EOMONTH(CF$4,0)<=Settings!$B$5,N(Settings!$C$21),N(Calc!$AG$87))) | CH9: =IF(OR(Settings!$A$21="",Settings!$F$21="Yes",OR(EOMONTH(CH$4,0)<=Settings!$B$5,CH$4>TODAY())),"",IF(EOMONTH(CG$4,0)<=Settings!$B$5,N(Settings!$C$21),N(Calc!$AG$88))) | CI9: =IF(OR(Settings!$A$21="",Settings!$F$21="Yes",OR(EOMONTH(CI$4,0)<=Settings!$B$5,CI$4>TODAY())),"",IF(EOMONTH(CH$4,0)<=Settings!$B$5,N(Settings!$C$21),N(Calc!$AG$89))) | CJ9: =IF(OR(Settings!$A$21="",Settings!$F$21="Yes",OR(EOMONTH(CJ$4,0)<=Settings!$B$5,CJ$4>TODAY())),"",IF(EOMONTH(CI$4,0)<=Settings!$B$5,N(Settings!$C$21),N(Calc!$AG$90))) | CK9: =IF(OR(Settings!$A$21="",Settings!$F$21="Yes",OR(EOMONTH(CK$4,0)<=Settings!$B$5,CK$4>TODAY())),"",IF(EOMONTH(CJ$4,0)<=Settings!$B$5,N(Settings!$C$21),N(Calc!$AG$91))) | CL9: =IF(OR(Settings!$A$21="",Settings!$F$21="Yes",OR(EOMONTH(CL$4,0)<=Settings!$B$5,CL$4>TODAY())),"",IF(EOMONTH(CK$4,0)<=Settings!$B$5,N(Settings!$C$21),N(Calc!$AG$92))) | CM9: =IF(OR(Settings!$A$21="",Settings!$F$21="Yes",OR(EOMONTH(CM$4,0)<=Settings!$B$5,CM$4>TODAY())),"",IF(EOMONTH(CL$4,0)<=Settings!$B$5,N(Settings!$C$21),N(Calc!$AG$93))) | CN9: =IF(OR(Settings!$A$21="",Settings!$F$21="Yes",OR(EOMONTH(CN$4,0)<=Settings!$B$5,CN$4>TODAY())),"",IF(EOMONTH(CM$4,0)<=Settings!$B$5,N(Settings!$C$21),N(Calc!$AG$94))) | CO9: =IF(OR(Settings!$A$21="",Settings!$F$21="Yes",OR(EOMONTH(CO$4,0)<=Settings!$B$5,CO$4>TODAY())),"",IF(EOMONTH(CN$4,0)<=Settings!$B$5,N(Settings!$C$21),N(Calc!$AG$95))) | CP9: =IF(OR(Settings!$A$21="",Settings!$F$21="Yes",OR(EOMONTH(CP$4,0)<=Settings!$B$5,CP$4>TODAY())),"",IF(EOMONTH(CO$4,0)<=Settings!$B$5,N(Settings!$C$21),N(Calc!$AG$96))) | CQ9: =IF(OR(Settings!$A$21="",Settings!$F$21="Yes",OR(EOMONTH(CQ$4,0)<=Settings!$B$5,CQ$4>TODAY())),"",IF(EOMONTH(CP$4,0)<=Settings!$B$5,N(Settings!$C$21),N(Calc!$AG$97))) | CR9: =IF(OR(Settings!$A$21="",Settings!$F$21="Yes",OR(EOMONTH(CR$4,0)<=Settings!$B$5,CR$4>TODAY())),"",IF(EOMONTH(CQ$4,0)<=Settings!$B$5,N(Settings!$C$21),N(Calc!$AG$98))) | CS9: =IF(OR(Settings!$A$21="",Settings!$F$21="Yes",OR(EOMONTH(CS$4,0)<=Settings!$B$5,CS$4>TODAY())),"",IF(EOMONTH(CR$4,0)<=Settings!$B$5,N(Settings!$C$21),N(Calc!$AG$99))) | CT9: =IF(OR(Settings!$A$21="",Settings!$F$21="Yes",OR(EOMONTH(CT$4,0)<=Settings!$B$5,CT$4>TODAY())),"",IF(EOMONTH(CS$4,0)<=Settings!$B$5,N(Settings!$C$21),N(Calc!$AG$100))) | CU9: =IF(OR(Settings!$A$21="",Settings!$F$21="Yes",OR(EOMONTH(CU$4,0)<=Settings!$B$5,CU$4>TODAY())),"",IF(EOMONTH(CT$4,0)<=Settings!$B$5,N(Settings!$C$21),N(Calc!$AG$101))) | CV9: =IF(OR(Settings!$A$21="",Settings!$F$21="Yes",OR(EOMONTH(CV$4,0)<=Settings!$B$5,CV$4>TODAY())),"",IF(EOMONTH(CU$4,0)<=Settings!$B$5,N(Settings!$C$21),N(Calc!$AG$102))) | CW9: =IF(OR(Settings!$A$21="",Settings!$F$21="Yes",OR(EOMONTH(CW$4,0)<=Settings!$B$5,CW$4>TODAY())),"",IF(EOMONTH(CV$4,0)<=Settings!$B$5,N(Settings!$C$21),N(Calc!$AG$103))) | CX9: =IF(OR(Settings!$A$21="",Settings!$F$21="Yes",OR(EOMONTH(CX$4,0)<=Settings!$B$5,CX$4>TODAY())),"",IF(EOMONTH(CW$4,0)<=Settings!$B$5,N(Settings!$C$21),N(Calc!$AG$104))) | CY9: =IF(OR(Settings!$A$21="",Settings!$F$21="Yes",OR(EOMONTH(CY$4,0)<=Settings!$B$5,CY$4>TODAY())),"",IF(EOMONTH(CX$4,0)<=Settings!$B$5,N(Settings!$C$21),N(Calc!$AG$105))) | CZ9: =IF(OR(Settings!$A$21="",Settings!$F$21="Yes",OR(EOMONTH(CZ$4,0)<=Settings!$B$5,CZ$4>TODAY())),"",IF(EOMONTH(CY$4,0)<=Settings!$B$5,N(Settings!$C$21),N(Calc!$AG$106))) | DA9: =IF(OR(Settings!$A$21="",Settings!$F$21="Yes",OR(EOMONTH(DA$4,0)<=Settings!$B$5,DA$4>TODAY())),"",IF(EOMONTH(CZ$4,0)<=Settings!$B$5,N(Settings!$C$21),N(Calc!$AG$107))) | DB9: =IF(OR(Settings!$A$21="",Settings!$F$21="Yes",OR(EOMONTH(DB$4,0)<=Settings!$B$5,DB$4>TODAY())),"",IF(EOMONTH(DA$4,0)<=Settings!$B$5,N(Settings!$C$21),N(Calc!$AG$108))) | DC9: =IF(OR(Settings!$A$21="",Settings!$F$21="Yes",OR(EOMONTH(DC$4,0)<=Settings!$B$5,DC$4>TODAY())),"",IF(EOMONTH(DB$4,0)<=Settings!$B$5,N(Settings!$C$21),N(Calc!$AG$109))) | DD9: =IF(OR(Settings!$A$21="",Settings!$F$21="Yes",OR(EOMONTH(DD$4,0)<=Settings!$B$5,DD$4>TODAY())),"",IF(EOMONTH(DC$4,0)<=Settings!$B$5,N(Settings!$C$21),N(Calc!$AG$110))) | DE9: =IF(OR(Settings!$A$21="",Settings!$F$21="Yes",OR(EOMONTH(DE$4,0)<=Settings!$B$5,DE$4>TODAY())),"",IF(EOMONTH(DD$4,0)<=Settings!$B$5,N(Settings!$C$21),N(Calc!$AG$111))) | DF9: =IF(OR(Settings!$A$21="",Settings!$F$21="Yes",OR(EOMONTH(DF$4,0)<=Settings!$B$5,DF$4>TODAY())),"",IF(EOMONTH(DE$4,0)<=Settings!$B$5,N(Settings!$C$21),N(Calc!$AG$112))) | DG9: =IF(OR(Settings!$A$21="",Settings!$F$21="Yes",OR(EOMONTH(DG$4,0)<=Settings!$B$5,DG$4>TODAY())),"",IF(EOMONTH(DF$4,0)<=Settings!$B$5,N(Settings!$C$21),N(Calc!$AG$113))) | DH9: =IF(OR(Settings!$A$21="",Settings!$F$21="Yes",OR(EOMONTH(DH$4,0)<=Settings!$B$5,DH$4>TODAY())),"",IF(EOMONTH(DG$4,0)<=Settings!$B$5,N(Settings!$C$21),N(Calc!$AG$114))) | DI9: =IF(OR(Settings!$A$21="",Settings!$F$21="Yes",OR(EOMONTH(DI$4,0)<=Settings!$B$5,DI$4>TODAY())),"",IF(EOMONTH(DH$4,0)<=Settings!$B$5,N(Settings!$C$21),N(Calc!$AG$115))) | DJ9: =IF(OR(Settings!$A$21="",Settings!$F$21="Yes",OR(EOMONTH(DJ$4,0)<=Settings!$B$5,DJ$4>TODAY())),"",IF(EOMONTH(DI$4,0)<=Settings!$B$5,N(Settings!$C$21),N(Calc!$AG$116))) | DK9: =IF(OR(Settings!$A$21="",Settings!$F$21="Yes",OR(EOMONTH(DK$4,0)<=Settings!$B$5,DK$4>TODAY())),"",IF(EOMONTH(DJ$4,0)<=Settings!$B$5,N(Settings!$C$21),N(Calc!$AG$117))) | DL9: =IF(OR(Settings!$A$21="",Settings!$F$21="Yes",OR(EOMONTH(DL$4,0)<=Settings!$B$5,DL$4>TODAY())),"",IF(EOMONTH(DK$4,0)<=Settings!$B$5,N(Settings!$C$21),N(Calc!$AG$118))) | DM9: =IF(OR(Settings!$A$21="",Settings!$F$21="Yes",OR(EOMONTH(DM$4,0)<=Settings!$B$5,DM$4>TODAY())),"",IF(EOMONTH(DL$4,0)<=Settings!$B$5,N(Settings!$C$21),N(Calc!$AG$119))) | DN9: =IF(OR(Settings!$A$21="",Settings!$F$21="Yes",OR(EOMONTH(DN$4,0)<=Settings!$B$5,DN$4>TODAY())),"",IF(EOMONTH(DM$4,0)<=Settings!$B$5,N(Settings!$C$21),N(Calc!$AG$120))) | DO9: =IF(OR(Settings!$A$21="",Settings!$F$21="Yes",OR(EOMONTH(DO$4,0)<=Settings!$B$5,DO$4>TODAY())),"",IF(EOMONTH(DN$4,0)<=Settings!$B$5,N(Settings!$C$21),N(Calc!$AG$121))) | DP9: =IF(OR(Settings!$A$21="",Settings!$F$21="Yes",OR(EOMONTH(DP$4,0)<=Settings!$B$5,DP$4>TODAY())),"",IF(EOMONTH(DO$4,0)<=Settings!$B$5,N(Settings!$C$21),N(Calc!$AG$122))) | DQ9: =IF(OR(Settings!$A$21="",Settings!$F$21="Yes",OR(EOMONTH(DQ$4,0)<=Settings!$B$5,DQ$4>TODAY())),"",IF(EOMONTH(DP$4,0)<=Settings!$B$5,N(Settings!$C$21),N(Calc!$AG$123))) | DR9: =IF(OR(Settings!$A$21="",Settings!$F$21="Yes",OR(EOMONTH(DR$4,0)<=Settings!$B$5,DR$4>TODAY())),"",IF(EOMONTH(DQ$4,0)<=Settings!$B$5,N(Settings!$C$21),N(Calc!$AG$124))) | DS9: =IF(OR(Settings!$A$21="",Settings!$F$21="Yes",OR(EOMONTH(DS$4,0)<=Settings!$B$5,DS$4>TODAY())),"",IF(EOMONTH(DR$4,0)<=Settings!$B$5,N(Settings!$C$21),N(Calc!$AG$125))) | DT9: =IF(OR(Settings!$A$21="",Settings!$F$21="Yes",OR(EOMONTH(DT$4,0)<=Settings!$B$5,DT$4>TODAY())),"",IF(EOMONTH(DS$4,0)<=Settings!$B$5,N(Settings!$C$21),N(Calc!$AG$126))) | DU9: =IF(OR(Settings!$A$21="",Settings!$F$21="Yes",OR(EOMONTH(DU$4,0)<=Settings!$B$5,DU$4>TODAY())),"",IF(EOMONTH(DT$4,0)<=Settings!$B$5,N(Settings!$C$21),N(Calc!$AG$127))) | DV9: =IF(OR(Settings!$A$21="",Settings!$F$21="Yes",OR(EOMONTH(DV$4,0)<=Settings!$B$5,DV$4>TODAY())),"",IF(EOMONTH(DU$4,0)<=Settings!$B$5,N(Settings!$C$21),N(Calc!$AG$128))) | DW9: =IF(OR(Settings!$A$21="",Settings!$F$21="Yes",OR(EOMONTH(DW$4,0)<=Settings!$B$5,DW$4>TODAY())),"",IF(EOMONTH(DV$4,0)<=Settings!$B$5,N(Settings!$C$21),N(Calc!$AG$129))) | DX9: =IF(OR(Settings!$A$21="",Settings!$F$21="Yes",OR(EOMONTH(DX$4,0)<=Settings!$B$5,DX$4>TODAY())),"",IF(EOMONTH(DW$4,0)<=Settings!$B$5,N(Settings!$C$21),N(Calc!$AG$130))) | DY9: =IF(OR(Settings!$A$21="",Settings!$F$21="Yes",OR(EOMONTH(DY$4,0)<=Settings!$B$5,DY$4>TODAY())),"",IF(EOMONTH(DX$4,0)<=Settings!$B$5,N(Settings!$C$21),N(Calc!$AG$131))) | DZ9: =IF(OR(Settings!$A$21="",Settings!$F$21="Yes",OR(EOMONTH(DZ$4,0)<=Settings!$B$5,DZ$4>TODAY())),"",IF(EOMONTH(DY$4,0)<=Settings!$B$5,N(Settings!$C$21),N(Calc!$AG$132))) | EA9: =IF(OR(Settings!$A$21="",Settings!$F$21="Yes",OR(EOMONTH(EA$4,0)<=Settings!$B$5,EA$4>TODAY())),"",IF(EOMONTH(DZ$4,0)<=Settings!$B$5,N(Settings!$C$21),N(Calc!$AG$133))) | EB9: =IF(OR(Settings!$A$21="",Settings!$F$21="Yes",OR(EOMONTH(EB$4,0)<=Settings!$B$5,EB$4>TODAY())),"",IF(EOMONTH(EA$4,0)<=Settings!$B$5,N(Settings!$C$21),N(Calc!$AG$134))) | EC9: =IF(OR(Settings!$A$21="",Settings!$F$21="Yes",OR(EOMONTH(EC$4,0)<=Settings!$B$5,EC$4>TODAY())),"",IF(EOMONTH(EB$4,0)<=Settings!$B$5,N(Settings!$C$21),N(Calc!$AG$135))) | ED9: =IF(OR(Settings!$A$21="",Settings!$F$21="Yes",OR(EOMONTH(ED$4,0)<=Settings!$B$5,ED$4>TODAY())),"",IF(EOMONTH(EC$4,0)<=Settings!$B$5,N(Settings!$C$21),N(Calc!$AG$136))) | EE9: =IF(OR(Settings!$A$21="",Settings!$F$21="Yes",OR(EOMONTH(EE$4,0)<=Settings!$B$5,EE$4>TODAY())),"",IF(EOMONTH(ED$4,0)<=Settings!$B$5,N(Settings!$C$21),N(Calc!$AG$137))) | EF9: =IF(OR(Settings!$A$21="",Settings!$F$21="Yes",OR(EOMONTH(EF$4,0)<=Settings!$B$5,EF$4>TODAY())),"",IF(EOMONTH(EE$4,0)<=Settings!$B$5,N(Settings!$C$21),N(Calc!$AG$138))) | EG9: =IF(OR(Settings!$A$21="",Settings!$F$21="Yes",OR(EOMONTH(EG$4,0)<=Settings!$B$5,EG$4>TODAY())),"",IF(EOMONTH(EF$4,0)<=Settings!$B$5,N(Settings!$C$21),N(Calc!$AG$139))) | EH9: =IF(OR(Settings!$A$21="",Settings!$F$21="Yes",OR(EOMONTH(EH$4,0)<=Settings!$B$5,EH$4>TODAY())),"",IF(EOMONTH(EG$4,0)<=Settings!$B$5,N(Settings!$C$21),N(Calc!$AG$140))) | EI9: =IF(OR(Settings!$A$21="",Settings!$F$21="Yes",OR(EOMONTH(EI$4,0)<=Settings!$B$5,EI$4>TODAY())),"",IF(EOMONTH(EH$4,0)<=Settings!$B$5,N(Settings!$C$21),N(Calc!$AG$141))) | EJ9: =IF(OR(Settings!$A$21="",Settings!$F$21="Yes",OR(EOMONTH(EJ$4,0)<=Settings!$B$5,EJ$4>TODAY())),"",IF(EOMONTH(EI$4,0)<=Settings!$B$5,N(Settings!$C$21),N(Calc!$AG$142))) | EK9: =IF(OR(Settings!$A$21="",Settings!$F$21="Yes",OR(EOMONTH(EK$4,0)<=Settings!$B$5,EK$4>TODAY())),"",IF(EOMONTH(EJ$4,0)<=Settings!$B$5,N(Settings!$C$21),N(Calc!$AG$143))) | EL9: =IF(OR(Settings!$A$21="",Settings!$F$21="Yes",OR(EOMONTH(EL$4,0)<=Settings!$B$5,EL$4>TODAY())),"",IF(EOMONTH(EK$4,0)<=Settings!$B$5,N(Settings!$C$21),N(Calc!$AG$144))) | EM9: =IF(OR(Settings!$A$21="",Settings!$F$21="Yes",OR(EOMONTH(EM$4,0)<=Settings!$B$5,EM$4>TODAY())),"",IF(EOMONTH(EL$4,0)<=Settings!$B$5,N(Settings!$C$21),N(Calc!$AG$145))) | EN9: =IF(OR(Settings!$A$21="",Settings!$F$21="Yes",OR(EOMONTH(EN$4,0)<=Settings!$B$5,EN$4>TODAY())),"",IF(EOMONTH(EM$4,0)<=Settings!$B$5,N(Settings!$C$21),N(Calc!$AG$146))) | EO9: =IF(OR(Settings!$A$21="",Settings!$F$21="Yes",OR(EOMONTH(EO$4,0)<=Settings!$B$5,EO$4>TODAY())),"",IF(EOMONTH(EN$4,0)<=Settings!$B$5,N(Settings!$C$21),N(Calc!$AG$147))) | EP9: =IF(OR(Settings!$A$21="",Settings!$F$21="Yes",OR(EOMONTH(EP$4,0)<=Settings!$B$5,EP$4>TODAY())),"",IF(EOMONTH(EO$4,0)<=Settings!$B$5,N(Settings!$C$21),N(Calc!$AG$148))) | EQ9: =IF(OR(Settings!$A$21="",Settings!$F$21="Yes",OR(EOMONTH(EQ$4,0)<=Settings!$B$5,EQ$4>TODAY())),"",IF(EOMONTH(EP$4,0)<=Settings!$B$5,N(Settings!$C$21),N(Calc!$AG$149))) | ER9: =IF(OR(Settings!$A$21="",Settings!$F$21="Yes",OR(EOMONTH(ER$4,0)<=Settings!$B$5,ER$4>TODAY())),"",IF(EOMONTH(EQ$4,0)<=Settings!$B$5,N(Settings!$C$21),N(Calc!$AG$150))) | ES9: =IF(OR(Settings!$A$21="",Settings!$F$21="Yes",OR(EOMONTH(ES$4,0)<=Settings!$B$5,ES$4>TODAY())),"",IF(EOMONTH(ER$4,0)<=Settings!$B$5,N(Settings!$C$21),N(Calc!$AG$151))) | ET9: =IF(OR(Settings!$A$21="",Settings!$F$21="Yes",OR(EOMONTH(ET$4,0)<=Settings!$B$5,ET$4>TODAY())),"",IF(EOMONTH(ES$4,0)<=Settings!$B$5,N(Settings!$C$21),N(Calc!$AG$152))) | EU9: =IF(OR(Settings!$A$21="",Settings!$F$21="Yes",OR(EOMONTH(EU$4,0)<=Settings!$B$5,EU$4>TODAY())),"",IF(EOMONTH(ET$4,0)<=Settings!$B$5,N(Settings!$C$21),N(Calc!$AG$153))) | EV9: =IF(OR(Settings!$A$21="",Settings!$F$21="Yes",OR(EOMONTH(EV$4,0)<=Settings!$B$5,EV$4>TODAY())),"",IF(EOMONTH(EU$4,0)<=Settings!$B$5,N(Settings!$C$21),N(Calc!$AG$154))) | EW9: =IF(OR(Settings!$A$21="",Settings!$F$21="Yes",OR(EOMONTH(EW$4,0)<=Settings!$B$5,EW$4>TODAY())),"",IF(EOMONTH(EV$4,0)<=Settings!$B$5,N(Settings!$C$21),N(Calc!$AG$155))) | EX9: =IF(OR(Settings!$A$21="",Settings!$F$21="Yes",OR(EOMONTH(EX$4,0)<=Settings!$B$5,EX$4>TODAY())),"",IF(EOMONTH(EW$4,0)<=Settings!$B$5,N(Settings!$C$21),N(Calc!$AG$156))) | EY9: =IF(OR(Settings!$A$21="",Settings!$F$21="Yes",OR(EOMONTH(EY$4,0)<=Settings!$B$5,EY$4>TODAY())),"",IF(EOMONTH(EX$4,0)<=Settings!$B$5,N(Settings!$C$21),N(Calc!$AG$157))) | EZ9: =IF(OR(Settings!$A$21="",Settings!$F$21="Yes",OR(EOMONTH(EZ$4,0)<=Settings!$B$5,EZ$4>TODAY())),"",IF(EOMONTH(EY$4,0)<=Settings!$B$5,N(Settings!$C$21),N(Calc!$AG$158))) | FA9: =IF(OR(Settings!$A$21="",Settings!$F$21="Yes",OR(EOMONTH(FA$4,0)<=Settings!$B$5,FA$4>TODAY())),"",IF(EOMONTH(EZ$4,0)<=Settings!$B$5,N(Settings!$C$21),N(Calc!$AG$159))) | FB9: =IF(OR(Settings!$A$21="",Settings!$F$21="Yes",OR(EOMONTH(FB$4,0)<=Settings!$B$5,FB$4>TODAY())),"",IF(EOMONTH(FA$4,0)<=Settings!$B$5,N(Settings!$C$21),N(Calc!$AG$160))) | FC9: =IF(OR(Settings!$A$21="",Settings!$F$21="Yes",OR(EOMONTH(FC$4,0)<=Settings!$B$5,FC$4>TODAY())),"",IF(EOMONTH(FB$4,0)<=Settings!$B$5,N(Settings!$C$21),N(Calc!$AG$161))) | FD9: =IF(OR(Settings!$A$21="",Settings!$F$21="Yes",OR(EOMONTH(FD$4,0)<=Settings!$B$5,FD$4>TODAY())),"",IF(EOMONTH(FC$4,0)<=Settings!$B$5,N(Settings!$C$21),N(Calc!$AG$162))) | FE9: =IF(OR(Settings!$A$21="",Settings!$F$21="Yes",OR(EOMONTH(FE$4,0)<=Settings!$B$5,FE$4>TODAY())),"",IF(EOMONTH(FD$4,0)<=Settings!$B$5,N(Settings!$C$21),N(Calc!$AG$163))) | FF9: =IF(OR(Settings!$A$21="",Settings!$F$21="Yes",OR(EOMONTH(FF$4,0)<=Settings!$B$5,FF$4>TODAY())),"",IF(EOMONTH(FE$4,0)<=Settings!$B$5,N(Settings!$C$21),N(Calc!$AG$164))) | FG9: =IF(OR(Settings!$A$21="",Settings!$F$21="Yes",OR(EOMONTH(FG$4,0)<=Settings!$B$5,FG$4>TODAY())),"",IF(EOMONTH(FF$4,0)<=Settings!$B$5,N(Settings!$C$21),N(Calc!$AG$165))) | FH9: =IF(OR(Settings!$A$21="",Settings!$F$21="Yes",OR(EOMONTH(FH$4,0)<=Settings!$B$5,FH$4>TODAY())),"",IF(EOMONTH(FG$4,0)<=Settings!$B$5,N(Settings!$C$21),N(Calc!$AG$166))) | FI9: =IF(OR(Settings!$A$21="",Settings!$F$21="Yes",OR(EOMONTH(FI$4,0)<=Settings!$B$5,FI$4>TODAY())),"",IF(EOMONTH(FH$4,0)<=Settings!$B$5,N(Settings!$C$21),N(Calc!$AG$167))) | FJ9: =IF(OR(Settings!$A$21="",Settings!$F$21="Yes",OR(EOMONTH(FJ$4,0)<=Settings!$B$5,FJ$4>TODAY())),"",IF(EOMONTH(FI$4,0)<=Settings!$B$5,N(Settings!$C$21),N(Calc!$AG$168))) | FK9: =IF(OR(Settings!$A$21="",Settings!$F$21="Yes",OR(EOMONTH(FK$4,0)<=Settings!$B$5,FK$4>TODAY())),"",IF(EOMONTH(FJ$4,0)<=Settings!$B$5,N(Settings!$C$21),N(Calc!$AG$169))) | FL9: =IF(OR(Settings!$A$21="",Settings!$F$21="Yes",OR(EOMONTH(FL$4,0)<=Settings!$B$5,FL$4>TODAY())),"",IF(EOMONTH(FK$4,0)<=Settings!$B$5,N(Settings!$C$21),N(Calc!$AG$170))) | FM9: =IF(OR(Settings!$A$21="",Settings!$F$21="Yes",OR(EOMONTH(FM$4,0)<=Settings!$B$5,FM$4>TODAY())),"",IF(EOMONTH(FL$4,0)<=Settings!$B$5,N(Settings!$C$21),N(Calc!$AG$171))) | FN9: =IF(OR(Settings!$A$21="",Settings!$F$21="Yes",OR(EOMONTH(FN$4,0)<=Settings!$B$5,FN$4>TODAY())),"",IF(EOMONTH(FM$4,0)<=Settings!$B$5,N(Settings!$C$21),N(Calc!$AG$172))) | FO9: =IF(OR(Settings!$A$21="",Settings!$F$21="Yes",OR(EOMONTH(FO$4,0)<=Settings!$B$5,FO$4>TODAY())),"",IF(EOMONTH(FN$4,0)<=Settings!$B$5,N(Settings!$C$21),N(Calc!$AG$173))) | FP9: =IF(OR(Settings!$A$21="",Settings!$F$21="Yes",OR(EOMONTH(FP$4,0)<=Settings!$B$5,FP$4>TODAY())),"",IF(EOMONTH(FO$4,0)<=Settings!$B$5,N(Settings!$C$21),N(Calc!$AG$174))) | FQ9: =IF(OR(Settings!$A$21="",Settings!$F$21="Yes",OR(EOMONTH(FQ$4,0)<=Settings!$B$5,FQ$4>TODAY())),"",IF(EOMONTH(FP$4,0)<=Settings!$B$5,N(Settings!$C$21),N(Calc!$AG$175))) | FR9: =IF(OR(Settings!$A$21="",Settings!$F$21="Yes",OR(EOMONTH(FR$4,0)<=Settings!$B$5,FR$4>TODAY())),"",IF(EOMONTH(FQ$4,0)<=Settings!$B$5,N(Settings!$C$21),N(Calc!$AG$176))) | FS9: =IF(OR(Settings!$A$21="",Settings!$F$21="Yes",OR(EOMONTH(FS$4,0)<=Settings!$B$5,FS$4>TODAY())),"",IF(EOMONTH(FR$4,0)<=Settings!$B$5,N(Settings!$C$21),N(Calc!$AG$177))) | FT9: =IF(OR(Settings!$A$21="",Settings!$F$21="Yes",OR(EOMONTH(FT$4,0)<=Settings!$B$5,FT$4>TODAY())),"",IF(EOMONTH(FS$4,0)<=Settings!$B$5,N(Settings!$C$21),N(Calc!$AG$178))) | FU9: =IF(OR(Settings!$A$21="",Settings!$F$21="Yes",OR(EOMONTH(FU$4,0)<=Settings!$B$5,FU$4>TODAY())),"",IF(EOMONTH(FT$4,0)<=Settings!$B$5,N(Settings!$C$21),N(Calc!$AG$179))) | FV9: =IF(OR(Settings!$A$21="",Settings!$F$21="Yes",OR(EOMONTH(FV$4,0)<=Settings!$B$5,FV$4>TODAY())),"",IF(EOMONTH(FU$4,0)<=Settings!$B$5,N(Settings!$C$21),N(Calc!$AG$180))) | FW9: =IF(OR(Settings!$A$21="",Settings!$F$21="Yes",OR(EOMONTH(FW$4,0)<=Settings!$B$5,FW$4>TODAY())),"",IF(EOMONTH(FV$4,0)<=Settings!$B$5,N(Settings!$C$21),N(Calc!$AG$181))) | FX9: =IF(OR(Settings!$A$21="",Settings!$F$21="Yes",OR(EOMONTH(FX$4,0)<=Settings!$B$5,FX$4>TODAY())),"",IF(EOMONTH(FW$4,0)<=Settings!$B$5,N(Settings!$C$21),N(Calc!$AG$182)))
A10: =IF(Settings!$A$22="","(unused)",Settings!$A$22&IF(Settings!$E$22="No"," (retired)","")) | B10: =IF(Settings!$A$22="","",IF(Settings!$F$22="Yes","REQUIRED","optional · grey = unchanged")&IF(OR(Settings!$B$22="Card",Settings!$B$22="Loan")," · amount owed","")) | C10: =IF(OR(Settings!$A$22="",Settings!$F$22="Yes",OR(EOMONTH(C$4,0)<=Settings!$B$5,C$4>TODAY())),"",N(Settings!$C$22)) | D10: =IF(OR(Settings!$A$22="",Settings!$F$22="Yes",OR(EOMONTH(D$4,0)<=Settings!$B$5,D$4>TODAY())),"",IF(EOMONTH(C$4,0)<=Settings!$B$5,N(Settings!$C$22),N(Calc!$AH$6))) | E10: =IF(OR(Settings!$A$22="",Settings!$F$22="Yes",OR(EOMONTH(E$4,0)<=Settings!$B$5,E$4>TODAY())),"",IF(EOMONTH(D$4,0)<=Settings!$B$5,N(Settings!$C$22),N(Calc!$AH$7))) | F10: =IF(OR(Settings!$A$22="",Settings!$F$22="Yes",OR(EOMONTH(F$4,0)<=Settings!$B$5,F$4>TODAY())),"",IF(EOMONTH(E$4,0)<=Settings!$B$5,N(Settings!$C$22),N(Calc!$AH$8))) | G10: =IF(OR(Settings!$A$22="",Settings!$F$22="Yes",OR(EOMONTH(G$4,0)<=Settings!$B$5,G$4>TODAY())),"",IF(EOMONTH(F$4,0)<=Settings!$B$5,N(Settings!$C$22),N(Calc!$AH$9))) | H10: =IF(OR(Settings!$A$22="",Settings!$F$22="Yes",OR(EOMONTH(H$4,0)<=Settings!$B$5,H$4>TODAY())),"",IF(EOMONTH(G$4,0)<=Settings!$B$5,N(Settings!$C$22),N(Calc!$AH$10))) | I10: =IF(OR(Settings!$A$22="",Settings!$F$22="Yes",OR(EOMONTH(I$4,0)<=Settings!$B$5,I$4>TODAY())),"",IF(EOMONTH(H$4,0)<=Settings!$B$5,N(Settings!$C$22),N(Calc!$AH$11))) | J10: =IF(OR(Settings!$A$22="",Settings!$F$22="Yes",OR(EOMONTH(J$4,0)<=Settings!$B$5,J$4>TODAY())),"",IF(EOMONTH(I$4,0)<=Settings!$B$5,N(Settings!$C$22),N(Calc!$AH$12))) | K10: =IF(OR(Settings!$A$22="",Settings!$F$22="Yes",OR(EOMONTH(K$4,0)<=Settings!$B$5,K$4>TODAY())),"",IF(EOMONTH(J$4,0)<=Settings!$B$5,N(Settings!$C$22),N(Calc!$AH$13))) | L10: =IF(OR(Settings!$A$22="",Settings!$F$22="Yes",OR(EOMONTH(L$4,0)<=Settings!$B$5,L$4>TODAY())),"",IF(EOMONTH(K$4,0)<=Settings!$B$5,N(Settings!$C$22),N(Calc!$AH$14))) | M10: =IF(OR(Settings!$A$22="",Settings!$F$22="Yes",OR(EOMONTH(M$4,0)<=Settings!$B$5,M$4>TODAY())),"",IF(EOMONTH(L$4,0)<=Settings!$B$5,N(Settings!$C$22),N(Calc!$AH$15))) | N10: =IF(OR(Settings!$A$22="",Settings!$F$22="Yes",OR(EOMONTH(N$4,0)<=Settings!$B$5,N$4>TODAY())),"",IF(EOMONTH(M$4,0)<=Settings!$B$5,N(Settings!$C$22),N(Calc!$AH$16))) | O10: =IF(OR(Settings!$A$22="",Settings!$F$22="Yes",OR(EOMONTH(O$4,0)<=Settings!$B$5,O$4>TODAY())),"",IF(EOMONTH(N$4,0)<=Settings!$B$5,N(Settings!$C$22),N(Calc!$AH$17))) | P10: =IF(OR(Settings!$A$22="",Settings!$F$22="Yes",OR(EOMONTH(P$4,0)<=Settings!$B$5,P$4>TODAY())),"",IF(EOMONTH(O$4,0)<=Settings!$B$5,N(Settings!$C$22),N(Calc!$AH$18))) | Q10: =IF(OR(Settings!$A$22="",Settings!$F$22="Yes",OR(EOMONTH(Q$4,0)<=Settings!$B$5,Q$4>TODAY())),"",IF(EOMONTH(P$4,0)<=Settings!$B$5,N(Settings!$C$22),N(Calc!$AH$19))) | R10: =IF(OR(Settings!$A$22="",Settings!$F$22="Yes",OR(EOMONTH(R$4,0)<=Settings!$B$5,R$4>TODAY())),"",IF(EOMONTH(Q$4,0)<=Settings!$B$5,N(Settings!$C$22),N(Calc!$AH$20))) | S10: =IF(OR(Settings!$A$22="",Settings!$F$22="Yes",OR(EOMONTH(S$4,0)<=Settings!$B$5,S$4>TODAY())),"",IF(EOMONTH(R$4,0)<=Settings!$B$5,N(Settings!$C$22),N(Calc!$AH$21))) | T10: =IF(OR(Settings!$A$22="",Settings!$F$22="Yes",OR(EOMONTH(T$4,0)<=Settings!$B$5,T$4>TODAY())),"",IF(EOMONTH(S$4,0)<=Settings!$B$5,N(Settings!$C$22),N(Calc!$AH$22))) | U10: =IF(OR(Settings!$A$22="",Settings!$F$22="Yes",OR(EOMONTH(U$4,0)<=Settings!$B$5,U$4>TODAY())),"",IF(EOMONTH(T$4,0)<=Settings!$B$5,N(Settings!$C$22),N(Calc!$AH$23))) | V10: =IF(OR(Settings!$A$22="",Settings!$F$22="Yes",OR(EOMONTH(V$4,0)<=Settings!$B$5,V$4>TODAY())),"",IF(EOMONTH(U$4,0)<=Settings!$B$5,N(Settings!$C$22),N(Calc!$AH$24))) | W10: =IF(OR(Settings!$A$22="",Settings!$F$22="Yes",OR(EOMONTH(W$4,0)<=Settings!$B$5,W$4>TODAY())),"",IF(EOMONTH(V$4,0)<=Settings!$B$5,N(Settings!$C$22),N(Calc!$AH$25))) | X10: =IF(OR(Settings!$A$22="",Settings!$F$22="Yes",OR(EOMONTH(X$4,0)<=Settings!$B$5,X$4>TODAY())),"",IF(EOMONTH(W$4,0)<=Settings!$B$5,N(Settings!$C$22),N(Calc!$AH$26))) | Y10: =IF(OR(Settings!$A$22="",Settings!$F$22="Yes",OR(EOMONTH(Y$4,0)<=Settings!$B$5,Y$4>TODAY())),"",IF(EOMONTH(X$4,0)<=Settings!$B$5,N(Settings!$C$22),N(Calc!$AH$27))) | Z10: =IF(OR(Settings!$A$22="",Settings!$F$22="Yes",OR(EOMONTH(Z$4,0)<=Settings!$B$5,Z$4>TODAY())),"",IF(EOMONTH(Y$4,0)<=Settings!$B$5,N(Settings!$C$22),N(Calc!$AH$28))) | AA10: =IF(OR(Settings!$A$22="",Settings!$F$22="Yes",OR(EOMONTH(AA$4,0)<=Settings!$B$5,AA$4>TODAY())),"",IF(EOMONTH(Z$4,0)<=Settings!$B$5,N(Settings!$C$22),N(Calc!$AH$29))) | AB10: =IF(OR(Settings!$A$22="",Settings!$F$22="Yes",OR(EOMONTH(AB$4,0)<=Settings!$B$5,AB$4>TODAY())),"",IF(EOMONTH(AA$4,0)<=Settings!$B$5,N(Settings!$C$22),N(Calc!$AH$30))) | AC10: =IF(OR(Settings!$A$22="",Settings!$F$22="Yes",OR(EOMONTH(AC$4,0)<=Settings!$B$5,AC$4>TODAY())),"",IF(EOMONTH(AB$4,0)<=Settings!$B$5,N(Settings!$C$22),N(Calc!$AH$31))) | AD10: =IF(OR(Settings!$A$22="",Settings!$F$22="Yes",OR(EOMONTH(AD$4,0)<=Settings!$B$5,AD$4>TODAY())),"",IF(EOMONTH(AC$4,0)<=Settings!$B$5,N(Settings!$C$22),N(Calc!$AH$32))) | AE10: =IF(OR(Settings!$A$22="",Settings!$F$22="Yes",OR(EOMONTH(AE$4,0)<=Settings!$B$5,AE$4>TODAY())),"",IF(EOMONTH(AD$4,0)<=Settings!$B$5,N(Settings!$C$22),N(Calc!$AH$33))) | AF10: =IF(OR(Settings!$A$22="",Settings!$F$22="Yes",OR(EOMONTH(AF$4,0)<=Settings!$B$5,AF$4>TODAY())),"",IF(EOMONTH(AE$4,0)<=Settings!$B$5,N(Settings!$C$22),N(Calc!$AH$34))) | AG10: =IF(OR(Settings!$A$22="",Settings!$F$22="Yes",OR(EOMONTH(AG$4,0)<=Settings!$B$5,AG$4>TODAY())),"",IF(EOMONTH(AF$4,0)<=Settings!$B$5,N(Settings!$C$22),N(Calc!$AH$35))) | AH10: =IF(OR(Settings!$A$22="",Settings!$F$22="Yes",OR(EOMONTH(AH$4,0)<=Settings!$B$5,AH$4>TODAY())),"",IF(EOMONTH(AG$4,0)<=Settings!$B$5,N(Settings!$C$22),N(Calc!$AH$36))) | AI10: =IF(OR(Settings!$A$22="",Settings!$F$22="Yes",OR(EOMONTH(AI$4,0)<=Settings!$B$5,AI$4>TODAY())),"",IF(EOMONTH(AH$4,0)<=Settings!$B$5,N(Settings!$C$22),N(Calc!$AH$37))) | AJ10: =IF(OR(Settings!$A$22="",Settings!$F$22="Yes",OR(EOMONTH(AJ$4,0)<=Settings!$B$5,AJ$4>TODAY())),"",IF(EOMONTH(AI$4,0)<=Settings!$B$5,N(Settings!$C$22),N(Calc!$AH$38))) | AK10: =IF(OR(Settings!$A$22="",Settings!$F$22="Yes",OR(EOMONTH(AK$4,0)<=Settings!$B$5,AK$4>TODAY())),"",IF(EOMONTH(AJ$4,0)<=Settings!$B$5,N(Settings!$C$22),N(Calc!$AH$39))) | AL10: =IF(OR(Settings!$A$22="",Settings!$F$22="Yes",OR(EOMONTH(AL$4,0)<=Settings!$B$5,AL$4>TODAY())),"",IF(EOMONTH(AK$4,0)<=Settings!$B$5,N(Settings!$C$22),N(Calc!$AH$40))) | AM10: =IF(OR(Settings!$A$22="",Settings!$F$22="Yes",OR(EOMONTH(AM$4,0)<=Settings!$B$5,AM$4>TODAY())),"",IF(EOMONTH(AL$4,0)<=Settings!$B$5,N(Settings!$C$22),N(Calc!$AH$41))) | AN10: =IF(OR(Settings!$A$22="",Settings!$F$22="Yes",OR(EOMONTH(AN$4,0)<=Settings!$B$5,AN$4>TODAY())),"",IF(EOMONTH(AM$4,0)<=Settings!$B$5,N(Settings!$C$22),N(Calc!$AH$42))) | AO10: =IF(OR(Settings!$A$22="",Settings!$F$22="Yes",OR(EOMONTH(AO$4,0)<=Settings!$B$5,AO$4>TODAY())),"",IF(EOMONTH(AN$4,0)<=Settings!$B$5,N(Settings!$C$22),N(Calc!$AH$43))) | AP10: =IF(OR(Settings!$A$22="",Settings!$F$22="Yes",OR(EOMONTH(AP$4,0)<=Settings!$B$5,AP$4>TODAY())),"",IF(EOMONTH(AO$4,0)<=Settings!$B$5,N(Settings!$C$22),N(Calc!$AH$44))) | AQ10: =IF(OR(Settings!$A$22="",Settings!$F$22="Yes",OR(EOMONTH(AQ$4,0)<=Settings!$B$5,AQ$4>TODAY())),"",IF(EOMONTH(AP$4,0)<=Settings!$B$5,N(Settings!$C$22),N(Calc!$AH$45))) | AR10: =IF(OR(Settings!$A$22="",Settings!$F$22="Yes",OR(EOMONTH(AR$4,0)<=Settings!$B$5,AR$4>TODAY())),"",IF(EOMONTH(AQ$4,0)<=Settings!$B$5,N(Settings!$C$22),N(Calc!$AH$46))) | AS10: =IF(OR(Settings!$A$22="",Settings!$F$22="Yes",OR(EOMONTH(AS$4,0)<=Settings!$B$5,AS$4>TODAY())),"",IF(EOMONTH(AR$4,0)<=Settings!$B$5,N(Settings!$C$22),N(Calc!$AH$47))) | AT10: =IF(OR(Settings!$A$22="",Settings!$F$22="Yes",OR(EOMONTH(AT$4,0)<=Settings!$B$5,AT$4>TODAY())),"",IF(EOMONTH(AS$4,0)<=Settings!$B$5,N(Settings!$C$22),N(Calc!$AH$48))) | AU10: =IF(OR(Settings!$A$22="",Settings!$F$22="Yes",OR(EOMONTH(AU$4,0)<=Settings!$B$5,AU$4>TODAY())),"",IF(EOMONTH(AT$4,0)<=Settings!$B$5,N(Settings!$C$22),N(Calc!$AH$49))) | AV10: =IF(OR(Settings!$A$22="",Settings!$F$22="Yes",OR(EOMONTH(AV$4,0)<=Settings!$B$5,AV$4>TODAY())),"",IF(EOMONTH(AU$4,0)<=Settings!$B$5,N(Settings!$C$22),N(Calc!$AH$50))) | AW10: =IF(OR(Settings!$A$22="",Settings!$F$22="Yes",OR(EOMONTH(AW$4,0)<=Settings!$B$5,AW$4>TODAY())),"",IF(EOMONTH(AV$4,0)<=Settings!$B$5,N(Settings!$C$22),N(Calc!$AH$51))) | AX10: =IF(OR(Settings!$A$22="",Settings!$F$22="Yes",OR(EOMONTH(AX$4,0)<=Settings!$B$5,AX$4>TODAY())),"",IF(EOMONTH(AW$4,0)<=Settings!$B$5,N(Settings!$C$22),N(Calc!$AH$52))) | AY10: =IF(OR(Settings!$A$22="",Settings!$F$22="Yes",OR(EOMONTH(AY$4,0)<=Settings!$B$5,AY$4>TODAY())),"",IF(EOMONTH(AX$4,0)<=Settings!$B$5,N(Settings!$C$22),N(Calc!$AH$53))) | AZ10: =IF(OR(Settings!$A$22="",Settings!$F$22="Yes",OR(EOMONTH(AZ$4,0)<=Settings!$B$5,AZ$4>TODAY())),"",IF(EOMONTH(AY$4,0)<=Settings!$B$5,N(Settings!$C$22),N(Calc!$AH$54))) | BA10: =IF(OR(Settings!$A$22="",Settings!$F$22="Yes",OR(EOMONTH(BA$4,0)<=Settings!$B$5,BA$4>TODAY())),"",IF(EOMONTH(AZ$4,0)<=Settings!$B$5,N(Settings!$C$22),N(Calc!$AH$55))) | BB10: =IF(OR(Settings!$A$22="",Settings!$F$22="Yes",OR(EOMONTH(BB$4,0)<=Settings!$B$5,BB$4>TODAY())),"",IF(EOMONTH(BA$4,0)<=Settings!$B$5,N(Settings!$C$22),N(Calc!$AH$56))) | BC10: =IF(OR(Settings!$A$22="",Settings!$F$22="Yes",OR(EOMONTH(BC$4,0)<=Settings!$B$5,BC$4>TODAY())),"",IF(EOMONTH(BB$4,0)<=Settings!$B$5,N(Settings!$C$22),N(Calc!$AH$57))) | BD10: =IF(OR(Settings!$A$22="",Settings!$F$22="Yes",OR(EOMONTH(BD$4,0)<=Settings!$B$5,BD$4>TODAY())),"",IF(EOMONTH(BC$4,0)<=Settings!$B$5,N(Settings!$C$22),N(Calc!$AH$58))) | BE10: =IF(OR(Settings!$A$22="",Settings!$F$22="Yes",OR(EOMONTH(BE$4,0)<=Settings!$B$5,BE$4>TODAY())),"",IF(EOMONTH(BD$4,0)<=Settings!$B$5,N(Settings!$C$22),N(Calc!$AH$59))) | BF10: =IF(OR(Settings!$A$22="",Settings!$F$22="Yes",OR(EOMONTH(BF$4,0)<=Settings!$B$5,BF$4>TODAY())),"",IF(EOMONTH(BE$4,0)<=Settings!$B$5,N(Settings!$C$22),N(Calc!$AH$60))) | BG10: =IF(OR(Settings!$A$22="",Settings!$F$22="Yes",OR(EOMONTH(BG$4,0)<=Settings!$B$5,BG$4>TODAY())),"",IF(EOMONTH(BF$4,0)<=Settings!$B$5,N(Settings!$C$22),N(Calc!$AH$61))) | BH10: =IF(OR(Settings!$A$22="",Settings!$F$22="Yes",OR(EOMONTH(BH$4,0)<=Settings!$B$5,BH$4>TODAY())),"",IF(EOMONTH(BG$4,0)<=Settings!$B$5,N(Settings!$C$22),N(Calc!$AH$62))) | BI10: =IF(OR(Settings!$A$22="",Settings!$F$22="Yes",OR(EOMONTH(BI$4,0)<=Settings!$B$5,BI$4>TODAY())),"",IF(EOMONTH(BH$4,0)<=Settings!$B$5,N(Settings!$C$22),N(Calc!$AH$63))) | BJ10: =IF(OR(Settings!$A$22="",Settings!$F$22="Yes",OR(EOMONTH(BJ$4,0)<=Settings!$B$5,BJ$4>TODAY())),"",IF(EOMONTH(BI$4,0)<=Settings!$B$5,N(Settings!$C$22),N(Calc!$AH$64))) | BK10: =IF(OR(Settings!$A$22="",Settings!$F$22="Yes",OR(EOMONTH(BK$4,0)<=Settings!$B$5,BK$4>TODAY())),"",IF(EOMONTH(BJ$4,0)<=Settings!$B$5,N(Settings!$C$22),N(Calc!$AH$65))) | BL10: =IF(OR(Settings!$A$22="",Settings!$F$22="Yes",OR(EOMONTH(BL$4,0)<=Settings!$B$5,BL$4>TODAY())),"",IF(EOMONTH(BK$4,0)<=Settings!$B$5,N(Settings!$C$22),N(Calc!$AH$66))) | BM10: =IF(OR(Settings!$A$22="",Settings!$F$22="Yes",OR(EOMONTH(BM$4,0)<=Settings!$B$5,BM$4>TODAY())),"",IF(EOMONTH(BL$4,0)<=Settings!$B$5,N(Settings!$C$22),N(Calc!$AH$67))) | BN10: =IF(OR(Settings!$A$22="",Settings!$F$22="Yes",OR(EOMONTH(BN$4,0)<=Settings!$B$5,BN$4>TODAY())),"",IF(EOMONTH(BM$4,0)<=Settings!$B$5,N(Settings!$C$22),N(Calc!$AH$68))) | BO10: =IF(OR(Settings!$A$22="",Settings!$F$22="Yes",OR(EOMONTH(BO$4,0)<=Settings!$B$5,BO$4>TODAY())),"",IF(EOMONTH(BN$4,0)<=Settings!$B$5,N(Settings!$C$22),N(Calc!$AH$69))) | BP10: =IF(OR(Settings!$A$22="",Settings!$F$22="Yes",OR(EOMONTH(BP$4,0)<=Settings!$B$5,BP$4>TODAY())),"",IF(EOMONTH(BO$4,0)<=Settings!$B$5,N(Settings!$C$22),N(Calc!$AH$70))) | BQ10: =IF(OR(Settings!$A$22="",Settings!$F$22="Yes",OR(EOMONTH(BQ$4,0)<=Settings!$B$5,BQ$4>TODAY())),"",IF(EOMONTH(BP$4,0)<=Settings!$B$5,N(Settings!$C$22),N(Calc!$AH$71))) | BR10: =IF(OR(Settings!$A$22="",Settings!$F$22="Yes",OR(EOMONTH(BR$4,0)<=Settings!$B$5,BR$4>TODAY())),"",IF(EOMONTH(BQ$4,0)<=Settings!$B$5,N(Settings!$C$22),N(Calc!$AH$72))) | BS10: =IF(OR(Settings!$A$22="",Settings!$F$22="Yes",OR(EOMONTH(BS$4,0)<=Settings!$B$5,BS$4>TODAY())),"",IF(EOMONTH(BR$4,0)<=Settings!$B$5,N(Settings!$C$22),N(Calc!$AH$73))) | BT10: =IF(OR(Settings!$A$22="",Settings!$F$22="Yes",OR(EOMONTH(BT$4,0)<=Settings!$B$5,BT$4>TODAY())),"",IF(EOMONTH(BS$4,0)<=Settings!$B$5,N(Settings!$C$22),N(Calc!$AH$74))) | BU10: =IF(OR(Settings!$A$22="",Settings!$F$22="Yes",OR(EOMONTH(BU$4,0)<=Settings!$B$5,BU$4>TODAY())),"",IF(EOMONTH(BT$4,0)<=Settings!$B$5,N(Settings!$C$22),N(Calc!$AH$75))) | BV10: =IF(OR(Settings!$A$22="",Settings!$F$22="Yes",OR(EOMONTH(BV$4,0)<=Settings!$B$5,BV$4>TODAY())),"",IF(EOMONTH(BU$4,0)<=Settings!$B$5,N(Settings!$C$22),N(Calc!$AH$76))) | BW10: =IF(OR(Settings!$A$22="",Settings!$F$22="Yes",OR(EOMONTH(BW$4,0)<=Settings!$B$5,BW$4>TODAY())),"",IF(EOMONTH(BV$4,0)<=Settings!$B$5,N(Settings!$C$22),N(Calc!$AH$77))) | BX10: =IF(OR(Settings!$A$22="",Settings!$F$22="Yes",OR(EOMONTH(BX$4,0)<=Settings!$B$5,BX$4>TODAY())),"",IF(EOMONTH(BW$4,0)<=Settings!$B$5,N(Settings!$C$22),N(Calc!$AH$78))) | BY10: =IF(OR(Settings!$A$22="",Settings!$F$22="Yes",OR(EOMONTH(BY$4,0)<=Settings!$B$5,BY$4>TODAY())),"",IF(EOMONTH(BX$4,0)<=Settings!$B$5,N(Settings!$C$22),N(Calc!$AH$79))) | BZ10: =IF(OR(Settings!$A$22="",Settings!$F$22="Yes",OR(EOMONTH(BZ$4,0)<=Settings!$B$5,BZ$4>TODAY())),"",IF(EOMONTH(BY$4,0)<=Settings!$B$5,N(Settings!$C$22),N(Calc!$AH$80))) | CA10: =IF(OR(Settings!$A$22="",Settings!$F$22="Yes",OR(EOMONTH(CA$4,0)<=Settings!$B$5,CA$4>TODAY())),"",IF(EOMONTH(BZ$4,0)<=Settings!$B$5,N(Settings!$C$22),N(Calc!$AH$81))) | CB10: =IF(OR(Settings!$A$22="",Settings!$F$22="Yes",OR(EOMONTH(CB$4,0)<=Settings!$B$5,CB$4>TODAY())),"",IF(EOMONTH(CA$4,0)<=Settings!$B$5,N(Settings!$C$22),N(Calc!$AH$82))) | CC10: =IF(OR(Settings!$A$22="",Settings!$F$22="Yes",OR(EOMONTH(CC$4,0)<=Settings!$B$5,CC$4>TODAY())),"",IF(EOMONTH(CB$4,0)<=Settings!$B$5,N(Settings!$C$22),N(Calc!$AH$83))) | CD10: =IF(OR(Settings!$A$22="",Settings!$F$22="Yes",OR(EOMONTH(CD$4,0)<=Settings!$B$5,CD$4>TODAY())),"",IF(EOMONTH(CC$4,0)<=Settings!$B$5,N(Settings!$C$22),N(Calc!$AH$84))) | CE10: =IF(OR(Settings!$A$22="",Settings!$F$22="Yes",OR(EOMONTH(CE$4,0)<=Settings!$B$5,CE$4>TODAY())),"",IF(EOMONTH(CD$4,0)<=Settings!$B$5,N(Settings!$C$22),N(Calc!$AH$85))) | CF10: =IF(OR(Settings!$A$22="",Settings!$F$22="Yes",OR(EOMONTH(CF$4,0)<=Settings!$B$5,CF$4>TODAY())),"",IF(EOMONTH(CE$4,0)<=Settings!$B$5,N(Settings!$C$22),N(Calc!$AH$86))) | CG10: =IF(OR(Settings!$A$22="",Settings!$F$22="Yes",OR(EOMONTH(CG$4,0)<=Settings!$B$5,CG$4>TODAY())),"",IF(EOMONTH(CF$4,0)<=Settings!$B$5,N(Settings!$C$22),N(Calc!$AH$87))) | CH10: =IF(OR(Settings!$A$22="",Settings!$F$22="Yes",OR(EOMONTH(CH$4,0)<=Settings!$B$5,CH$4>TODAY())),"",IF(EOMONTH(CG$4,0)<=Settings!$B$5,N(Settings!$C$22),N(Calc!$AH$88))) | CI10: =IF(OR(Settings!$A$22="",Settings!$F$22="Yes",OR(EOMONTH(CI$4,0)<=Settings!$B$5,CI$4>TODAY())),"",IF(EOMONTH(CH$4,0)<=Settings!$B$5,N(Settings!$C$22),N(Calc!$AH$89))) | CJ10: =IF(OR(Settings!$A$22="",Settings!$F$22="Yes",OR(EOMONTH(CJ$4,0)<=Settings!$B$5,CJ$4>TODAY())),"",IF(EOMONTH(CI$4,0)<=Settings!$B$5,N(Settings!$C$22),N(Calc!$AH$90))) | CK10: =IF(OR(Settings!$A$22="",Settings!$F$22="Yes",OR(EOMONTH(CK$4,0)<=Settings!$B$5,CK$4>TODAY())),"",IF(EOMONTH(CJ$4,0)<=Settings!$B$5,N(Settings!$C$22),N(Calc!$AH$91))) | CL10: =IF(OR(Settings!$A$22="",Settings!$F$22="Yes",OR(EOMONTH(CL$4,0)<=Settings!$B$5,CL$4>TODAY())),"",IF(EOMONTH(CK$4,0)<=Settings!$B$5,N(Settings!$C$22),N(Calc!$AH$92))) | CM10: =IF(OR(Settings!$A$22="",Settings!$F$22="Yes",OR(EOMONTH(CM$4,0)<=Settings!$B$5,CM$4>TODAY())),"",IF(EOMONTH(CL$4,0)<=Settings!$B$5,N(Settings!$C$22),N(Calc!$AH$93))) | CN10: =IF(OR(Settings!$A$22="",Settings!$F$22="Yes",OR(EOMONTH(CN$4,0)<=Settings!$B$5,CN$4>TODAY())),"",IF(EOMONTH(CM$4,0)<=Settings!$B$5,N(Settings!$C$22),N(Calc!$AH$94))) | CO10: =IF(OR(Settings!$A$22="",Settings!$F$22="Yes",OR(EOMONTH(CO$4,0)<=Settings!$B$5,CO$4>TODAY())),"",IF(EOMONTH(CN$4,0)<=Settings!$B$5,N(Settings!$C$22),N(Calc!$AH$95))) | CP10: =IF(OR(Settings!$A$22="",Settings!$F$22="Yes",OR(EOMONTH(CP$4,0)<=Settings!$B$5,CP$4>TODAY())),"",IF(EOMONTH(CO$4,0)<=Settings!$B$5,N(Settings!$C$22),N(Calc!$AH$96))) | CQ10: =IF(OR(Settings!$A$22="",Settings!$F$22="Yes",OR(EOMONTH(CQ$4,0)<=Settings!$B$5,CQ$4>TODAY())),"",IF(EOMONTH(CP$4,0)<=Settings!$B$5,N(Settings!$C$22),N(Calc!$AH$97))) | CR10: =IF(OR(Settings!$A$22="",Settings!$F$22="Yes",OR(EOMONTH(CR$4,0)<=Settings!$B$5,CR$4>TODAY())),"",IF(EOMONTH(CQ$4,0)<=Settings!$B$5,N(Settings!$C$22),N(Calc!$AH$98))) | CS10: =IF(OR(Settings!$A$22="",Settings!$F$22="Yes",OR(EOMONTH(CS$4,0)<=Settings!$B$5,CS$4>TODAY())),"",IF(EOMONTH(CR$4,0)<=Settings!$B$5,N(Settings!$C$22),N(Calc!$AH$99))) | CT10: =IF(OR(Settings!$A$22="",Settings!$F$22="Yes",OR(EOMONTH(CT$4,0)<=Settings!$B$5,CT$4>TODAY())),"",IF(EOMONTH(CS$4,0)<=Settings!$B$5,N(Settings!$C$22),N(Calc!$AH$100))) | CU10: =IF(OR(Settings!$A$22="",Settings!$F$22="Yes",OR(EOMONTH(CU$4,0)<=Settings!$B$5,CU$4>TODAY())),"",IF(EOMONTH(CT$4,0)<=Settings!$B$5,N(Settings!$C$22),N(Calc!$AH$101))) | CV10: =IF(OR(Settings!$A$22="",Settings!$F$22="Yes",OR(EOMONTH(CV$4,0)<=Settings!$B$5,CV$4>TODAY())),"",IF(EOMONTH(CU$4,0)<=Settings!$B$5,N(Settings!$C$22),N(Calc!$AH$102))) | CW10: =IF(OR(Settings!$A$22="",Settings!$F$22="Yes",OR(EOMONTH(CW$4,0)<=Settings!$B$5,CW$4>TODAY())),"",IF(EOMONTH(CV$4,0)<=Settings!$B$5,N(Settings!$C$22),N(Calc!$AH$103))) | CX10: =IF(OR(Settings!$A$22="",Settings!$F$22="Yes",OR(EOMONTH(CX$4,0)<=Settings!$B$5,CX$4>TODAY())),"",IF(EOMONTH(CW$4,0)<=Settings!$B$5,N(Settings!$C$22),N(Calc!$AH$104))) | CY10: =IF(OR(Settings!$A$22="",Settings!$F$22="Yes",OR(EOMONTH(CY$4,0)<=Settings!$B$5,CY$4>TODAY())),"",IF(EOMONTH(CX$4,0)<=Settings!$B$5,N(Settings!$C$22),N(Calc!$AH$105))) | CZ10: =IF(OR(Settings!$A$22="",Settings!$F$22="Yes",OR(EOMONTH(CZ$4,0)<=Settings!$B$5,CZ$4>TODAY())),"",IF(EOMONTH(CY$4,0)<=Settings!$B$5,N(Settings!$C$22),N(Calc!$AH$106))) | DA10: =IF(OR(Settings!$A$22="",Settings!$F$22="Yes",OR(EOMONTH(DA$4,0)<=Settings!$B$5,DA$4>TODAY())),"",IF(EOMONTH(CZ$4,0)<=Settings!$B$5,N(Settings!$C$22),N(Calc!$AH$107))) | DB10: =IF(OR(Settings!$A$22="",Settings!$F$22="Yes",OR(EOMONTH(DB$4,0)<=Settings!$B$5,DB$4>TODAY())),"",IF(EOMONTH(DA$4,0)<=Settings!$B$5,N(Settings!$C$22),N(Calc!$AH$108))) | DC10: =IF(OR(Settings!$A$22="",Settings!$F$22="Yes",OR(EOMONTH(DC$4,0)<=Settings!$B$5,DC$4>TODAY())),"",IF(EOMONTH(DB$4,0)<=Settings!$B$5,N(Settings!$C$22),N(Calc!$AH$109))) | DD10: =IF(OR(Settings!$A$22="",Settings!$F$22="Yes",OR(EOMONTH(DD$4,0)<=Settings!$B$5,DD$4>TODAY())),"",IF(EOMONTH(DC$4,0)<=Settings!$B$5,N(Settings!$C$22),N(Calc!$AH$110))) | DE10: =IF(OR(Settings!$A$22="",Settings!$F$22="Yes",OR(EOMONTH(DE$4,0)<=Settings!$B$5,DE$4>TODAY())),"",IF(EOMONTH(DD$4,0)<=Settings!$B$5,N(Settings!$C$22),N(Calc!$AH$111))) | DF10: =IF(OR(Settings!$A$22="",Settings!$F$22="Yes",OR(EOMONTH(DF$4,0)<=Settings!$B$5,DF$4>TODAY())),"",IF(EOMONTH(DE$4,0)<=Settings!$B$5,N(Settings!$C$22),N(Calc!$AH$112))) | DG10: =IF(OR(Settings!$A$22="",Settings!$F$22="Yes",OR(EOMONTH(DG$4,0)<=Settings!$B$5,DG$4>TODAY())),"",IF(EOMONTH(DF$4,0)<=Settings!$B$5,N(Settings!$C$22),N(Calc!$AH$113))) | DH10: =IF(OR(Settings!$A$22="",Settings!$F$22="Yes",OR(EOMONTH(DH$4,0)<=Settings!$B$5,DH$4>TODAY())),"",IF(EOMONTH(DG$4,0)<=Settings!$B$5,N(Settings!$C$22),N(Calc!$AH$114))) | DI10: =IF(OR(Settings!$A$22="",Settings!$F$22="Yes",OR(EOMONTH(DI$4,0)<=Settings!$B$5,DI$4>TODAY())),"",IF(EOMONTH(DH$4,0)<=Settings!$B$5,N(Settings!$C$22),N(Calc!$AH$115))) | DJ10: =IF(OR(Settings!$A$22="",Settings!$F$22="Yes",OR(EOMONTH(DJ$4,0)<=Settings!$B$5,DJ$4>TODAY())),"",IF(EOMONTH(DI$4,0)<=Settings!$B$5,N(Settings!$C$22),N(Calc!$AH$116))) | DK10: =IF(OR(Settings!$A$22="",Settings!$F$22="Yes",OR(EOMONTH(DK$4,0)<=Settings!$B$5,DK$4>TODAY())),"",IF(EOMONTH(DJ$4,0)<=Settings!$B$5,N(Settings!$C$22),N(Calc!$AH$117))) | DL10: =IF(OR(Settings!$A$22="",Settings!$F$22="Yes",OR(EOMONTH(DL$4,0)<=Settings!$B$5,DL$4>TODAY())),"",IF(EOMONTH(DK$4,0)<=Settings!$B$5,N(Settings!$C$22),N(Calc!$AH$118))) | DM10: =IF(OR(Settings!$A$22="",Settings!$F$22="Yes",OR(EOMONTH(DM$4,0)<=Settings!$B$5,DM$4>TODAY())),"",IF(EOMONTH(DL$4,0)<=Settings!$B$5,N(Settings!$C$22),N(Calc!$AH$119))) | DN10: =IF(OR(Settings!$A$22="",Settings!$F$22="Yes",OR(EOMONTH(DN$4,0)<=Settings!$B$5,DN$4>TODAY())),"",IF(EOMONTH(DM$4,0)<=Settings!$B$5,N(Settings!$C$22),N(Calc!$AH$120))) | DO10: =IF(OR(Settings!$A$22="",Settings!$F$22="Yes",OR(EOMONTH(DO$4,0)<=Settings!$B$5,DO$4>TODAY())),"",IF(EOMONTH(DN$4,0)<=Settings!$B$5,N(Settings!$C$22),N(Calc!$AH$121))) | DP10: =IF(OR(Settings!$A$22="",Settings!$F$22="Yes",OR(EOMONTH(DP$4,0)<=Settings!$B$5,DP$4>TODAY())),"",IF(EOMONTH(DO$4,0)<=Settings!$B$5,N(Settings!$C$22),N(Calc!$AH$122))) | DQ10: =IF(OR(Settings!$A$22="",Settings!$F$22="Yes",OR(EOMONTH(DQ$4,0)<=Settings!$B$5,DQ$4>TODAY())),"",IF(EOMONTH(DP$4,0)<=Settings!$B$5,N(Settings!$C$22),N(Calc!$AH$123))) | DR10: =IF(OR(Settings!$A$22="",Settings!$F$22="Yes",OR(EOMONTH(DR$4,0)<=Settings!$B$5,DR$4>TODAY())),"",IF(EOMONTH(DQ$4,0)<=Settings!$B$5,N(Settings!$C$22),N(Calc!$AH$124))) | DS10: =IF(OR(Settings!$A$22="",Settings!$F$22="Yes",OR(EOMONTH(DS$4,0)<=Settings!$B$5,DS$4>TODAY())),"",IF(EOMONTH(DR$4,0)<=Settings!$B$5,N(Settings!$C$22),N(Calc!$AH$125))) | DT10: =IF(OR(Settings!$A$22="",Settings!$F$22="Yes",OR(EOMONTH(DT$4,0)<=Settings!$B$5,DT$4>TODAY())),"",IF(EOMONTH(DS$4,0)<=Settings!$B$5,N(Settings!$C$22),N(Calc!$AH$126))) | DU10: =IF(OR(Settings!$A$22="",Settings!$F$22="Yes",OR(EOMONTH(DU$4,0)<=Settings!$B$5,DU$4>TODAY())),"",IF(EOMONTH(DT$4,0)<=Settings!$B$5,N(Settings!$C$22),N(Calc!$AH$127))) | DV10: =IF(OR(Settings!$A$22="",Settings!$F$22="Yes",OR(EOMONTH(DV$4,0)<=Settings!$B$5,DV$4>TODAY())),"",IF(EOMONTH(DU$4,0)<=Settings!$B$5,N(Settings!$C$22),N(Calc!$AH$128))) | DW10: =IF(OR(Settings!$A$22="",Settings!$F$22="Yes",OR(EOMONTH(DW$4,0)<=Settings!$B$5,DW$4>TODAY())),"",IF(EOMONTH(DV$4,0)<=Settings!$B$5,N(Settings!$C$22),N(Calc!$AH$129))) | DX10: =IF(OR(Settings!$A$22="",Settings!$F$22="Yes",OR(EOMONTH(DX$4,0)<=Settings!$B$5,DX$4>TODAY())),"",IF(EOMONTH(DW$4,0)<=Settings!$B$5,N(Settings!$C$22),N(Calc!$AH$130))) | DY10: =IF(OR(Settings!$A$22="",Settings!$F$22="Yes",OR(EOMONTH(DY$4,0)<=Settings!$B$5,DY$4>TODAY())),"",IF(EOMONTH(DX$4,0)<=Settings!$B$5,N(Settings!$C$22),N(Calc!$AH$131))) | DZ10: =IF(OR(Settings!$A$22="",Settings!$F$22="Yes",OR(EOMONTH(DZ$4,0)<=Settings!$B$5,DZ$4>TODAY())),"",IF(EOMONTH(DY$4,0)<=Settings!$B$5,N(Settings!$C$22),N(Calc!$AH$132))) | EA10: =IF(OR(Settings!$A$22="",Settings!$F$22="Yes",OR(EOMONTH(EA$4,0)<=Settings!$B$5,EA$4>TODAY())),"",IF(EOMONTH(DZ$4,0)<=Settings!$B$5,N(Settings!$C$22),N(Calc!$AH$133))) | EB10: =IF(OR(Settings!$A$22="",Settings!$F$22="Yes",OR(EOMONTH(EB$4,0)<=Settings!$B$5,EB$4>TODAY())),"",IF(EOMONTH(EA$4,0)<=Settings!$B$5,N(Settings!$C$22),N(Calc!$AH$134))) | EC10: =IF(OR(Settings!$A$22="",Settings!$F$22="Yes",OR(EOMONTH(EC$4,0)<=Settings!$B$5,EC$4>TODAY())),"",IF(EOMONTH(EB$4,0)<=Settings!$B$5,N(Settings!$C$22),N(Calc!$AH$135))) | ED10: =IF(OR(Settings!$A$22="",Settings!$F$22="Yes",OR(EOMONTH(ED$4,0)<=Settings!$B$5,ED$4>TODAY())),"",IF(EOMONTH(EC$4,0)<=Settings!$B$5,N(Settings!$C$22),N(Calc!$AH$136))) | EE10: =IF(OR(Settings!$A$22="",Settings!$F$22="Yes",OR(EOMONTH(EE$4,0)<=Settings!$B$5,EE$4>TODAY())),"",IF(EOMONTH(ED$4,0)<=Settings!$B$5,N(Settings!$C$22),N(Calc!$AH$137))) | EF10: =IF(OR(Settings!$A$22="",Settings!$F$22="Yes",OR(EOMONTH(EF$4,0)<=Settings!$B$5,EF$4>TODAY())),"",IF(EOMONTH(EE$4,0)<=Settings!$B$5,N(Settings!$C$22),N(Calc!$AH$138))) | EG10: =IF(OR(Settings!$A$22="",Settings!$F$22="Yes",OR(EOMONTH(EG$4,0)<=Settings!$B$5,EG$4>TODAY())),"",IF(EOMONTH(EF$4,0)<=Settings!$B$5,N(Settings!$C$22),N(Calc!$AH$139))) | EH10: =IF(OR(Settings!$A$22="",Settings!$F$22="Yes",OR(EOMONTH(EH$4,0)<=Settings!$B$5,EH$4>TODAY())),"",IF(EOMONTH(EG$4,0)<=Settings!$B$5,N(Settings!$C$22),N(Calc!$AH$140))) | EI10: =IF(OR(Settings!$A$22="",Settings!$F$22="Yes",OR(EOMONTH(EI$4,0)<=Settings!$B$5,EI$4>TODAY())),"",IF(EOMONTH(EH$4,0)<=Settings!$B$5,N(Settings!$C$22),N(Calc!$AH$141))) | EJ10: =IF(OR(Settings!$A$22="",Settings!$F$22="Yes",OR(EOMONTH(EJ$4,0)<=Settings!$B$5,EJ$4>TODAY())),"",IF(EOMONTH(EI$4,0)<=Settings!$B$5,N(Settings!$C$22),N(Calc!$AH$142))) | EK10: =IF(OR(Settings!$A$22="",Settings!$F$22="Yes",OR(EOMONTH(EK$4,0)<=Settings!$B$5,EK$4>TODAY())),"",IF(EOMONTH(EJ$4,0)<=Settings!$B$5,N(Settings!$C$22),N(Calc!$AH$143))) | EL10: =IF(OR(Settings!$A$22="",Settings!$F$22="Yes",OR(EOMONTH(EL$4,0)<=Settings!$B$5,EL$4>TODAY())),"",IF(EOMONTH(EK$4,0)<=Settings!$B$5,N(Settings!$C$22),N(Calc!$AH$144))) | EM10: =IF(OR(Settings!$A$22="",Settings!$F$22="Yes",OR(EOMONTH(EM$4,0)<=Settings!$B$5,EM$4>TODAY())),"",IF(EOMONTH(EL$4,0)<=Settings!$B$5,N(Settings!$C$22),N(Calc!$AH$145))) | EN10: =IF(OR(Settings!$A$22="",Settings!$F$22="Yes",OR(EOMONTH(EN$4,0)<=Settings!$B$5,EN$4>TODAY())),"",IF(EOMONTH(EM$4,0)<=Settings!$B$5,N(Settings!$C$22),N(Calc!$AH$146))) | EO10: =IF(OR(Settings!$A$22="",Settings!$F$22="Yes",OR(EOMONTH(EO$4,0)<=Settings!$B$5,EO$4>TODAY())),"",IF(EOMONTH(EN$4,0)<=Settings!$B$5,N(Settings!$C$22),N(Calc!$AH$147))) | EP10: =IF(OR(Settings!$A$22="",Settings!$F$22="Yes",OR(EOMONTH(EP$4,0)<=Settings!$B$5,EP$4>TODAY())),"",IF(EOMONTH(EO$4,0)<=Settings!$B$5,N(Settings!$C$22),N(Calc!$AH$148))) | EQ10: =IF(OR(Settings!$A$22="",Settings!$F$22="Yes",OR(EOMONTH(EQ$4,0)<=Settings!$B$5,EQ$4>TODAY())),"",IF(EOMONTH(EP$4,0)<=Settings!$B$5,N(Settings!$C$22),N(Calc!$AH$149))) | ER10: =IF(OR(Settings!$A$22="",Settings!$F$22="Yes",OR(EOMONTH(ER$4,0)<=Settings!$B$5,ER$4>TODAY())),"",IF(EOMONTH(EQ$4,0)<=Settings!$B$5,N(Settings!$C$22),N(Calc!$AH$150))) | ES10: =IF(OR(Settings!$A$22="",Settings!$F$22="Yes",OR(EOMONTH(ES$4,0)<=Settings!$B$5,ES$4>TODAY())),"",IF(EOMONTH(ER$4,0)<=Settings!$B$5,N(Settings!$C$22),N(Calc!$AH$151))) | ET10: =IF(OR(Settings!$A$22="",Settings!$F$22="Yes",OR(EOMONTH(ET$4,0)<=Settings!$B$5,ET$4>TODAY())),"",IF(EOMONTH(ES$4,0)<=Settings!$B$5,N(Settings!$C$22),N(Calc!$AH$152))) | EU10: =IF(OR(Settings!$A$22="",Settings!$F$22="Yes",OR(EOMONTH(EU$4,0)<=Settings!$B$5,EU$4>TODAY())),"",IF(EOMONTH(ET$4,0)<=Settings!$B$5,N(Settings!$C$22),N(Calc!$AH$153))) | EV10: =IF(OR(Settings!$A$22="",Settings!$F$22="Yes",OR(EOMONTH(EV$4,0)<=Settings!$B$5,EV$4>TODAY())),"",IF(EOMONTH(EU$4,0)<=Settings!$B$5,N(Settings!$C$22),N(Calc!$AH$154))) | EW10: =IF(OR(Settings!$A$22="",Settings!$F$22="Yes",OR(EOMONTH(EW$4,0)<=Settings!$B$5,EW$4>TODAY())),"",IF(EOMONTH(EV$4,0)<=Settings!$B$5,N(Settings!$C$22),N(Calc!$AH$155))) | EX10: =IF(OR(Settings!$A$22="",Settings!$F$22="Yes",OR(EOMONTH(EX$4,0)<=Settings!$B$5,EX$4>TODAY())),"",IF(EOMONTH(EW$4,0)<=Settings!$B$5,N(Settings!$C$22),N(Calc!$AH$156))) | EY10: =IF(OR(Settings!$A$22="",Settings!$F$22="Yes",OR(EOMONTH(EY$4,0)<=Settings!$B$5,EY$4>TODAY())),"",IF(EOMONTH(EX$4,0)<=Settings!$B$5,N(Settings!$C$22),N(Calc!$AH$157))) | EZ10: =IF(OR(Settings!$A$22="",Settings!$F$22="Yes",OR(EOMONTH(EZ$4,0)<=Settings!$B$5,EZ$4>TODAY())),"",IF(EOMONTH(EY$4,0)<=Settings!$B$5,N(Settings!$C$22),N(Calc!$AH$158))) | FA10: =IF(OR(Settings!$A$22="",Settings!$F$22="Yes",OR(EOMONTH(FA$4,0)<=Settings!$B$5,FA$4>TODAY())),"",IF(EOMONTH(EZ$4,0)<=Settings!$B$5,N(Settings!$C$22),N(Calc!$AH$159))) | FB10: =IF(OR(Settings!$A$22="",Settings!$F$22="Yes",OR(EOMONTH(FB$4,0)<=Settings!$B$5,FB$4>TODAY())),"",IF(EOMONTH(FA$4,0)<=Settings!$B$5,N(Settings!$C$22),N(Calc!$AH$160))) | FC10: =IF(OR(Settings!$A$22="",Settings!$F$22="Yes",OR(EOMONTH(FC$4,0)<=Settings!$B$5,FC$4>TODAY())),"",IF(EOMONTH(FB$4,0)<=Settings!$B$5,N(Settings!$C$22),N(Calc!$AH$161))) | FD10: =IF(OR(Settings!$A$22="",Settings!$F$22="Yes",OR(EOMONTH(FD$4,0)<=Settings!$B$5,FD$4>TODAY())),"",IF(EOMONTH(FC$4,0)<=Settings!$B$5,N(Settings!$C$22),N(Calc!$AH$162))) | FE10: =IF(OR(Settings!$A$22="",Settings!$F$22="Yes",OR(EOMONTH(FE$4,0)<=Settings!$B$5,FE$4>TODAY())),"",IF(EOMONTH(FD$4,0)<=Settings!$B$5,N(Settings!$C$22),N(Calc!$AH$163))) | FF10: =IF(OR(Settings!$A$22="",Settings!$F$22="Yes",OR(EOMONTH(FF$4,0)<=Settings!$B$5,FF$4>TODAY())),"",IF(EOMONTH(FE$4,0)<=Settings!$B$5,N(Settings!$C$22),N(Calc!$AH$164))) | FG10: =IF(OR(Settings!$A$22="",Settings!$F$22="Yes",OR(EOMONTH(FG$4,0)<=Settings!$B$5,FG$4>TODAY())),"",IF(EOMONTH(FF$4,0)<=Settings!$B$5,N(Settings!$C$22),N(Calc!$AH$165))) | FH10: =IF(OR(Settings!$A$22="",Settings!$F$22="Yes",OR(EOMONTH(FH$4,0)<=Settings!$B$5,FH$4>TODAY())),"",IF(EOMONTH(FG$4,0)<=Settings!$B$5,N(Settings!$C$22),N(Calc!$AH$166))) | FI10: =IF(OR(Settings!$A$22="",Settings!$F$22="Yes",OR(EOMONTH(FI$4,0)<=Settings!$B$5,FI$4>TODAY())),"",IF(EOMONTH(FH$4,0)<=Settings!$B$5,N(Settings!$C$22),N(Calc!$AH$167))) | FJ10: =IF(OR(Settings!$A$22="",Settings!$F$22="Yes",OR(EOMONTH(FJ$4,0)<=Settings!$B$5,FJ$4>TODAY())),"",IF(EOMONTH(FI$4,0)<=Settings!$B$5,N(Settings!$C$22),N(Calc!$AH$168))) | FK10: =IF(OR(Settings!$A$22="",Settings!$F$22="Yes",OR(EOMONTH(FK$4,0)<=Settings!$B$5,FK$4>TODAY())),"",IF(EOMONTH(FJ$4,0)<=Settings!$B$5,N(Settings!$C$22),N(Calc!$AH$169))) | FL10: =IF(OR(Settings!$A$22="",Settings!$F$22="Yes",OR(EOMONTH(FL$4,0)<=Settings!$B$5,FL$4>TODAY())),"",IF(EOMONTH(FK$4,0)<=Settings!$B$5,N(Settings!$C$22),N(Calc!$AH$170))) | FM10: =IF(OR(Settings!$A$22="",Settings!$F$22="Yes",OR(EOMONTH(FM$4,0)<=Settings!$B$5,FM$4>TODAY())),"",IF(EOMONTH(FL$4,0)<=Settings!$B$5,N(Settings!$C$22),N(Calc!$AH$171))) | FN10: =IF(OR(Settings!$A$22="",Settings!$F$22="Yes",OR(EOMONTH(FN$4,0)<=Settings!$B$5,FN$4>TODAY())),"",IF(EOMONTH(FM$4,0)<=Settings!$B$5,N(Settings!$C$22),N(Calc!$AH$172))) | FO10: =IF(OR(Settings!$A$22="",Settings!$F$22="Yes",OR(EOMONTH(FO$4,0)<=Settings!$B$5,FO$4>TODAY())),"",IF(EOMONTH(FN$4,0)<=Settings!$B$5,N(Settings!$C$22),N(Calc!$AH$173))) | FP10: =IF(OR(Settings!$A$22="",Settings!$F$22="Yes",OR(EOMONTH(FP$4,0)<=Settings!$B$5,FP$4>TODAY())),"",IF(EOMONTH(FO$4,0)<=Settings!$B$5,N(Settings!$C$22),N(Calc!$AH$174))) | FQ10: =IF(OR(Settings!$A$22="",Settings!$F$22="Yes",OR(EOMONTH(FQ$4,0)<=Settings!$B$5,FQ$4>TODAY())),"",IF(EOMONTH(FP$4,0)<=Settings!$B$5,N(Settings!$C$22),N(Calc!$AH$175))) | FR10: =IF(OR(Settings!$A$22="",Settings!$F$22="Yes",OR(EOMONTH(FR$4,0)<=Settings!$B$5,FR$4>TODAY())),"",IF(EOMONTH(FQ$4,0)<=Settings!$B$5,N(Settings!$C$22),N(Calc!$AH$176))) | FS10: =IF(OR(Settings!$A$22="",Settings!$F$22="Yes",OR(EOMONTH(FS$4,0)<=Settings!$B$5,FS$4>TODAY())),"",IF(EOMONTH(FR$4,0)<=Settings!$B$5,N(Settings!$C$22),N(Calc!$AH$177))) | FT10: =IF(OR(Settings!$A$22="",Settings!$F$22="Yes",OR(EOMONTH(FT$4,0)<=Settings!$B$5,FT$4>TODAY())),"",IF(EOMONTH(FS$4,0)<=Settings!$B$5,N(Settings!$C$22),N(Calc!$AH$178))) | FU10: =IF(OR(Settings!$A$22="",Settings!$F$22="Yes",OR(EOMONTH(FU$4,0)<=Settings!$B$5,FU$4>TODAY())),"",IF(EOMONTH(FT$4,0)<=Settings!$B$5,N(Settings!$C$22),N(Calc!$AH$179))) | FV10: =IF(OR(Settings!$A$22="",Settings!$F$22="Yes",OR(EOMONTH(FV$4,0)<=Settings!$B$5,FV$4>TODAY())),"",IF(EOMONTH(FU$4,0)<=Settings!$B$5,N(Settings!$C$22),N(Calc!$AH$180))) | FW10: =IF(OR(Settings!$A$22="",Settings!$F$22="Yes",OR(EOMONTH(FW$4,0)<=Settings!$B$5,FW$4>TODAY())),"",IF(EOMONTH(FV$4,0)<=Settings!$B$5,N(Settings!$C$22),N(Calc!$AH$181))) | FX10: =IF(OR(Settings!$A$22="",Settings!$F$22="Yes",OR(EOMONTH(FX$4,0)<=Settings!$B$5,FX$4>TODAY())),"",IF(EOMONTH(FW$4,0)<=Settings!$B$5,N(Settings!$C$22),N(Calc!$AH$182)))
A11: =IF(Settings!$A$23="","(unused)",Settings!$A$23&IF(Settings!$E$23="No"," (retired)","")) | B11: =IF(Settings!$A$23="","",IF(Settings!$F$23="Yes","REQUIRED","optional · grey = unchanged")&IF(OR(Settings!$B$23="Card",Settings!$B$23="Loan")," · amount owed","")) | C11: =IF(OR(Settings!$A$23="",Settings!$F$23="Yes",OR(EOMONTH(C$4,0)<=Settings!$B$5,C$4>TODAY())),"",N(Settings!$C$23)) | D11: =IF(OR(Settings!$A$23="",Settings!$F$23="Yes",OR(EOMONTH(D$4,0)<=Settings!$B$5,D$4>TODAY())),"",IF(EOMONTH(C$4,0)<=Settings!$B$5,N(Settings!$C$23),N(Calc!$AI$6))) | E11: =IF(OR(Settings!$A$23="",Settings!$F$23="Yes",OR(EOMONTH(E$4,0)<=Settings!$B$5,E$4>TODAY())),"",IF(EOMONTH(D$4,0)<=Settings!$B$5,N(Settings!$C$23),N(Calc!$AI$7))) | F11: =IF(OR(Settings!$A$23="",Settings!$F$23="Yes",OR(EOMONTH(F$4,0)<=Settings!$B$5,F$4>TODAY())),"",IF(EOMONTH(E$4,0)<=Settings!$B$5,N(Settings!$C$23),N(Calc!$AI$8))) | G11: =IF(OR(Settings!$A$23="",Settings!$F$23="Yes",OR(EOMONTH(G$4,0)<=Settings!$B$5,G$4>TODAY())),"",IF(EOMONTH(F$4,0)<=Settings!$B$5,N(Settings!$C$23),N(Calc!$AI$9))) | H11: =IF(OR(Settings!$A$23="",Settings!$F$23="Yes",OR(EOMONTH(H$4,0)<=Settings!$B$5,H$4>TODAY())),"",IF(EOMONTH(G$4,0)<=Settings!$B$5,N(Settings!$C$23),N(Calc!$AI$10))) | I11: =IF(OR(Settings!$A$23="",Settings!$F$23="Yes",OR(EOMONTH(I$4,0)<=Settings!$B$5,I$4>TODAY())),"",IF(EOMONTH(H$4,0)<=Settings!$B$5,N(Settings!$C$23),N(Calc!$AI$11))) | J11: =IF(OR(Settings!$A$23="",Settings!$F$23="Yes",OR(EOMONTH(J$4,0)<=Settings!$B$5,J$4>TODAY())),"",IF(EOMONTH(I$4,0)<=Settings!$B$5,N(Settings!$C$23),N(Calc!$AI$12))) | K11: =IF(OR(Settings!$A$23="",Settings!$F$23="Yes",OR(EOMONTH(K$4,0)<=Settings!$B$5,K$4>TODAY())),"",IF(EOMONTH(J$4,0)<=Settings!$B$5,N(Settings!$C$23),N(Calc!$AI$13))) | L11: =IF(OR(Settings!$A$23="",Settings!$F$23="Yes",OR(EOMONTH(L$4,0)<=Settings!$B$5,L$4>TODAY())),"",IF(EOMONTH(K$4,0)<=Settings!$B$5,N(Settings!$C$23),N(Calc!$AI$14))) | M11: =IF(OR(Settings!$A$23="",Settings!$F$23="Yes",OR(EOMONTH(M$4,0)<=Settings!$B$5,M$4>TODAY())),"",IF(EOMONTH(L$4,0)<=Settings!$B$5,N(Settings!$C$23),N(Calc!$AI$15))) | N11: =IF(OR(Settings!$A$23="",Settings!$F$23="Yes",OR(EOMONTH(N$4,0)<=Settings!$B$5,N$4>TODAY())),"",IF(EOMONTH(M$4,0)<=Settings!$B$5,N(Settings!$C$23),N(Calc!$AI$16))) | O11: =IF(OR(Settings!$A$23="",Settings!$F$23="Yes",OR(EOMONTH(O$4,0)<=Settings!$B$5,O$4>TODAY())),"",IF(EOMONTH(N$4,0)<=Settings!$B$5,N(Settings!$C$23),N(Calc!$AI$17))) | P11: =IF(OR(Settings!$A$23="",Settings!$F$23="Yes",OR(EOMONTH(P$4,0)<=Settings!$B$5,P$4>TODAY())),"",IF(EOMONTH(O$4,0)<=Settings!$B$5,N(Settings!$C$23),N(Calc!$AI$18))) | Q11: =IF(OR(Settings!$A$23="",Settings!$F$23="Yes",OR(EOMONTH(Q$4,0)<=Settings!$B$5,Q$4>TODAY())),"",IF(EOMONTH(P$4,0)<=Settings!$B$5,N(Settings!$C$23),N(Calc!$AI$19))) | R11: =IF(OR(Settings!$A$23="",Settings!$F$23="Yes",OR(EOMONTH(R$4,0)<=Settings!$B$5,R$4>TODAY())),"",IF(EOMONTH(Q$4,0)<=Settings!$B$5,N(Settings!$C$23),N(Calc!$AI$20))) | S11: =IF(OR(Settings!$A$23="",Settings!$F$23="Yes",OR(EOMONTH(S$4,0)<=Settings!$B$5,S$4>TODAY())),"",IF(EOMONTH(R$4,0)<=Settings!$B$5,N(Settings!$C$23),N(Calc!$AI$21))) | T11: =IF(OR(Settings!$A$23="",Settings!$F$23="Yes",OR(EOMONTH(T$4,0)<=Settings!$B$5,T$4>TODAY())),"",IF(EOMONTH(S$4,0)<=Settings!$B$5,N(Settings!$C$23),N(Calc!$AI$22))) | U11: =IF(OR(Settings!$A$23="",Settings!$F$23="Yes",OR(EOMONTH(U$4,0)<=Settings!$B$5,U$4>TODAY())),"",IF(EOMONTH(T$4,0)<=Settings!$B$5,N(Settings!$C$23),N(Calc!$AI$23))) | V11: =IF(OR(Settings!$A$23="",Settings!$F$23="Yes",OR(EOMONTH(V$4,0)<=Settings!$B$5,V$4>TODAY())),"",IF(EOMONTH(U$4,0)<=Settings!$B$5,N(Settings!$C$23),N(Calc!$AI$24))) | W11: =IF(OR(Settings!$A$23="",Settings!$F$23="Yes",OR(EOMONTH(W$4,0)<=Settings!$B$5,W$4>TODAY())),"",IF(EOMONTH(V$4,0)<=Settings!$B$5,N(Settings!$C$23),N(Calc!$AI$25))) | X11: =IF(OR(Settings!$A$23="",Settings!$F$23="Yes",OR(EOMONTH(X$4,0)<=Settings!$B$5,X$4>TODAY())),"",IF(EOMONTH(W$4,0)<=Settings!$B$5,N(Settings!$C$23),N(Calc!$AI$26))) | Y11: =IF(OR(Settings!$A$23="",Settings!$F$23="Yes",OR(EOMONTH(Y$4,0)<=Settings!$B$5,Y$4>TODAY())),"",IF(EOMONTH(X$4,0)<=Settings!$B$5,N(Settings!$C$23),N(Calc!$AI$27))) | Z11: =IF(OR(Settings!$A$23="",Settings!$F$23="Yes",OR(EOMONTH(Z$4,0)<=Settings!$B$5,Z$4>TODAY())),"",IF(EOMONTH(Y$4,0)<=Settings!$B$5,N(Settings!$C$23),N(Calc!$AI$28))) | AA11: =IF(OR(Settings!$A$23="",Settings!$F$23="Yes",OR(EOMONTH(AA$4,0)<=Settings!$B$5,AA$4>TODAY())),"",IF(EOMONTH(Z$4,0)<=Settings!$B$5,N(Settings!$C$23),N(Calc!$AI$29))) | AB11: =IF(OR(Settings!$A$23="",Settings!$F$23="Yes",OR(EOMONTH(AB$4,0)<=Settings!$B$5,AB$4>TODAY())),"",IF(EOMONTH(AA$4,0)<=Settings!$B$5,N(Settings!$C$23),N(Calc!$AI$30))) | AC11: =IF(OR(Settings!$A$23="",Settings!$F$23="Yes",OR(EOMONTH(AC$4,0)<=Settings!$B$5,AC$4>TODAY())),"",IF(EOMONTH(AB$4,0)<=Settings!$B$5,N(Settings!$C$23),N(Calc!$AI$31))) | AD11: =IF(OR(Settings!$A$23="",Settings!$F$23="Yes",OR(EOMONTH(AD$4,0)<=Settings!$B$5,AD$4>TODAY())),"",IF(EOMONTH(AC$4,0)<=Settings!$B$5,N(Settings!$C$23),N(Calc!$AI$32))) | AE11: =IF(OR(Settings!$A$23="",Settings!$F$23="Yes",OR(EOMONTH(AE$4,0)<=Settings!$B$5,AE$4>TODAY())),"",IF(EOMONTH(AD$4,0)<=Settings!$B$5,N(Settings!$C$23),N(Calc!$AI$33))) | AF11: =IF(OR(Settings!$A$23="",Settings!$F$23="Yes",OR(EOMONTH(AF$4,0)<=Settings!$B$5,AF$4>TODAY())),"",IF(EOMONTH(AE$4,0)<=Settings!$B$5,N(Settings!$C$23),N(Calc!$AI$34))) | AG11: =IF(OR(Settings!$A$23="",Settings!$F$23="Yes",OR(EOMONTH(AG$4,0)<=Settings!$B$5,AG$4>TODAY())),"",IF(EOMONTH(AF$4,0)<=Settings!$B$5,N(Settings!$C$23),N(Calc!$AI$35))) | AH11: =IF(OR(Settings!$A$23="",Settings!$F$23="Yes",OR(EOMONTH(AH$4,0)<=Settings!$B$5,AH$4>TODAY())),"",IF(EOMONTH(AG$4,0)<=Settings!$B$5,N(Settings!$C$23),N(Calc!$AI$36))) | AI11: =IF(OR(Settings!$A$23="",Settings!$F$23="Yes",OR(EOMONTH(AI$4,0)<=Settings!$B$5,AI$4>TODAY())),"",IF(EOMONTH(AH$4,0)<=Settings!$B$5,N(Settings!$C$23),N(Calc!$AI$37))) | AJ11: =IF(OR(Settings!$A$23="",Settings!$F$23="Yes",OR(EOMONTH(AJ$4,0)<=Settings!$B$5,AJ$4>TODAY())),"",IF(EOMONTH(AI$4,0)<=Settings!$B$5,N(Settings!$C$23),N(Calc!$AI$38))) | AK11: =IF(OR(Settings!$A$23="",Settings!$F$23="Yes",OR(EOMONTH(AK$4,0)<=Settings!$B$5,AK$4>TODAY())),"",IF(EOMONTH(AJ$4,0)<=Settings!$B$5,N(Settings!$C$23),N(Calc!$AI$39))) | AL11: =IF(OR(Settings!$A$23="",Settings!$F$23="Yes",OR(EOMONTH(AL$4,0)<=Settings!$B$5,AL$4>TODAY())),"",IF(EOMONTH(AK$4,0)<=Settings!$B$5,N(Settings!$C$23),N(Calc!$AI$40))) | AM11: =IF(OR(Settings!$A$23="",Settings!$F$23="Yes",OR(EOMONTH(AM$4,0)<=Settings!$B$5,AM$4>TODAY())),"",IF(EOMONTH(AL$4,0)<=Settings!$B$5,N(Settings!$C$23),N(Calc!$AI$41))) | AN11: =IF(OR(Settings!$A$23="",Settings!$F$23="Yes",OR(EOMONTH(AN$4,0)<=Settings!$B$5,AN$4>TODAY())),"",IF(EOMONTH(AM$4,0)<=Settings!$B$5,N(Settings!$C$23),N(Calc!$AI$42))) | AO11: =IF(OR(Settings!$A$23="",Settings!$F$23="Yes",OR(EOMONTH(AO$4,0)<=Settings!$B$5,AO$4>TODAY())),"",IF(EOMONTH(AN$4,0)<=Settings!$B$5,N(Settings!$C$23),N(Calc!$AI$43))) | AP11: =IF(OR(Settings!$A$23="",Settings!$F$23="Yes",OR(EOMONTH(AP$4,0)<=Settings!$B$5,AP$4>TODAY())),"",IF(EOMONTH(AO$4,0)<=Settings!$B$5,N(Settings!$C$23),N(Calc!$AI$44))) | AQ11: =IF(OR(Settings!$A$23="",Settings!$F$23="Yes",OR(EOMONTH(AQ$4,0)<=Settings!$B$5,AQ$4>TODAY())),"",IF(EOMONTH(AP$4,0)<=Settings!$B$5,N(Settings!$C$23),N(Calc!$AI$45))) | AR11: =IF(OR(Settings!$A$23="",Settings!$F$23="Yes",OR(EOMONTH(AR$4,0)<=Settings!$B$5,AR$4>TODAY())),"",IF(EOMONTH(AQ$4,0)<=Settings!$B$5,N(Settings!$C$23),N(Calc!$AI$46))) | AS11: =IF(OR(Settings!$A$23="",Settings!$F$23="Yes",OR(EOMONTH(AS$4,0)<=Settings!$B$5,AS$4>TODAY())),"",IF(EOMONTH(AR$4,0)<=Settings!$B$5,N(Settings!$C$23),N(Calc!$AI$47))) | AT11: =IF(OR(Settings!$A$23="",Settings!$F$23="Yes",OR(EOMONTH(AT$4,0)<=Settings!$B$5,AT$4>TODAY())),"",IF(EOMONTH(AS$4,0)<=Settings!$B$5,N(Settings!$C$23),N(Calc!$AI$48))) | AU11: =IF(OR(Settings!$A$23="",Settings!$F$23="Yes",OR(EOMONTH(AU$4,0)<=Settings!$B$5,AU$4>TODAY())),"",IF(EOMONTH(AT$4,0)<=Settings!$B$5,N(Settings!$C$23),N(Calc!$AI$49))) | AV11: =IF(OR(Settings!$A$23="",Settings!$F$23="Yes",OR(EOMONTH(AV$4,0)<=Settings!$B$5,AV$4>TODAY())),"",IF(EOMONTH(AU$4,0)<=Settings!$B$5,N(Settings!$C$23),N(Calc!$AI$50))) | AW11: =IF(OR(Settings!$A$23="",Settings!$F$23="Yes",OR(EOMONTH(AW$4,0)<=Settings!$B$5,AW$4>TODAY())),"",IF(EOMONTH(AV$4,0)<=Settings!$B$5,N(Settings!$C$23),N(Calc!$AI$51))) | AX11: =IF(OR(Settings!$A$23="",Settings!$F$23="Yes",OR(EOMONTH(AX$4,0)<=Settings!$B$5,AX$4>TODAY())),"",IF(EOMONTH(AW$4,0)<=Settings!$B$5,N(Settings!$C$23),N(Calc!$AI$52))) | AY11: =IF(OR(Settings!$A$23="",Settings!$F$23="Yes",OR(EOMONTH(AY$4,0)<=Settings!$B$5,AY$4>TODAY())),"",IF(EOMONTH(AX$4,0)<=Settings!$B$5,N(Settings!$C$23),N(Calc!$AI$53))) | AZ11: =IF(OR(Settings!$A$23="",Settings!$F$23="Yes",OR(EOMONTH(AZ$4,0)<=Settings!$B$5,AZ$4>TODAY())),"",IF(EOMONTH(AY$4,0)<=Settings!$B$5,N(Settings!$C$23),N(Calc!$AI$54))) | BA11: =IF(OR(Settings!$A$23="",Settings!$F$23="Yes",OR(EOMONTH(BA$4,0)<=Settings!$B$5,BA$4>TODAY())),"",IF(EOMONTH(AZ$4,0)<=Settings!$B$5,N(Settings!$C$23),N(Calc!$AI$55))) | BB11: =IF(OR(Settings!$A$23="",Settings!$F$23="Yes",OR(EOMONTH(BB$4,0)<=Settings!$B$5,BB$4>TODAY())),"",IF(EOMONTH(BA$4,0)<=Settings!$B$5,N(Settings!$C$23),N(Calc!$AI$56))) | BC11: =IF(OR(Settings!$A$23="",Settings!$F$23="Yes",OR(EOMONTH(BC$4,0)<=Settings!$B$5,BC$4>TODAY())),"",IF(EOMONTH(BB$4,0)<=Settings!$B$5,N(Settings!$C$23),N(Calc!$AI$57))) | BD11: =IF(OR(Settings!$A$23="",Settings!$F$23="Yes",OR(EOMONTH(BD$4,0)<=Settings!$B$5,BD$4>TODAY())),"",IF(EOMONTH(BC$4,0)<=Settings!$B$5,N(Settings!$C$23),N(Calc!$AI$58))) | BE11: =IF(OR(Settings!$A$23="",Settings!$F$23="Yes",OR(EOMONTH(BE$4,0)<=Settings!$B$5,BE$4>TODAY())),"",IF(EOMONTH(BD$4,0)<=Settings!$B$5,N(Settings!$C$23),N(Calc!$AI$59))) | BF11: =IF(OR(Settings!$A$23="",Settings!$F$23="Yes",OR(EOMONTH(BF$4,0)<=Settings!$B$5,BF$4>TODAY())),"",IF(EOMONTH(BE$4,0)<=Settings!$B$5,N(Settings!$C$23),N(Calc!$AI$60))) | BG11: =IF(OR(Settings!$A$23="",Settings!$F$23="Yes",OR(EOMONTH(BG$4,0)<=Settings!$B$5,BG$4>TODAY())),"",IF(EOMONTH(BF$4,0)<=Settings!$B$5,N(Settings!$C$23),N(Calc!$AI$61))) | BH11: =IF(OR(Settings!$A$23="",Settings!$F$23="Yes",OR(EOMONTH(BH$4,0)<=Settings!$B$5,BH$4>TODAY())),"",IF(EOMONTH(BG$4,0)<=Settings!$B$5,N(Settings!$C$23),N(Calc!$AI$62))) | BI11: =IF(OR(Settings!$A$23="",Settings!$F$23="Yes",OR(EOMONTH(BI$4,0)<=Settings!$B$5,BI$4>TODAY())),"",IF(EOMONTH(BH$4,0)<=Settings!$B$5,N(Settings!$C$23),N(Calc!$AI$63))) | BJ11: =IF(OR(Settings!$A$23="",Settings!$F$23="Yes",OR(EOMONTH(BJ$4,0)<=Settings!$B$5,BJ$4>TODAY())),"",IF(EOMONTH(BI$4,0)<=Settings!$B$5,N(Settings!$C$23),N(Calc!$AI$64))) | BK11: =IF(OR(Settings!$A$23="",Settings!$F$23="Yes",OR(EOMONTH(BK$4,0)<=Settings!$B$5,BK$4>TODAY())),"",IF(EOMONTH(BJ$4,0)<=Settings!$B$5,N(Settings!$C$23),N(Calc!$AI$65))) | BL11: =IF(OR(Settings!$A$23="",Settings!$F$23="Yes",OR(EOMONTH(BL$4,0)<=Settings!$B$5,BL$4>TODAY())),"",IF(EOMONTH(BK$4,0)<=Settings!$B$5,N(Settings!$C$23),N(Calc!$AI$66))) | BM11: =IF(OR(Settings!$A$23="",Settings!$F$23="Yes",OR(EOMONTH(BM$4,0)<=Settings!$B$5,BM$4>TODAY())),"",IF(EOMONTH(BL$4,0)<=Settings!$B$5,N(Settings!$C$23),N(Calc!$AI$67))) | BN11: =IF(OR(Settings!$A$23="",Settings!$F$23="Yes",OR(EOMONTH(BN$4,0)<=Settings!$B$5,BN$4>TODAY())),"",IF(EOMONTH(BM$4,0)<=Settings!$B$5,N(Settings!$C$23),N(Calc!$AI$68))) | BO11: =IF(OR(Settings!$A$23="",Settings!$F$23="Yes",OR(EOMONTH(BO$4,0)<=Settings!$B$5,BO$4>TODAY())),"",IF(EOMONTH(BN$4,0)<=Settings!$B$5,N(Settings!$C$23),N(Calc!$AI$69))) | BP11: =IF(OR(Settings!$A$23="",Settings!$F$23="Yes",OR(EOMONTH(BP$4,0)<=Settings!$B$5,BP$4>TODAY())),"",IF(EOMONTH(BO$4,0)<=Settings!$B$5,N(Settings!$C$23),N(Calc!$AI$70))) | BQ11: =IF(OR(Settings!$A$23="",Settings!$F$23="Yes",OR(EOMONTH(BQ$4,0)<=Settings!$B$5,BQ$4>TODAY())),"",IF(EOMONTH(BP$4,0)<=Settings!$B$5,N(Settings!$C$23),N(Calc!$AI$71))) | BR11: =IF(OR(Settings!$A$23="",Settings!$F$23="Yes",OR(EOMONTH(BR$4,0)<=Settings!$B$5,BR$4>TODAY())),"",IF(EOMONTH(BQ$4,0)<=Settings!$B$5,N(Settings!$C$23),N(Calc!$AI$72))) | BS11: =IF(OR(Settings!$A$23="",Settings!$F$23="Yes",OR(EOMONTH(BS$4,0)<=Settings!$B$5,BS$4>TODAY())),"",IF(EOMONTH(BR$4,0)<=Settings!$B$5,N(Settings!$C$23),N(Calc!$AI$73))) | BT11: =IF(OR(Settings!$A$23="",Settings!$F$23="Yes",OR(EOMONTH(BT$4,0)<=Settings!$B$5,BT$4>TODAY())),"",IF(EOMONTH(BS$4,0)<=Settings!$B$5,N(Settings!$C$23),N(Calc!$AI$74))) | BU11: =IF(OR(Settings!$A$23="",Settings!$F$23="Yes",OR(EOMONTH(BU$4,0)<=Settings!$B$5,BU$4>TODAY())),"",IF(EOMONTH(BT$4,0)<=Settings!$B$5,N(Settings!$C$23),N(Calc!$AI$75))) | BV11: =IF(OR(Settings!$A$23="",Settings!$F$23="Yes",OR(EOMONTH(BV$4,0)<=Settings!$B$5,BV$4>TODAY())),"",IF(EOMONTH(BU$4,0)<=Settings!$B$5,N(Settings!$C$23),N(Calc!$AI$76))) | BW11: =IF(OR(Settings!$A$23="",Settings!$F$23="Yes",OR(EOMONTH(BW$4,0)<=Settings!$B$5,BW$4>TODAY())),"",IF(EOMONTH(BV$4,0)<=Settings!$B$5,N(Settings!$C$23),N(Calc!$AI$77))) | BX11: =IF(OR(Settings!$A$23="",Settings!$F$23="Yes",OR(EOMONTH(BX$4,0)<=Settings!$B$5,BX$4>TODAY())),"",IF(EOMONTH(BW$4,0)<=Settings!$B$5,N(Settings!$C$23),N(Calc!$AI$78))) | BY11: =IF(OR(Settings!$A$23="",Settings!$F$23="Yes",OR(EOMONTH(BY$4,0)<=Settings!$B$5,BY$4>TODAY())),"",IF(EOMONTH(BX$4,0)<=Settings!$B$5,N(Settings!$C$23),N(Calc!$AI$79))) | BZ11: =IF(OR(Settings!$A$23="",Settings!$F$23="Yes",OR(EOMONTH(BZ$4,0)<=Settings!$B$5,BZ$4>TODAY())),"",IF(EOMONTH(BY$4,0)<=Settings!$B$5,N(Settings!$C$23),N(Calc!$AI$80))) | CA11: =IF(OR(Settings!$A$23="",Settings!$F$23="Yes",OR(EOMONTH(CA$4,0)<=Settings!$B$5,CA$4>TODAY())),"",IF(EOMONTH(BZ$4,0)<=Settings!$B$5,N(Settings!$C$23),N(Calc!$AI$81))) | CB11: =IF(OR(Settings!$A$23="",Settings!$F$23="Yes",OR(EOMONTH(CB$4,0)<=Settings!$B$5,CB$4>TODAY())),"",IF(EOMONTH(CA$4,0)<=Settings!$B$5,N(Settings!$C$23),N(Calc!$AI$82))) | CC11: =IF(OR(Settings!$A$23="",Settings!$F$23="Yes",OR(EOMONTH(CC$4,0)<=Settings!$B$5,CC$4>TODAY())),"",IF(EOMONTH(CB$4,0)<=Settings!$B$5,N(Settings!$C$23),N(Calc!$AI$83))) | CD11: =IF(OR(Settings!$A$23="",Settings!$F$23="Yes",OR(EOMONTH(CD$4,0)<=Settings!$B$5,CD$4>TODAY())),"",IF(EOMONTH(CC$4,0)<=Settings!$B$5,N(Settings!$C$23),N(Calc!$AI$84))) | CE11: =IF(OR(Settings!$A$23="",Settings!$F$23="Yes",OR(EOMONTH(CE$4,0)<=Settings!$B$5,CE$4>TODAY())),"",IF(EOMONTH(CD$4,0)<=Settings!$B$5,N(Settings!$C$23),N(Calc!$AI$85))) | CF11: =IF(OR(Settings!$A$23="",Settings!$F$23="Yes",OR(EOMONTH(CF$4,0)<=Settings!$B$5,CF$4>TODAY())),"",IF(EOMONTH(CE$4,0)<=Settings!$B$5,N(Settings!$C$23),N(Calc!$AI$86))) | CG11: =IF(OR(Settings!$A$23="",Settings!$F$23="Yes",OR(EOMONTH(CG$4,0)<=Settings!$B$5,CG$4>TODAY())),"",IF(EOMONTH(CF$4,0)<=Settings!$B$5,N(Settings!$C$23),N(Calc!$AI$87))) | CH11: =IF(OR(Settings!$A$23="",Settings!$F$23="Yes",OR(EOMONTH(CH$4,0)<=Settings!$B$5,CH$4>TODAY())),"",IF(EOMONTH(CG$4,0)<=Settings!$B$5,N(Settings!$C$23),N(Calc!$AI$88))) | CI11: =IF(OR(Settings!$A$23="",Settings!$F$23="Yes",OR(EOMONTH(CI$4,0)<=Settings!$B$5,CI$4>TODAY())),"",IF(EOMONTH(CH$4,0)<=Settings!$B$5,N(Settings!$C$23),N(Calc!$AI$89))) | CJ11: =IF(OR(Settings!$A$23="",Settings!$F$23="Yes",OR(EOMONTH(CJ$4,0)<=Settings!$B$5,CJ$4>TODAY())),"",IF(EOMONTH(CI$4,0)<=Settings!$B$5,N(Settings!$C$23),N(Calc!$AI$90))) | CK11: =IF(OR(Settings!$A$23="",Settings!$F$23="Yes",OR(EOMONTH(CK$4,0)<=Settings!$B$5,CK$4>TODAY())),"",IF(EOMONTH(CJ$4,0)<=Settings!$B$5,N(Settings!$C$23),N(Calc!$AI$91))) | CL11: =IF(OR(Settings!$A$23="",Settings!$F$23="Yes",OR(EOMONTH(CL$4,0)<=Settings!$B$5,CL$4>TODAY())),"",IF(EOMONTH(CK$4,0)<=Settings!$B$5,N(Settings!$C$23),N(Calc!$AI$92))) | CM11: =IF(OR(Settings!$A$23="",Settings!$F$23="Yes",OR(EOMONTH(CM$4,0)<=Settings!$B$5,CM$4>TODAY())),"",IF(EOMONTH(CL$4,0)<=Settings!$B$5,N(Settings!$C$23),N(Calc!$AI$93))) | CN11: =IF(OR(Settings!$A$23="",Settings!$F$23="Yes",OR(EOMONTH(CN$4,0)<=Settings!$B$5,CN$4>TODAY())),"",IF(EOMONTH(CM$4,0)<=Settings!$B$5,N(Settings!$C$23),N(Calc!$AI$94))) | CO11: =IF(OR(Settings!$A$23="",Settings!$F$23="Yes",OR(EOMONTH(CO$4,0)<=Settings!$B$5,CO$4>TODAY())),"",IF(EOMONTH(CN$4,0)<=Settings!$B$5,N(Settings!$C$23),N(Calc!$AI$95))) | CP11: =IF(OR(Settings!$A$23="",Settings!$F$23="Yes",OR(EOMONTH(CP$4,0)<=Settings!$B$5,CP$4>TODAY())),"",IF(EOMONTH(CO$4,0)<=Settings!$B$5,N(Settings!$C$23),N(Calc!$AI$96))) | CQ11: =IF(OR(Settings!$A$23="",Settings!$F$23="Yes",OR(EOMONTH(CQ$4,0)<=Settings!$B$5,CQ$4>TODAY())),"",IF(EOMONTH(CP$4,0)<=Settings!$B$5,N(Settings!$C$23),N(Calc!$AI$97))) | CR11: =IF(OR(Settings!$A$23="",Settings!$F$23="Yes",OR(EOMONTH(CR$4,0)<=Settings!$B$5,CR$4>TODAY())),"",IF(EOMONTH(CQ$4,0)<=Settings!$B$5,N(Settings!$C$23),N(Calc!$AI$98))) | CS11: =IF(OR(Settings!$A$23="",Settings!$F$23="Yes",OR(EOMONTH(CS$4,0)<=Settings!$B$5,CS$4>TODAY())),"",IF(EOMONTH(CR$4,0)<=Settings!$B$5,N(Settings!$C$23),N(Calc!$AI$99))) | CT11: =IF(OR(Settings!$A$23="",Settings!$F$23="Yes",OR(EOMONTH(CT$4,0)<=Settings!$B$5,CT$4>TODAY())),"",IF(EOMONTH(CS$4,0)<=Settings!$B$5,N(Settings!$C$23),N(Calc!$AI$100))) | CU11: =IF(OR(Settings!$A$23="",Settings!$F$23="Yes",OR(EOMONTH(CU$4,0)<=Settings!$B$5,CU$4>TODAY())),"",IF(EOMONTH(CT$4,0)<=Settings!$B$5,N(Settings!$C$23),N(Calc!$AI$101))) | CV11: =IF(OR(Settings!$A$23="",Settings!$F$23="Yes",OR(EOMONTH(CV$4,0)<=Settings!$B$5,CV$4>TODAY())),"",IF(EOMONTH(CU$4,0)<=Settings!$B$5,N(Settings!$C$23),N(Calc!$AI$102))) | CW11: =IF(OR(Settings!$A$23="",Settings!$F$23="Yes",OR(EOMONTH(CW$4,0)<=Settings!$B$5,CW$4>TODAY())),"",IF(EOMONTH(CV$4,0)<=Settings!$B$5,N(Settings!$C$23),N(Calc!$AI$103))) | CX11: =IF(OR(Settings!$A$23="",Settings!$F$23="Yes",OR(EOMONTH(CX$4,0)<=Settings!$B$5,CX$4>TODAY())),"",IF(EOMONTH(CW$4,0)<=Settings!$B$5,N(Settings!$C$23),N(Calc!$AI$104))) | CY11: =IF(OR(Settings!$A$23="",Settings!$F$23="Yes",OR(EOMONTH(CY$4,0)<=Settings!$B$5,CY$4>TODAY())),"",IF(EOMONTH(CX$4,0)<=Settings!$B$5,N(Settings!$C$23),N(Calc!$AI$105))) | CZ11: =IF(OR(Settings!$A$23="",Settings!$F$23="Yes",OR(EOMONTH(CZ$4,0)<=Settings!$B$5,CZ$4>TODAY())),"",IF(EOMONTH(CY$4,0)<=Settings!$B$5,N(Settings!$C$23),N(Calc!$AI$106))) | DA11: =IF(OR(Settings!$A$23="",Settings!$F$23="Yes",OR(EOMONTH(DA$4,0)<=Settings!$B$5,DA$4>TODAY())),"",IF(EOMONTH(CZ$4,0)<=Settings!$B$5,N(Settings!$C$23),N(Calc!$AI$107))) | DB11: =IF(OR(Settings!$A$23="",Settings!$F$23="Yes",OR(EOMONTH(DB$4,0)<=Settings!$B$5,DB$4>TODAY())),"",IF(EOMONTH(DA$4,0)<=Settings!$B$5,N(Settings!$C$23),N(Calc!$AI$108))) | DC11: =IF(OR(Settings!$A$23="",Settings!$F$23="Yes",OR(EOMONTH(DC$4,0)<=Settings!$B$5,DC$4>TODAY())),"",IF(EOMONTH(DB$4,0)<=Settings!$B$5,N(Settings!$C$23),N(Calc!$AI$109))) | DD11: =IF(OR(Settings!$A$23="",Settings!$F$23="Yes",OR(EOMONTH(DD$4,0)<=Settings!$B$5,DD$4>TODAY())),"",IF(EOMONTH(DC$4,0)<=Settings!$B$5,N(Settings!$C$23),N(Calc!$AI$110))) | DE11: =IF(OR(Settings!$A$23="",Settings!$F$23="Yes",OR(EOMONTH(DE$4,0)<=Settings!$B$5,DE$4>TODAY())),"",IF(EOMONTH(DD$4,0)<=Settings!$B$5,N(Settings!$C$23),N(Calc!$AI$111))) | DF11: =IF(OR(Settings!$A$23="",Settings!$F$23="Yes",OR(EOMONTH(DF$4,0)<=Settings!$B$5,DF$4>TODAY())),"",IF(EOMONTH(DE$4,0)<=Settings!$B$5,N(Settings!$C$23),N(Calc!$AI$112))) | DG11: =IF(OR(Settings!$A$23="",Settings!$F$23="Yes",OR(EOMONTH(DG$4,0)<=Settings!$B$5,DG$4>TODAY())),"",IF(EOMONTH(DF$4,0)<=Settings!$B$5,N(Settings!$C$23),N(Calc!$AI$113))) | DH11: =IF(OR(Settings!$A$23="",Settings!$F$23="Yes",OR(EOMONTH(DH$4,0)<=Settings!$B$5,DH$4>TODAY())),"",IF(EOMONTH(DG$4,0)<=Settings!$B$5,N(Settings!$C$23),N(Calc!$AI$114))) | DI11: =IF(OR(Settings!$A$23="",Settings!$F$23="Yes",OR(EOMONTH(DI$4,0)<=Settings!$B$5,DI$4>TODAY())),"",IF(EOMONTH(DH$4,0)<=Settings!$B$5,N(Settings!$C$23),N(Calc!$AI$115))) | DJ11: =IF(OR(Settings!$A$23="",Settings!$F$23="Yes",OR(EOMONTH(DJ$4,0)<=Settings!$B$5,DJ$4>TODAY())),"",IF(EOMONTH(DI$4,0)<=Settings!$B$5,N(Settings!$C$23),N(Calc!$AI$116))) | DK11: =IF(OR(Settings!$A$23="",Settings!$F$23="Yes",OR(EOMONTH(DK$4,0)<=Settings!$B$5,DK$4>TODAY())),"",IF(EOMONTH(DJ$4,0)<=Settings!$B$5,N(Settings!$C$23),N(Calc!$AI$117))) | DL11: =IF(OR(Settings!$A$23="",Settings!$F$23="Yes",OR(EOMONTH(DL$4,0)<=Settings!$B$5,DL$4>TODAY())),"",IF(EOMONTH(DK$4,0)<=Settings!$B$5,N(Settings!$C$23),N(Calc!$AI$118))) | DM11: =IF(OR(Settings!$A$23="",Settings!$F$23="Yes",OR(EOMONTH(DM$4,0)<=Settings!$B$5,DM$4>TODAY())),"",IF(EOMONTH(DL$4,0)<=Settings!$B$5,N(Settings!$C$23),N(Calc!$AI$119))) | DN11: =IF(OR(Settings!$A$23="",Settings!$F$23="Yes",OR(EOMONTH(DN$4,0)<=Settings!$B$5,DN$4>TODAY())),"",IF(EOMONTH(DM$4,0)<=Settings!$B$5,N(Settings!$C$23),N(Calc!$AI$120))) | DO11: =IF(OR(Settings!$A$23="",Settings!$F$23="Yes",OR(EOMONTH(DO$4,0)<=Settings!$B$5,DO$4>TODAY())),"",IF(EOMONTH(DN$4,0)<=Settings!$B$5,N(Settings!$C$23),N(Calc!$AI$121))) | DP11: =IF(OR(Settings!$A$23="",Settings!$F$23="Yes",OR(EOMONTH(DP$4,0)<=Settings!$B$5,DP$4>TODAY())),"",IF(EOMONTH(DO$4,0)<=Settings!$B$5,N(Settings!$C$23),N(Calc!$AI$122))) | DQ11: =IF(OR(Settings!$A$23="",Settings!$F$23="Yes",OR(EOMONTH(DQ$4,0)<=Settings!$B$5,DQ$4>TODAY())),"",IF(EOMONTH(DP$4,0)<=Settings!$B$5,N(Settings!$C$23),N(Calc!$AI$123))) | DR11: =IF(OR(Settings!$A$23="",Settings!$F$23="Yes",OR(EOMONTH(DR$4,0)<=Settings!$B$5,DR$4>TODAY())),"",IF(EOMONTH(DQ$4,0)<=Settings!$B$5,N(Settings!$C$23),N(Calc!$AI$124))) | DS11: =IF(OR(Settings!$A$23="",Settings!$F$23="Yes",OR(EOMONTH(DS$4,0)<=Settings!$B$5,DS$4>TODAY())),"",IF(EOMONTH(DR$4,0)<=Settings!$B$5,N(Settings!$C$23),N(Calc!$AI$125))) | DT11: =IF(OR(Settings!$A$23="",Settings!$F$23="Yes",OR(EOMONTH(DT$4,0)<=Settings!$B$5,DT$4>TODAY())),"",IF(EOMONTH(DS$4,0)<=Settings!$B$5,N(Settings!$C$23),N(Calc!$AI$126))) | DU11: =IF(OR(Settings!$A$23="",Settings!$F$23="Yes",OR(EOMONTH(DU$4,0)<=Settings!$B$5,DU$4>TODAY())),"",IF(EOMONTH(DT$4,0)<=Settings!$B$5,N(Settings!$C$23),N(Calc!$AI$127))) | DV11: =IF(OR(Settings!$A$23="",Settings!$F$23="Yes",OR(EOMONTH(DV$4,0)<=Settings!$B$5,DV$4>TODAY())),"",IF(EOMONTH(DU$4,0)<=Settings!$B$5,N(Settings!$C$23),N(Calc!$AI$128))) | DW11: =IF(OR(Settings!$A$23="",Settings!$F$23="Yes",OR(EOMONTH(DW$4,0)<=Settings!$B$5,DW$4>TODAY())),"",IF(EOMONTH(DV$4,0)<=Settings!$B$5,N(Settings!$C$23),N(Calc!$AI$129))) | DX11: =IF(OR(Settings!$A$23="",Settings!$F$23="Yes",OR(EOMONTH(DX$4,0)<=Settings!$B$5,DX$4>TODAY())),"",IF(EOMONTH(DW$4,0)<=Settings!$B$5,N(Settings!$C$23),N(Calc!$AI$130))) | DY11: =IF(OR(Settings!$A$23="",Settings!$F$23="Yes",OR(EOMONTH(DY$4,0)<=Settings!$B$5,DY$4>TODAY())),"",IF(EOMONTH(DX$4,0)<=Settings!$B$5,N(Settings!$C$23),N(Calc!$AI$131))) | DZ11: =IF(OR(Settings!$A$23="",Settings!$F$23="Yes",OR(EOMONTH(DZ$4,0)<=Settings!$B$5,DZ$4>TODAY())),"",IF(EOMONTH(DY$4,0)<=Settings!$B$5,N(Settings!$C$23),N(Calc!$AI$132))) | EA11: =IF(OR(Settings!$A$23="",Settings!$F$23="Yes",OR(EOMONTH(EA$4,0)<=Settings!$B$5,EA$4>TODAY())),"",IF(EOMONTH(DZ$4,0)<=Settings!$B$5,N(Settings!$C$23),N(Calc!$AI$133))) | EB11: =IF(OR(Settings!$A$23="",Settings!$F$23="Yes",OR(EOMONTH(EB$4,0)<=Settings!$B$5,EB$4>TODAY())),"",IF(EOMONTH(EA$4,0)<=Settings!$B$5,N(Settings!$C$23),N(Calc!$AI$134))) | EC11: =IF(OR(Settings!$A$23="",Settings!$F$23="Yes",OR(EOMONTH(EC$4,0)<=Settings!$B$5,EC$4>TODAY())),"",IF(EOMONTH(EB$4,0)<=Settings!$B$5,N(Settings!$C$23),N(Calc!$AI$135))) | ED11: =IF(OR(Settings!$A$23="",Settings!$F$23="Yes",OR(EOMONTH(ED$4,0)<=Settings!$B$5,ED$4>TODAY())),"",IF(EOMONTH(EC$4,0)<=Settings!$B$5,N(Settings!$C$23),N(Calc!$AI$136))) | EE11: =IF(OR(Settings!$A$23="",Settings!$F$23="Yes",OR(EOMONTH(EE$4,0)<=Settings!$B$5,EE$4>TODAY())),"",IF(EOMONTH(ED$4,0)<=Settings!$B$5,N(Settings!$C$23),N(Calc!$AI$137))) | EF11: =IF(OR(Settings!$A$23="",Settings!$F$23="Yes",OR(EOMONTH(EF$4,0)<=Settings!$B$5,EF$4>TODAY())),"",IF(EOMONTH(EE$4,0)<=Settings!$B$5,N(Settings!$C$23),N(Calc!$AI$138))) | EG11: =IF(OR(Settings!$A$23="",Settings!$F$23="Yes",OR(EOMONTH(EG$4,0)<=Settings!$B$5,EG$4>TODAY())),"",IF(EOMONTH(EF$4,0)<=Settings!$B$5,N(Settings!$C$23),N(Calc!$AI$139))) | EH11: =IF(OR(Settings!$A$23="",Settings!$F$23="Yes",OR(EOMONTH(EH$4,0)<=Settings!$B$5,EH$4>TODAY())),"",IF(EOMONTH(EG$4,0)<=Settings!$B$5,N(Settings!$C$23),N(Calc!$AI$140))) | EI11: =IF(OR(Settings!$A$23="",Settings!$F$23="Yes",OR(EOMONTH(EI$4,0)<=Settings!$B$5,EI$4>TODAY())),"",IF(EOMONTH(EH$4,0)<=Settings!$B$5,N(Settings!$C$23),N(Calc!$AI$141))) | EJ11: =IF(OR(Settings!$A$23="",Settings!$F$23="Yes",OR(EOMONTH(EJ$4,0)<=Settings!$B$5,EJ$4>TODAY())),"",IF(EOMONTH(EI$4,0)<=Settings!$B$5,N(Settings!$C$23),N(Calc!$AI$142))) | EK11: =IF(OR(Settings!$A$23="",Settings!$F$23="Yes",OR(EOMONTH(EK$4,0)<=Settings!$B$5,EK$4>TODAY())),"",IF(EOMONTH(EJ$4,0)<=Settings!$B$5,N(Settings!$C$23),N(Calc!$AI$143))) | EL11: =IF(OR(Settings!$A$23="",Settings!$F$23="Yes",OR(EOMONTH(EL$4,0)<=Settings!$B$5,EL$4>TODAY())),"",IF(EOMONTH(EK$4,0)<=Settings!$B$5,N(Settings!$C$23),N(Calc!$AI$144))) | EM11: =IF(OR(Settings!$A$23="",Settings!$F$23="Yes",OR(EOMONTH(EM$4,0)<=Settings!$B$5,EM$4>TODAY())),"",IF(EOMONTH(EL$4,0)<=Settings!$B$5,N(Settings!$C$23),N(Calc!$AI$145))) | EN11: =IF(OR(Settings!$A$23="",Settings!$F$23="Yes",OR(EOMONTH(EN$4,0)<=Settings!$B$5,EN$4>TODAY())),"",IF(EOMONTH(EM$4,0)<=Settings!$B$5,N(Settings!$C$23),N(Calc!$AI$146))) | EO11: =IF(OR(Settings!$A$23="",Settings!$F$23="Yes",OR(EOMONTH(EO$4,0)<=Settings!$B$5,EO$4>TODAY())),"",IF(EOMONTH(EN$4,0)<=Settings!$B$5,N(Settings!$C$23),N(Calc!$AI$147))) | EP11: =IF(OR(Settings!$A$23="",Settings!$F$23="Yes",OR(EOMONTH(EP$4,0)<=Settings!$B$5,EP$4>TODAY())),"",IF(EOMONTH(EO$4,0)<=Settings!$B$5,N(Settings!$C$23),N(Calc!$AI$148))) | EQ11: =IF(OR(Settings!$A$23="",Settings!$F$23="Yes",OR(EOMONTH(EQ$4,0)<=Settings!$B$5,EQ$4>TODAY())),"",IF(EOMONTH(EP$4,0)<=Settings!$B$5,N(Settings!$C$23),N(Calc!$AI$149))) | ER11: =IF(OR(Settings!$A$23="",Settings!$F$23="Yes",OR(EOMONTH(ER$4,0)<=Settings!$B$5,ER$4>TODAY())),"",IF(EOMONTH(EQ$4,0)<=Settings!$B$5,N(Settings!$C$23),N(Calc!$AI$150))) | ES11: =IF(OR(Settings!$A$23="",Settings!$F$23="Yes",OR(EOMONTH(ES$4,0)<=Settings!$B$5,ES$4>TODAY())),"",IF(EOMONTH(ER$4,0)<=Settings!$B$5,N(Settings!$C$23),N(Calc!$AI$151))) | ET11: =IF(OR(Settings!$A$23="",Settings!$F$23="Yes",OR(EOMONTH(ET$4,0)<=Settings!$B$5,ET$4>TODAY())),"",IF(EOMONTH(ES$4,0)<=Settings!$B$5,N(Settings!$C$23),N(Calc!$AI$152))) | EU11: =IF(OR(Settings!$A$23="",Settings!$F$23="Yes",OR(EOMONTH(EU$4,0)<=Settings!$B$5,EU$4>TODAY())),"",IF(EOMONTH(ET$4,0)<=Settings!$B$5,N(Settings!$C$23),N(Calc!$AI$153))) | EV11: =IF(OR(Settings!$A$23="",Settings!$F$23="Yes",OR(EOMONTH(EV$4,0)<=Settings!$B$5,EV$4>TODAY())),"",IF(EOMONTH(EU$4,0)<=Settings!$B$5,N(Settings!$C$23),N(Calc!$AI$154))) | EW11: =IF(OR(Settings!$A$23="",Settings!$F$23="Yes",OR(EOMONTH(EW$4,0)<=Settings!$B$5,EW$4>TODAY())),"",IF(EOMONTH(EV$4,0)<=Settings!$B$5,N(Settings!$C$23),N(Calc!$AI$155))) | EX11: =IF(OR(Settings!$A$23="",Settings!$F$23="Yes",OR(EOMONTH(EX$4,0)<=Settings!$B$5,EX$4>TODAY())),"",IF(EOMONTH(EW$4,0)<=Settings!$B$5,N(Settings!$C$23),N(Calc!$AI$156))) | EY11: =IF(OR(Settings!$A$23="",Settings!$F$23="Yes",OR(EOMONTH(EY$4,0)<=Settings!$B$5,EY$4>TODAY())),"",IF(EOMONTH(EX$4,0)<=Settings!$B$5,N(Settings!$C$23),N(Calc!$AI$157))) | EZ11: =IF(OR(Settings!$A$23="",Settings!$F$23="Yes",OR(EOMONTH(EZ$4,0)<=Settings!$B$5,EZ$4>TODAY())),"",IF(EOMONTH(EY$4,0)<=Settings!$B$5,N(Settings!$C$23),N(Calc!$AI$158))) | FA11: =IF(OR(Settings!$A$23="",Settings!$F$23="Yes",OR(EOMONTH(FA$4,0)<=Settings!$B$5,FA$4>TODAY())),"",IF(EOMONTH(EZ$4,0)<=Settings!$B$5,N(Settings!$C$23),N(Calc!$AI$159))) | FB11: =IF(OR(Settings!$A$23="",Settings!$F$23="Yes",OR(EOMONTH(FB$4,0)<=Settings!$B$5,FB$4>TODAY())),"",IF(EOMONTH(FA$4,0)<=Settings!$B$5,N(Settings!$C$23),N(Calc!$AI$160))) | FC11: =IF(OR(Settings!$A$23="",Settings!$F$23="Yes",OR(EOMONTH(FC$4,0)<=Settings!$B$5,FC$4>TODAY())),"",IF(EOMONTH(FB$4,0)<=Settings!$B$5,N(Settings!$C$23),N(Calc!$AI$161))) | FD11: =IF(OR(Settings!$A$23="",Settings!$F$23="Yes",OR(EOMONTH(FD$4,0)<=Settings!$B$5,FD$4>TODAY())),"",IF(EOMONTH(FC$4,0)<=Settings!$B$5,N(Settings!$C$23),N(Calc!$AI$162))) | FE11: =IF(OR(Settings!$A$23="",Settings!$F$23="Yes",OR(EOMONTH(FE$4,0)<=Settings!$B$5,FE$4>TODAY())),"",IF(EOMONTH(FD$4,0)<=Settings!$B$5,N(Settings!$C$23),N(Calc!$AI$163))) | FF11: =IF(OR(Settings!$A$23="",Settings!$F$23="Yes",OR(EOMONTH(FF$4,0)<=Settings!$B$5,FF$4>TODAY())),"",IF(EOMONTH(FE$4,0)<=Settings!$B$5,N(Settings!$C$23),N(Calc!$AI$164))) | FG11: =IF(OR(Settings!$A$23="",Settings!$F$23="Yes",OR(EOMONTH(FG$4,0)<=Settings!$B$5,FG$4>TODAY())),"",IF(EOMONTH(FF$4,0)<=Settings!$B$5,N(Settings!$C$23),N(Calc!$AI$165))) | FH11: =IF(OR(Settings!$A$23="",Settings!$F$23="Yes",OR(EOMONTH(FH$4,0)<=Settings!$B$5,FH$4>TODAY())),"",IF(EOMONTH(FG$4,0)<=Settings!$B$5,N(Settings!$C$23),N(Calc!$AI$166))) | FI11: =IF(OR(Settings!$A$23="",Settings!$F$23="Yes",OR(EOMONTH(FI$4,0)<=Settings!$B$5,FI$4>TODAY())),"",IF(EOMONTH(FH$4,0)<=Settings!$B$5,N(Settings!$C$23),N(Calc!$AI$167))) | FJ11: =IF(OR(Settings!$A$23="",Settings!$F$23="Yes",OR(EOMONTH(FJ$4,0)<=Settings!$B$5,FJ$4>TODAY())),"",IF(EOMONTH(FI$4,0)<=Settings!$B$5,N(Settings!$C$23),N(Calc!$AI$168))) | FK11: =IF(OR(Settings!$A$23="",Settings!$F$23="Yes",OR(EOMONTH(FK$4,0)<=Settings!$B$5,FK$4>TODAY())),"",IF(EOMONTH(FJ$4,0)<=Settings!$B$5,N(Settings!$C$23),N(Calc!$AI$169))) | FL11: =IF(OR(Settings!$A$23="",Settings!$F$23="Yes",OR(EOMONTH(FL$4,0)<=Settings!$B$5,FL$4>TODAY())),"",IF(EOMONTH(FK$4,0)<=Settings!$B$5,N(Settings!$C$23),N(Calc!$AI$170))) | FM11: =IF(OR(Settings!$A$23="",Settings!$F$23="Yes",OR(EOMONTH(FM$4,0)<=Settings!$B$5,FM$4>TODAY())),"",IF(EOMONTH(FL$4,0)<=Settings!$B$5,N(Settings!$C$23),N(Calc!$AI$171))) | FN11: =IF(OR(Settings!$A$23="",Settings!$F$23="Yes",OR(EOMONTH(FN$4,0)<=Settings!$B$5,FN$4>TODAY())),"",IF(EOMONTH(FM$4,0)<=Settings!$B$5,N(Settings!$C$23),N(Calc!$AI$172))) | FO11: =IF(OR(Settings!$A$23="",Settings!$F$23="Yes",OR(EOMONTH(FO$4,0)<=Settings!$B$5,FO$4>TODAY())),"",IF(EOMONTH(FN$4,0)<=Settings!$B$5,N(Settings!$C$23),N(Calc!$AI$173))) | FP11: =IF(OR(Settings!$A$23="",Settings!$F$23="Yes",OR(EOMONTH(FP$4,0)<=Settings!$B$5,FP$4>TODAY())),"",IF(EOMONTH(FO$4,0)<=Settings!$B$5,N(Settings!$C$23),N(Calc!$AI$174))) | FQ11: =IF(OR(Settings!$A$23="",Settings!$F$23="Yes",OR(EOMONTH(FQ$4,0)<=Settings!$B$5,FQ$4>TODAY())),"",IF(EOMONTH(FP$4,0)<=Settings!$B$5,N(Settings!$C$23),N(Calc!$AI$175))) | FR11: =IF(OR(Settings!$A$23="",Settings!$F$23="Yes",OR(EOMONTH(FR$4,0)<=Settings!$B$5,FR$4>TODAY())),"",IF(EOMONTH(FQ$4,0)<=Settings!$B$5,N(Settings!$C$23),N(Calc!$AI$176))) | FS11: =IF(OR(Settings!$A$23="",Settings!$F$23="Yes",OR(EOMONTH(FS$4,0)<=Settings!$B$5,FS$4>TODAY())),"",IF(EOMONTH(FR$4,0)<=Settings!$B$5,N(Settings!$C$23),N(Calc!$AI$177))) | FT11: =IF(OR(Settings!$A$23="",Settings!$F$23="Yes",OR(EOMONTH(FT$4,0)<=Settings!$B$5,FT$4>TODAY())),"",IF(EOMONTH(FS$4,0)<=Settings!$B$5,N(Settings!$C$23),N(Calc!$AI$178))) | FU11: =IF(OR(Settings!$A$23="",Settings!$F$23="Yes",OR(EOMONTH(FU$4,0)<=Settings!$B$5,FU$4>TODAY())),"",IF(EOMONTH(FT$4,0)<=Settings!$B$5,N(Settings!$C$23),N(Calc!$AI$179))) | FV11: =IF(OR(Settings!$A$23="",Settings!$F$23="Yes",OR(EOMONTH(FV$4,0)<=Settings!$B$5,FV$4>TODAY())),"",IF(EOMONTH(FU$4,0)<=Settings!$B$5,N(Settings!$C$23),N(Calc!$AI$180))) | FW11: =IF(OR(Settings!$A$23="",Settings!$F$23="Yes",OR(EOMONTH(FW$4,0)<=Settings!$B$5,FW$4>TODAY())),"",IF(EOMONTH(FV$4,0)<=Settings!$B$5,N(Settings!$C$23),N(Calc!$AI$181))) | FX11: =IF(OR(Settings!$A$23="",Settings!$F$23="Yes",OR(EOMONTH(FX$4,0)<=Settings!$B$5,FX$4>TODAY())),"",IF(EOMONTH(FW$4,0)<=Settings!$B$5,N(Settings!$C$23),N(Calc!$AI$182)))
